Workbook

Sheet ESF
B2: JELCOM SOLUCIONES EMPRESARIALES SAS
B3: NIT. 901360819
B4: ESTADO DE SITUACIÓN FINANCIERA A:
B5: (Cifras expresadas en pesos colombianos - M$)
B7: ACTIVO | D7: NOTA | F7: 31.01.2026 | H7: 31.12.2025 | I7: 30.11.2025 | J7: 31.10.2025 | K7: 30.09.2025 | L7: 31.08.2025 | M7: 31.07.2025 | N7: 30.06.2025 | O7: 31.05.2025 | P7: 30.04.2025 | Q7: 31.03.2025 | R7: 28.02.2025 | S7: 31.01.2025 | U7: 31.12.2024 | V7: 30.11.2024 | W7: 31.10.2024 | X7: 30.09.2024 | Y7: 31.08.2024 | Z7: 31.07.2024 | AA7: 30.06.2024 | AB7: 31.05.2024 | AC7: 30.04.2024 | AD7: 31.03.2024 | AE7: 29.02.2023 | AF7: 31.01.2024 | AH7: 31.12.2023 | AI7: 30.11.2023 | AJ7: 31.10.2023 | AK7: 30.09.2023 | AL7: 31.08.2023 | AM7: 30.07.2023 | AN7: 30.06.2023 | AO7: 31.05.2023 | AP7: 31.04.2023 | AQ7: 31.03.2023 | AR7: 28.02.2023 | AS7: 31.01.2023 | AU7: 31.12.2022 | AV7: 30.11.2022 | AW7: 31.10.2022 | AX7: 30.09.2022 | AY7: 31.08.2022 | AZ7: 31.07.2022 | BA7: 30.06.2022 | BB7: 31.05.2022 | BC7: 31.04.2022 | BD7: 31.03.2022 | BE7: 28.02.2022 | BF7: 31.01.2022 | BH7: 31.12.2021 | BI7: 30.09.2021 | BJ7: 30.08.2021 | BK7: 30.07.2021 | BL7: 30.06.2021 | BM7: 01.05.2021 | BO7: 31.12.2020
B9: Corriente
B10: Efectivo y Equivalentes al Efectivo | D10: 4 | F10: =+'NOTAS ESF'!B10 -> 26352599 | H10: =+'NOTAS ESF'!D10 -> 65794723 | I10: =+'NOTAS ESF'!E10 -> 29244298 | J10: =+'NOTAS ESF'!F10 -> 21098136 | K10: =+'NOTAS ESF'!G10 -> 14529916 | L10: =+'NOTAS ESF'!H10 -> 10355964 | M10: =+'NOTAS ESF'!I10 -> 11927408 | N10: =+'NOTAS ESF'!J10 -> 5739207.5 | O10: =+'NOTAS ESF'!K10 -> 16777658 | ... S10: =+'NOTAS ESF'!O10 -> 7199659.9 | U10: =+'NOTAS ESF'!Q10 -> 5382680.7 | V10: =+'NOTAS ESF'!R10 -> 5032561 | W10: =+'NOTAS ESF'!S10 -> 4883116.8 | X10: =+'NOTAS ESF'!T10 -> 4072200.8 | Y10: =+'NOTAS ESF'!U10 -> -4649353.1 | Z10: =+'NOTAS ESF'!V10 -> -5795604.9 | AA10: =+'NOTAS ESF'!W10 -> -3994354.1 | AB10: =+'NOTAS ESF'!X10 -> -1573955.3 | ... AF10: =+'NOTAS ESF'!AB10 -> 6342950.9 | AH10: =+'NOTAS ESF'!AD10 -> 1846377.4 | AI10: =+'NOTAS ESF'!AE10 -> -16503757 | AJ10: =+'NOTAS ESF'!AF10 -> -15088454 | AK10: =+'NOTAS ESF'!AG10 -> -16610194 | AL10: =+'NOTAS ESF'!AH10 -> -16113342 | AM10: =+'NOTAS ESF'!AI10 -> -13926093 | AN10: =+'NOTAS ESF'!AJ10 -> -15129335 | AO10: =+'NOTAS ESF'!AK10 -> -12473354 | ... AS10: =+'NOTAS ESF'!AO10 -> -4863415.3 | AU10: =+'NOTAS ESF'!AQ10 -> 3821900.2 | AV10: =+'NOTAS ESF'!AR10 -> 89923 | AW10: =+'NOTAS ESF'!AS10 -> 3267146 | AX10: =+'NOTAS ESF'!AT10 -> 1261066 | AY10: =+'NOTAS ESF'!AU10 -> 102040 | AZ10: =+'NOTAS ESF'!AV10 -> 0 | BA10: =+'NOTAS ESF'!AW10 -> 0 | BB10: =+'NOTAS ESF'!AX10 -> 0 | ... BF10: =+'NOTAS ESF'!BB10 -> 0 | BH10: =+'NOTAS ESF'!BD10 -> 15221800 | BI10: =+'NOTAS ESF'!BE10 -> 0 | BJ10: =+'NOTAS ESF'!BF10 -> 0 | BK10: =+'NOTAS ESF'!BG10 -> 0 | BL10: =+'NOTAS ESF'!BH10 -> 0 | BM10: =+'NOTAS ESF'!BI10 -> 0 | BO10: =+'NOTAS ESF'!BK10 -> 2000000
B11: Instrumentos Financieros Cuentas Por Cobrar | D11: 5 | F11: =+'NOTAS ESF'!B14 -> 60550558 | H11: =+'NOTAS ESF'!D14 -> 26355626 | I11: =+'NOTAS ESF'!E14 -> 63694677 | J11: =+'NOTAS ESF'!F14 -> 46536961 | K11: =+'NOTAS ESF'!G14 -> 53380639 | L11: =+'NOTAS ESF'!H14 -> 39619796 | M11: =+'NOTAS ESF'!I14 -> 35652593 | N11: =+'NOTAS ESF'!J14 -> 33989755 | O11: =+'NOTAS ESF'!K14 -> 31431872 | ... S11: =+'NOTAS ESF'!O14 -> 8143514.7 | U11: =+'NOTAS ESF'!Q14 -> 15258879 | V11: =+'NOTAS ESF'!R14 -> 14415869 | W11: =+'NOTAS ESF'!S14 -> 14986890 | X11: =+'NOTAS ESF'!T14 -> 23162180 | Y11: =+'NOTAS ESF'!U14 -> 28904093 | Z11: =+'NOTAS ESF'!V14 -> 29247383 | AA11: =+'NOTAS ESF'!W14 -> 25029313 | AB11: =+'NOTAS ESF'!X14 -> 33443093 | ... AF11: =+'NOTAS ESF'!AB14 -> 21982196 | AH11: =+'NOTAS ESF'!AD14 -> 20841140 | AI11: =+'NOTAS ESF'!AE14 -> 4765667.3 | AJ11: =+'NOTAS ESF'!AF14 -> 4380307.3 | AK11: =+'NOTAS ESF'!AG14 -> 3878887.7 | AL11: =+'NOTAS ESF'!AH14 -> 3706628 | AM11: =+'NOTAS ESF'!AI14 -> 3427628 | AN11: =+'NOTAS ESF'!AJ14 -> 3133668 | AO11: =+'NOTAS ESF'!AK14 -> 2794188 | ... BM11: =+'NOTAS ESF'!BI14 -> 0 | BO11: =+'NOTAS ESF'!BK14 -> 0
B12: Total | F12: =SUM(F10:F11) -> 86903157 | H12: =SUM(H10:H11) -> 92150349 | I12: =SUM(I10:I11) -> 92938975 | J12: =SUM(J10:J11) -> 67635097 | K12: =SUM(K10:K11) -> 67910555 | L12: =SUM(L10:L11) -> 49975760 | M12: =SUM(M10:M11) -> 47580001 | N12: =SUM(N10:N11) -> 39728962 | O12: =SUM(O10:O11) -> 48209530 | ... S12: =SUM(S10:S11) -> 15343175 | U12: =SUM(U10:U11) -> 20641560 | V12: =SUM(V10:V11) -> 19448430 | W12: =SUM(W10:W11) -> 19870007 | X12: =SUM(X10:X11) -> 27234381 | Y12: =SUM(Y10:Y11) -> 24254740 | Z12: =SUM(Z10:Z11) -> 23451778 | AA12: =SUM(AA10:AA11) -> 21034959 | AB12: =SUM(AB10:AB11) -> 31869138 | ... AF12: =SUM(AF10:AF11) -> 28325147 | AH12: =SUM(AH10:AH11) -> 22687518 | AI12: =SUM(AI10:AI11) -> -11738090 | AJ12: =SUM(AJ10:AJ11) -> -10708147 | AK12: =SUM(AK10:AK11) -> -12731306 | AL12: =SUM(AL10:AL11) -> -12406714 | AM12: =SUM(AM10:AM11) -> -10498465 | AN12: =SUM(AN10:AN11) -> -11995667 | AO12: =SUM(AO10:AO11) -> -9679165.7 | ... AS12: =SUM(AS10:AS11) -> -3098320.3 | AU12: =SUM(AU10:AU11) -> 6365748.2 | AV12: =SUM(AV10:AV11) -> 887662 | AW12: =SUM(AW10:AW11) -> 40142491 | AX12: =SUM(AX10:AX11) -> 54084791 | AY12: =SUM(AY10:AY11) -> 31179818 | AZ12: =SUM(AZ10:AZ11) -> 17206089 | BA12: =SUM(BA10:BA11) -> 17206089 | BB12: =SUM(BB10:BB11) -> 17206089 | ... BF12: =SUM(BF10:BF11) -> 11686588 | BH12: =SUM(BH10:BH11) -> 15723388 | BI12: =SUM(BI10:BI11) -> 0 | BJ12: =SUM(BJ10:BJ11) -> 0 | BK12: =SUM(BK10:BK11) -> 0 | BL12: =SUM(BL10:BL11) -> 0 | BM12: =SUM(BM10:BM11) -> 0 | BO12: =SUM(BO10:BO11) -> 2000000
B14: No corriente
B15: Propiedad Planta y Equipo | D15: 6 | F15: =+'NOTAS ESF'!B61 -> 17386530 | H15: =+'NOTAS ESF'!D61 -> 17386530 | I15: =+'NOTAS ESF'!E61 -> 17386530 | J15: =+'NOTAS ESF'!F61 -> 17386530 | K15: =+'NOTAS ESF'!G61 -> 17386530 | L15: =+'NOTAS ESF'!H61 -> 17386530 | M15: =+'NOTAS ESF'!I61 -> 17386530 | N15: =+'NOTAS ESF'!J61 -> 17386530 | O15: =+'NOTAS ESF'!K61 -> 17386530 | ... S15: =+'NOTAS ESF'!O61 -> 17386530 | U15: =+'NOTAS ESF'!Q61 -> 17386530 | V15: =+'NOTAS ESF'!R61 -> 17386530 | W15: =+'NOTAS ESF'!S61 -> 17386530 | X15: =+'NOTAS ESF'!T61 -> 17386530 | Y15: =+'NOTAS ESF'!U61 -> 17386530 | Z15: =+'NOTAS ESF'!V61 -> 17386530 | AA15: =+'NOTAS ESF'!W61 -> 17386530 | AB15: =+'NOTAS ESF'!X61 -> 17386530 | ... AF15: =+'NOTAS ESF'!AB61 -> 17386530 | AH15: =+'NOTAS ESF'!AD61 -> 17386530 | AI15: =+'NOTAS ESF'!AE61 -> 13183193 | AJ15: =+'NOTAS ESF'!AF61 -> 13183193 | AK15: =+'NOTAS ESF'!AG61 -> 13183193 | AL15: =+'NOTAS ESF'!AH61 -> 13183193 | AM15: =+'NOTAS ESF'!AI61 -> 13183193 | AN15: =+'NOTAS ESF'!AJ61 -> 13183193 | AO15: =+'NOTAS ESF'!AK61 -> 13183193 | ... AS15: =+'NOTAS ESF'!AO61 -> 13183193 | AU15: =+'NOTAS ESF'!AQ61 -> 13183193 | AV15: =+'NOTAS ESF'!AR61 -> 9640732 | AW15: =+'NOTAS ESF'!AS61 -> 9853785 | AX15: =+'NOTAS ESF'!AT61 -> 10066838 | AY15: =+'NOTAS ESF'!AU61 -> 10279891 | AZ15: =+'NOTAS ESF'!AV61 -> 6892944 | BA15: =+'NOTAS ESF'!AW61 -> 7105997 | BB15: =+'NOTAS ESF'!AX61 -> 7319050 | ... BF15: =+'NOTAS ESF'!BB61 -> 8171262 | BH15: =+'NOTAS ESF'!BD61 -> 9583193 | BI15: =+'NOTAS ESF'!BE61 -> 0 | BJ15: =+'NOTAS ESF'!BF61 -> 0 | BK15: =+'NOTAS ESF'!BG61 -> 0 | BL15: =+'NOTAS ESF'!BH61 -> 0 | BM15: =+'NOTAS ESF'!BI61 -> 0 | BO15: =+'NOTAS ESF'!BK61 -> 0
B16: Activos Diferido | F16: =+'NOTAS ESF'!B69 -> 36327625 | H16: =+'NOTAS ESF'!D69 -> 36327625 | I16: =+'NOTAS ESF'!E69 -> 36327625 | J16: =+'NOTAS ESF'!F69 -> 36327625 | K16: =+'NOTAS ESF'!G69 -> 36327625 | L16: =+'NOTAS ESF'!H69 -> 36327625 | M16: =+'NOTAS ESF'!I69 -> 36327625 | N16: =+'NOTAS ESF'!J69 -> 36327625 | O16: =+'NOTAS ESF'!K69 -> 36327625 | ... S16: =+'NOTAS ESF'!O69 -> 36327625 | U16: =+'NOTAS ESF'!Q69 -> 36327625 | V16: =+'NOTAS ESF'!R69 -> 31808371 | W16: =+'NOTAS ESF'!S69 -> 29238600 | X16: =+'NOTAS ESF'!T69 -> 26656843 | Y16: =+'NOTAS ESF'!U69 -> 24207995 | Z16: =+'NOTAS ESF'!V69 -> 21747921 | AA16: =+'NOTAS ESF'!W69 -> 19339622 | AB16: =+'NOTAS ESF'!X69 -> 14232999 | ... AF16: =+'NOTAS ESF'!AB69 -> 2715692 | AH16: =+'NOTAS ESF'!AD69 -> 0 | AI16: =+'NOTAS ESF'!#REF! -> #REF! | AJ16: =+'NOTAS ESF'!#REF! -> #REF! | AK16: =+'NOTAS ESF'!#REF! -> #REF! | AL16: =+'NOTAS ESF'!#REF! -> #REF! | AM16: =+'NOTAS ESF'!#REF! -> #REF! | AN16: =+'NOTAS ESF'!#REF! -> #REF! | AO16: =+'NOTAS ESF'!#REF! -> #REF! | AP16: =+'NOTAS ESF'!#REF! -> #REF! | ... AS16: =+'NOTAS ESF'!#REF! -> #REF! | AU16: =+'NOTAS ESF'!AQ69 -> 24505488 | BH16: =+'NOTAS ESF'!BD69 -> 0 | BO16: =+'NOTAS ESF'!#REF! -> #REF!
B17: Total | F17: =SUM(F15:F16) -> 53714155 | H17: =SUM(H15:H16) -> 53714155 | I17: =SUM(I15:I16) -> 53714155 | J17: =SUM(J15:J16) -> 53714155 | K17: =SUM(K15:K16) -> 53714155 | L17: =SUM(L15:L16) -> 53714155 | M17: =SUM(M15:M16) -> 53714155 | N17: =SUM(N15:N16) -> 53714155 | O17: =SUM(O15:O16) -> 53714155 | ... S17: =SUM(S15:S16) -> 53714155 | U17: =SUM(U15:U16) -> 53714155 | V17: =SUM(V15:V16) -> 49194901 | W17: =SUM(W15:W16) -> 46625130 | X17: =SUM(X15:X16) -> 44043373 | Y17: =SUM(Y15:Y16) -> 41594525 | Z17: =SUM(Z15:Z16) -> 39134451 | AA17: =SUM(AA15:AA16) -> 36726152 | AB17: =SUM(AB15:AB16) -> 31619529 | ... AF17: =SUM(AF15:AF16) -> 20102222 | AH17: =SUM(AH15:AH16) -> 17386530 | AI17: =SUM(AI15:AI16) -> #REF! | AJ17: =SUM(AJ15:AJ16) -> #REF! | AK17: =SUM(AK15:AK16) -> #REF! | AL17: =SUM(AL15:AL16) -> #REF! | AM17: =SUM(AM15:AM16) -> #REF! | AN17: =SUM(AN15:AN16) -> #REF! | AO17: =SUM(AO15:AO16) -> #REF! | ... AS17: =SUM(AS15:AS16) -> #REF! | AU17: =SUM(AU15:AU16) -> 37688681 | AV17: =SUM(AV15:AV15) -> 9640732 | AW17: =SUM(AW15:AW15) -> 9853785 | AX17: =SUM(AX15:AX15) -> 10066838 | AY17: =SUM(AY15:AY15) -> 10279891 | AZ17: =SUM(AZ15:AZ15) -> 6892944 | BA17: =SUM(BA15:BA15) -> 7105997 | BB17: =SUM(BB15:BB15) -> 7319050 | BC17: =SUM(BC15:BC15) -> 7532103 | ... BF17: =SUM(BF15:BF15) -> 8171262 | BH17: =SUM(BH15:BH15) -> 9583193 | BI17: =SUM(BI15:BI15) -> 0 | BJ17: =SUM(BJ15:BJ15) -> 0 | BK17: =SUM(BK15:BK15) -> 0 | BL17: =SUM(BL15:BL15) -> 0 | BM17: =SUM(BM15:BM15) -> 0 | BO17: =SUM(BO15:BO15) -> 0
B19: Total Activo | F19: =+F12+F17 -> 1.4061731e+08 | H19: =+H12+H17 -> 1.458645e+08 | I19: =+I12+I17 -> 1.4665313e+08 | J19: =+J12+J17 -> 1.2134925e+08 | K19: =+K12+K17 -> 1.2162471e+08 | L19: =+L12+L17 -> 1.0368991e+08 | M19: =+M12+M17 -> 1.0129416e+08 | N19: =+N12+N17 -> 93443117 | O19: =+O12+O17 -> 1.0192369e+08 | ... S19: =+S12+S17 -> 69057330 | U19: =+U12+U17 -> 74355715 | V19: =+V12+V17 -> 68643331 | W19: =+W12+W17 -> 66495137 | X19: =+X12+X17 -> 71277754 | Y19: =+Y12+Y17 -> 65849265 | Z19: =+Z12+Z17 -> 62586229 | AA19: =+AA12+AA17 -> 57761111 | AB19: =+AB12+AB17 -> 63488667 | ... AF19: =+AF12+AF17 -> 48427369 | AH19: =+AH12+AH17 -> 40074048 | AI19: =+AI12+AI17 -> #REF! | AJ19: =+AJ12+AJ17 -> #REF! | AK19: =+AK12+AK17 -> #REF! | AL19: =+AL12+AL17 -> #REF! | AM19: =+AM12+AM17 -> #REF! | AN19: =+AN12+AN17 -> #REF! | AO19: =+AO12+AO17 -> #REF! | ... AS19: =+AS12+AS17 -> #REF! | AU19: =+AU12+AU17 -> 44054429 | AV19: =+AV17+AV12 -> 10528394 | AW19: =+AW17+AW12 -> 49996276 | AX19: =+AX17+AX12 -> 64151629 | AY19: =+AY17+AY12 -> 41459709 | AZ19: =+AZ17+AZ12 -> 24099033 | BA19: =+BA17+BA12 -> 24312086 | BB19: =+BB17+BB12 -> 24525139 | BC19: =+BC17+BC12 -> 25338364 | ... BF19: =+BF17+BF12 -> 19857850 | BH19: =+BH17+BH12 -> 25306581 | BI19: =+BI17+BI12 -> 0 | BJ19: =+BJ17+BJ12 -> 0 | BK19: =+BK17+BK12 -> 0 | BL19: =+BL17+BL12 -> 0 | BM19: =+BM17+BM12 -> 0 | BO19: =+BO17+BO12 -> 2000000
B21: PASIVOS
B23: Corriente
B24: Financieros | D24: 8 | F24: 0 | H24: 0 | I24: 0 | J24: 0 | K24: 0 | L24: 0 | M24: 0 | N24: 0 | O24: 0 | P24: 0 | Q24: 0 | R24: 0 | S24: 0 | U24: 0 | AX24: =+'NOTAS ESF'!#REF!*20% -> #REF! | AY24: =+'NOTAS ESF'!#REF!*20% -> #REF! | AZ24: =+'NOTAS ESF'!#REF!*20% -> #REF! | BA24: =+'NOTAS ESF'!#REF!*20% -> #REF! | BB24: =+'NOTAS ESF'!#REF!*20% -> #REF! | BC24: =+'NOTAS ESF'!#REF!*20% -> #REF! | BD24: =+'NOTAS ESF'!#REF!*20% -> #REF! | BE24: =+'NOTAS ESF'!#REF!*20% -> #REF! | BF24: =+'NOTAS ESF'!#REF!*20% -> #REF! | BH24: 0 | BI24: =+'NOTAS ESF'!#REF!*20% -> #REF! | BJ24: =+'NOTAS ESF'!#REF!*20% -> #REF! | BK24: =+'NOTAS ESF'!#REF!*20% -> #REF! | BL24: =+'NOTAS ESF'!#REF!*20% -> #REF! | BM24: =+'NOTAS ESF'!#REF!*20% -> #REF! | BO24: =+'NOTAS ESF'!#REF!*20% -> #REF!
B25: Proveedores Y Acreedores Comerciales | D25: 7 | F25: 0 | H25: 0 | I25: 0 | J25: 0 | K25: 0 | L25: 0 | M25: 0 | N25: 0 | O25: 0 | P25: 0 | Q25: 0 | R25: 0 | S25: 0 | U25: 0 | V25: 0 | W25: 0 | X25: 0 | Y25: 0 | Z25: 0 | AA25: 0 | AB25: 0 | AC25: 0 | AD25: 0 | AE25: 0 | AF25: 0 | AH25: 0 | AI25: 0 | AJ25: 0 | AK25: 0 | AL25: 0 | AM25: 0 | AN25: 0 | AO25: 0 | AP25: 0 | AQ25: 0 | AR25: 0 | AS25: 0 | AU25: 0 | AV25: 0 | AW25: 0 | AX25: 0 | AY25: 0 | AZ25: 0 | BA25: 0 | BB25: 0 | BC25: 0 | BD25: 0 | BE25: 0 | BF25: 0 | BH25: 0 | BI25: =+'NOTAS ESF'!#REF! -> #REF! | BJ25: =+'NOTAS ESF'!#REF! -> #REF! | BK25: =+'NOTAS ESF'!#REF! -> #REF! | BL25: =+'NOTAS ESF'!#REF! -> #REF! | BM25: =+'NOTAS ESF'!#REF! -> #REF! | BO25: 0
B26: Costos y Gastos Por Pagar | D26: 7 | F26: =+'NOTAS ESF'!B79 -> 4558817 | H26: =+'NOTAS ESF'!D79 -> 10155997 | I26: =+'NOTAS ESF'!E79 -> 9427003 | J26: =+'NOTAS ESF'!F79 -> 13568568 | K26: =+'NOTAS ESF'!G79 -> 13337057 | L26: =+'NOTAS ESF'!H79 -> 16305931 | M26: =+'NOTAS ESF'!I79 -> 19749101 | N26: =+'NOTAS ESF'!J79 -> 17140322 | O26: =+'NOTAS ESF'!K79 -> 20848428 | ... S26: =+'NOTAS ESF'!O79 -> 7877156 | U26: =+'NOTAS ESF'!Q79 -> 6941830 | V26: =+'NOTAS ESF'!R79 -> 2593000 | W26: =+'NOTAS ESF'!S79 -> 3691704 | X26: =+'NOTAS ESF'!T79 -> 4055497 | Y26: =+'NOTAS ESF'!U79 -> 2763553 | Z26: =+'NOTAS ESF'!V79 -> 2996811 | AA26: =+'NOTAS ESF'!W79 -> 2161391 | AB26: =+'NOTAS ESF'!X79 -> 3213352 | ... AF26: =+'NOTAS ESF'!AB79 -> 1329009 | BI26: =+'NOTAS ESF'!#REF!*20% -> #REF! | BJ26: =+'NOTAS ESF'!#REF!*20% -> #REF! | BK26: =+'NOTAS ESF'!#REF!*20% -> #REF! | BL26: =+'NOTAS ESF'!#REF!*20% -> #REF! | BM26: =+'NOTAS ESF'!#REF!*20% -> #REF! | BO26: 0
B27: No Finaniceros | D27: 8 | F27: =+'NOTAS ESF'!B98 -> 4356900 | H27: =+'NOTAS ESF'!D98 -> 3776000 | I27: =+'NOTAS ESF'!E98 -> 3856900 | J27: =+'NOTAS ESF'!F98 -> 3856900 | K27: =+'NOTAS ESF'!G98 -> 3808700 | L27: =+'NOTAS ESF'!H98 -> 3838500 | M27: =+'NOTAS ESF'!I98 -> 3856900 | N27: =+'NOTAS ESF'!J98 -> 3769500 | O27: =+'NOTAS ESF'!K98 -> 3669800 | ... S27: =+'NOTAS ESF'!O98 -> 698600 | U27: =+'NOTAS ESF'!Q98 -> 637600 | V27: =+'NOTAS ESF'!R98 -> 637600 | W27: =+'NOTAS ESF'!S98 -> 1636800 | X27: =+'NOTAS ESF'!T98 -> 1912800 | Y27: =+'NOTAS ESF'!U98 -> 1912800 | Z27: =+'NOTAS ESF'!V98 -> 1923700 | AA27: =+'NOTAS ESF'!W98 -> 2242500 | AB27: =+'NOTAS ESF'!X98 -> 3188000 | ... AF27: =+'NOTAS ESF'!AB98 -> 956400 | AH27: =+'NOTAS ESF'!AD98 -> 897900 | AI27: =+'NOTAS ESF'!AE98 -> 897900 | AJ27: =+'NOTAS ESF'!AF98 -> 1719000 | AK27: =+'NOTAS ESF'!AG98 -> 809400 | AL27: =+'NOTAS ESF'!AH98 -> 875700 | AM27: =+'NOTAS ESF'!AI98 -> 569000 | AN27: =+'NOTAS ESF'!AJ98 -> 720794 | AO27: =+'NOTAS ESF'!AK98 -> 569000 | ... AS27: =+'NOTAS ESF'!AO98 -> 569000 | AU27: =+'NOTAS ESF'!AQ98 -> 780400 | AV27: =+'NOTAS ESF'!AR98 -> 1492900 | AW27: =+'NOTAS ESF'!AS98 -> 1098944 | AX27: =+'NOTAS ESF'!AT98 -> 391956 | AY27: =+'NOTAS ESF'!AU98 -> 363278 | AZ27: =+'NOTAS ESF'!AV98 -> 513452 | BA27: =+'NOTAS ESF'!AW98 -> 374078 | BB27: =+'NOTAS ESF'!AX98 -> 374078 | ... BF27: =+'NOTAS ESF'!BB98 -> 116522 | BH27: =+'NOTAS ESF'!BD98 -> 446000 | BI27: =+'NOTAS ESF'!BE98 -> 0 | BJ27: =+'NOTAS ESF'!BF98 -> 0 | BK27: =+'NOTAS ESF'!BG98 -> 0 | BL27: =+'NOTAS ESF'!BH98 -> 0 | BM27: =+'NOTAS ESF'!BI98 -> 0 | BO27: =+'NOTAS ESF'!BK98 -> 0
B28: Fiscales | D28: 9 | F28: =+'NOTAS ESF'!B107 -> 38753449 | H28: =+'NOTAS ESF'!D107 -> 40687062 | I28: =+'NOTAS ESF'!E107 -> 36865926 | J28: =+'NOTAS ESF'!F107 -> 32224889 | K28: =+'NOTAS ESF'!G107 -> 27343774 | L28: =+'NOTAS ESF'!H107 -> 20796788 | M28: =+'NOTAS ESF'!I107 -> 21537467 | N28: =+'NOTAS ESF'!J107 -> 23015077 | O28: =+'NOTAS ESF'!K107 -> 24848147 | ... S28: =+'NOTAS ESF'!O107 -> 30697551 | U28: =+'NOTAS ESF'!Q107 -> 32974361 | V28: =+'NOTAS ESF'!R107 -> 32800049 | W28: =+'NOTAS ESF'!S107 -> 30758162 | X28: =+'NOTAS ESF'!T107 -> 31769128 | Y28: =+'NOTAS ESF'!U107 -> 31003445 | Z28: =+'NOTAS ESF'!V107 -> 29069622 | AA28: =+'NOTAS ESF'!W107 -> 26373928 | AB28: =+'NOTAS ESF'!X107 -> 27514427 | ... AF28: =+'NOTAS ESF'!AB107 -> 24251628 | AH28: =+'NOTAS ESF'!AD107 -> 19565238 | AI28: =+'NOTAS ESF'!AE107 -> 14531905 | AJ28: =+'NOTAS ESF'!AF107 -> 13621990 | AK28: =+'NOTAS ESF'!AG107 -> 11593683 | AL28: =+'NOTAS ESF'!AH107 -> 10977523 | AM28: =+'NOTAS ESF'!AI107 -> 10012082 | AN28: =+'NOTAS ESF'!AJ107 -> 9171171.7 | AO28: =+'NOTAS ESF'!AK107 -> 8670615.1 | ... AS28: =+'NOTAS ESF'!AO107 -> 268308 | AU28: =+'NOTAS ESF'!AQ107 -> 4036561 | AV28: =+'NOTAS ESF'!AR107 -> 3427601 | AW28: =+'NOTAS ESF'!AS107 -> 3427601 | AX28: =+'NOTAS ESF'!AT107 -> 2823278.4 | AY28: =+'NOTAS ESF'!AU107 -> 1827340.1 | AZ28: =+'NOTAS ESF'!AV107 -> -25516.32 | BA28: =+'NOTAS ESF'!AW107 -> 27081.76 | BB28: =+'NOTAS ESF'!AX107 -> 93272.21 | ... BF28: =+'NOTAS ESF'!BB107 -> -648977.02 | BH28: =+'NOTAS ESF'!BD107 -> 294499.83 | BI28: =+'NOTAS ESF'!BE107 -> 0 | BJ28: =+'NOTAS ESF'!BF107 -> 0 | BK28: =+'NOTAS ESF'!BG107 -> 0 | BL28: =+'NOTAS ESF'!BH107 -> 0 | BM28: =+'NOTAS ESF'!BI107 -> 0 | BO28: =+'NOTAS ESF'!BK107 -> 0
B29: Por Beneficios a Empleados | D29: 10 | F29: =+'NOTAS ESF'!B118 -> 44679735 | H29: =+'NOTAS ESF'!D118 -> 35230529 | I29: =+'NOTAS ESF'!E118 -> 46596939 | J29: =+'NOTAS ESF'!F118 -> 29319455 | K29: =+'NOTAS ESF'!G118 -> 44412470 | L29: =+'NOTAS ESF'!H118 -> 40577188 | M29: =+'NOTAS ESF'!I118 -> 36741704 | N29: =+'NOTAS ESF'!J118 -> 33292159 | O29: =+'NOTAS ESF'!K118 -> 37217535 | ... S29: =+'NOTAS ESF'!O118 -> 16395504 | U29: =+'NOTAS ESF'!Q118 -> 16398640 | V29: =+'NOTAS ESF'!R118 -> 16775928 | W29: =+'NOTAS ESF'!S118 -> 16355689 | X29: =+'NOTAS ESF'!T118 -> 20855057 | Y29: =+'NOTAS ESF'!U118 -> 17768027 | Z29: =+'NOTAS ESF'!V118 -> 17113268 | AA29: =+'NOTAS ESF'!W118 -> 17254521 | AB29: =+'NOTAS ESF'!X118 -> 17747629 | ... AF29: =+'NOTAS ESF'!AB118 -> 11572647 | AH29: =+'NOTAS ESF'!AD118 -> 10384219 | AI29: =+'NOTAS ESF'!AE118 -> 11172268 | AJ29: =+'NOTAS ESF'!AF118 -> 10466235 | AK29: =+'NOTAS ESF'!AG118 -> 5838235 | AL29: =+'NOTAS ESF'!AH118 -> 5506749 | AM29: =+'NOTAS ESF'!AI118 -> 4822615 | AN29: =+'NOTAS ESF'!AJ118 -> 5416539 | AO29: =+'NOTAS ESF'!AK118 -> 5076869 | ... AS29: =+'NOTAS ESF'!AO118 -> 3714002 | AU29: =+'NOTAS ESF'!AQ118 -> 3419676.7 | AV29: =+'NOTAS ESF'!AR118 -> 6199779 | AW29: =+'NOTAS ESF'!AS118 -> 5368633 | AX29: =+'NOTAS ESF'!AT118 -> 4087491 | AY29: =+'NOTAS ESF'!AU118 -> 2824195 | AZ29: =+'NOTAS ESF'!AV118 -> 2579874 | BA29: =+'NOTAS ESF'!AW118 -> 2162737 | BB29: =+'NOTAS ESF'!AX118 -> 2463015 | ... BF29: =+'NOTAS ESF'!BB118 -> 2415217 | BH29: =+'NOTAS ESF'!BD118 -> 1499566.3 | BI29: =+'NOTAS ESF'!BE118 -> 0 | BJ29: =+'NOTAS ESF'!BF118 -> 0 | BK29: =+'NOTAS ESF'!BG118 -> 0 | BL29: =+'NOTAS ESF'!BH118 -> 0 | BM29: =+'NOTAS ESF'!BI118 -> 0 | BO29: =+'NOTAS ESF'!BK118 -> 0
B30: Total | F30: =SUM(F24:F29) -> 92348901 | H30: =SUM(H24:H29) -> 89849588 | I30: =SUM(I24:I29) -> 96746768 | J30: =SUM(J24:J29) -> 78969812 | K30: =SUM(K24:K29) -> 88902001 | L30: =SUM(L24:L29) -> 81518407 | M30: =SUM(M24:M29) -> 81885172 | N30: =SUM(N24:N29) -> 77217058 | O30: =SUM(O24:O29) -> 86583910 | ... S30: =SUM(S24:S29) -> 55668811 | U30: =SUM(U24:U29) -> 56952431 | V30: =SUM(V24:V29) -> 52806577 | W30: =SUM(W24:W29) -> 52442355 | X30: =SUM(X24:X29) -> 58592482 | Y30: =SUM(Y24:Y29) -> 53447825 | Z30: =SUM(Z24:Z29) -> 51103401 | AA30: =SUM(AA24:AA29) -> 48032340 | AB30: =SUM(AB24:AB29) -> 51663408 | ... AF30: =SUM(AF24:AF29) -> 38109684 | AH30: =SUM(AH24:AH29) -> 30847357 | AI30: =SUM(AI24:AI29) -> 26602073 | AJ30: =SUM(AJ24:AJ29) -> 25807225 | AK30: =SUM(AK24:AK29) -> 18241318 | AL30: =SUM(AL24:AL29) -> 17359972 | AM30: =SUM(AM24:AM29) -> 15403697 | AN30: =SUM(AN24:AN29) -> 15308505 | AO30: =SUM(AO24:AO29) -> 14316484 | ... AS30: =SUM(AS24:AS29) -> 4551310 | AU30: =SUM(AU24:AU29) -> 8236637.7 | AV30: =SUM(AV24:AV29) -> 11120280 | AW30: =SUM(AW24:AW29) -> 9895178 | AX30: =+AX27+AX28+AX29 -> 7302725.4 | AY30: =+AY27+AY28+AY29 -> 5014813.1 | AZ30: =+AZ27+AZ28+AZ29 -> 3067809.7 | BA30: =+BA27+BA28+BA29 -> 2563896.8 | BB30: =+BB27+BB28+BB29 -> 2930365.2 | BC30: =+BC27+BC28+BC29 -> 2899502.2 | BD30: =+BD27+BD28+BD29 -> 2646652.7 | BE30: =+BE27+BE28+BE29 -> 1281004.5 | BF30: =+BF27+BF28+BF29 -> 1882762 | BH30: =SUM(BH24:BH29) -> 2240066.2 | BI30: =SUM(BI24:BI29) -> #REF! | BJ30: =SUM(BJ24:BJ29) -> #REF! | BK30: =SUM(BK24:BK29) -> #REF! | BL30: =SUM(BL24:BL29) -> #REF! | BM30: =SUM(BM24:BM29) -> #REF! | BO30: =SUM(BO24:BO29) -> #REF!
B32: No corriente
B33: Consignaciones sin Identificar | D33: 11 | F33: =+'NOTAS ESF'!B125 -> 6684000 | H33: =+'NOTAS ESF'!D125 -> 6684000 | I33: =+'NOTAS ESF'!E125 -> 6684000 | J33: =+'NOTAS ESF'!F125 -> 6684000 | K33: =+'NOTAS ESF'!G125 -> 6684000 | L33: =+'NOTAS ESF'!H125 -> 6684000 | M33: =+'NOTAS ESF'!I125 -> 6684000 | N33: =+'NOTAS ESF'!J125 -> 4284000 | O33: =+'NOTAS ESF'!K125 -> 4284000 | ... S33: =+'NOTAS ESF'!O125 -> 0 | U33: =+'NOTAS ESF'!Q125 -> 0 | V33: =+'NOTAS ESF'!R125 -> 0 | W33: =+'NOTAS ESF'!S125 -> 0 | X33: =+'NOTAS ESF'!T125 -> 0 | Y33: =+'NOTAS ESF'!U125 -> 0 | Z33: =+'NOTAS ESF'!V125 -> 0 | AA33: =+'NOTAS ESF'!W125 -> 0 | AB33: =+'NOTAS ESF'!X125 -> 1685431 | ... AF33: =+'NOTAS ESF'!AB125 -> 0 | AH33: =+'NOTAS ESF'!AD79 -> 40000 | AI33: =+'NOTAS ESF'!AE79 -> 29910000 | AJ33: =+'NOTAS ESF'!AF79 -> 33910000 | AK33: =+'NOTAS ESF'!AG79 -> 29910000 | AL33: =+'NOTAS ESF'!AH79 -> 34210385 | AM33: =+'NOTAS ESF'!AI79 -> 36724324 | AN33: =+'NOTAS ESF'!AJ79 -> 75507001 | AO33: =+'NOTAS ESF'!AK79 -> 71511775 | ... AS33: =+'NOTAS ESF'!AO79 -> 35845172 | AU33: =+'NOTAS ESF'!AQ79 -> 32460000 | AV33: =+'NOTAS ESF'!AR79 -> 1694936.5 | AW33: =+'NOTAS ESF'!AS79 -> 42400371 | AX33: =+'NOTAS ESF'!AT79 -> 43938473 | AY33: =+'NOTAS ESF'!AU79 -> 27215890 | AZ33: =+'NOTAS ESF'!AV79 -> 18825168 | BA33: =+'NOTAS ESF'!AW79 -> 18846889 | BB33: =+'NOTAS ESF'!AX79 -> 18760643 | ... BF33: =+'NOTAS ESF'!BB79 -> 17136601 | BH33: =+'NOTAS ESF'!BD79 -> 20000000 | BI33: =+'NOTAS ESF'!#REF!*80% -> #REF! | BJ33: =+'NOTAS ESF'!#REF!*80% -> #REF! | BK33: =+'NOTAS ESF'!#REF!*80% -> #REF! | BL33: =+'NOTAS ESF'!#REF!*80% -> #REF! | BM33: =+'NOTAS ESF'!#REF!*80% -> #REF! | BO33: =+'NOTAS ESF'!#REF!*80% -> #REF!
B34: Total | F34: =SUM(F32:F33) -> 6684000 | H34: =SUM(H32:H33) -> 6684000 | I34: =SUM(I32:I33) -> 6684000 | J34: =SUM(J32:J33) -> 6684000 | K34: =SUM(K32:K33) -> 6684000 | L34: =SUM(L32:L33) -> 6684000 | M34: =SUM(M32:M33) -> 6684000 | N34: =SUM(N32:N33) -> 4284000 | O34: =SUM(O32:O33) -> 4284000 | ... S34: =SUM(S32:S33) -> 0 | U34: =SUM(U32:U33) -> 0 | V34: =SUM(V32:V33) -> 0 | W34: =SUM(W32:W33) -> 0 | X34: =SUM(X32:X33) -> 0 | Y34: =SUM(Y32:Y33) -> 0 | Z34: =SUM(Z32:Z33) -> 0 | AA34: =SUM(AA32:AA33) -> 0 | AB34: =SUM(AB32:AB33) -> 1685431 | ... AF34: =SUM(AF32:AF33) -> 0 | AH34: =SUM(AH32:AH33) -> 40000 | AI34: =SUM(AI32:AI33) -> 29910000 | AJ34: =SUM(AJ32:AJ33) -> 33910000 | AK34: =SUM(AK32:AK33) -> 29910000 | AL34: =SUM(AL32:AL33) -> 34210385 | AM34: =SUM(AM32:AM33) -> 36724324 | AN34: =SUM(AN32:AN33) -> 75507001 | AO34: =SUM(AO32:AO33) -> 71511775 | ... AS34: =SUM(AS32:AS33) -> 35845172 | AU34: =SUM(AU32:AU33) -> 32460000 | AV34: =SUM(AV32:AV33) -> 1694936.5 | AW34: =SUM(AW32:AW33) -> 42400371 | AX34: =SUM(AX32:AX33) -> 43938473 | AY34: =SUM(AY32:AY33) -> 27215890 | AZ34: =SUM(AZ32:AZ33) -> 18825168 | BA34: =SUM(BA32:BA33) -> 18846889 | BB34: =SUM(BB32:BB33) -> 18760643 | ... BF34: =SUM(BF32:BF33) -> 17136601 | BH34: =SUM(BH32:BH33) -> 20000000 | BI34: =SUM(BI32:BI33) -> #REF! | BJ34: =SUM(BJ32:BJ33) -> #REF! | BK34: =SUM(BK32:BK33) -> #REF! | BL34: =SUM(BL32:BL33) -> #REF! | BM34: =SUM(BM32:BM33) -> #REF! | BO34: =SUM(BO32:BO33) -> #REF!
B36: Total Pasivo | F36: =+F34+F30 -> 99032901 | H36: =+H34+H30 -> 96533588 | I36: =+I34+I30 -> 1.0343077e+08 | J36: =+J34+J30 -> 85653812 | K36: =+K34+K30 -> 95586001 | L36: =+L34+L30 -> 88202407 | M36: =+M34+M30 -> 88569172 | N36: =+N34+N30 -> 81501058 | O36: =+O34+O30 -> 90867910 | ... S36: =+S34+S30 -> 55668811 | U36: =+U34+U30 -> 56952431 | V36: =+V34+V30 -> 52806577 | W36: =+W34+W30 -> 52442355 | X36: =+X34+X30 -> 58592482 | Y36: =+Y34+Y30 -> 53447825 | Z36: =+Z34+Z30 -> 51103401 | AA36: =+AA34+AA30 -> 48032340 | AB36: =+AB34+AB30 -> 53348839 | ... AF36: =+AF34+AF30 -> 38109684 | AH36: =+AH34+AH30 -> 30887357 | AI36: =+AI34+AI30 -> 56512073 | AJ36: =+AJ34+AJ30 -> 59717225 | AK36: =+AK34+AK30 -> 48151318 | AL36: =+AL34+AL30 -> 51570357 | AM36: =+AM34+AM30 -> 52128021 | AN36: =+AN34+AN30 -> 90815506 | AO36: =+AO34+AO30 -> 85828259 | ... AS36: =+AS34+AS30 -> 40396482 | AU36: =+AU34+AU30 -> 40696638 | AV36: =+AV34+AV30 -> 12815216 | AW36: =+AW34+AW30 -> 52295549 | AX36: =+AX34+AX30 -> 51241198 | AY36: =+AY34+AY30 -> 32230703 | AZ36: =+AZ34+AZ30 -> 21892978 | BA36: =+BA34+BA30 -> 21410786 | BB36: =+BB34+BB30 -> 21691009 | ... BF36: =+BF34+BF30 -> 19019363 | BH36: =+BH34+BH30 -> 22240066 | BI36: =+BI34+BI30 -> #REF! | BJ36: =+BJ34+BJ30 -> #REF! | BK36: =+BK34+BK30 -> #REF! | BL36: =+BL34+BL30 -> #REF! | BM36: =+BM34+BM30 -> #REF! | BO36: =+BO34+BO30 -> #REF!
B38: PATRIMONIO
B40: Capital Social | D40: 12 | F40: =+'NOTAS ESF'!B131 -> 2000000 | H40: =+'NOTAS ESF'!D131 -> 2000000 | I40: =+'NOTAS ESF'!E131 -> 2000000 | J40: =+'NOTAS ESF'!F131 -> 2000000 | K40: =+'NOTAS ESF'!G131 -> 2000000 | L40: =+'NOTAS ESF'!H131 -> 2000000 | M40: =+'NOTAS ESF'!I131 -> 2000000 | N40: =+'NOTAS ESF'!J131 -> 2000000 | O40: =+'NOTAS ESF'!K131 -> 2000000 | ... S40: =+'NOTAS ESF'!O131 -> 2000000 | U40: =+'NOTAS ESF'!Q131 -> 2000000 | V40: =+'NOTAS ESF'!R131 -> 2000000 | W40: =+'NOTAS ESF'!S131 -> 2000000 | X40: =+'NOTAS ESF'!T131 -> 2000000 | Y40: =+'NOTAS ESF'!U131 -> 2000000 | Z40: =+'NOTAS ESF'!V131 -> 2000000 | AA40: =+'NOTAS ESF'!W131 -> 2000000 | AB40: =+'NOTAS ESF'!X131 -> 2000000 | ... AF40: =+'NOTAS ESF'!AB131 -> 2000000 | AH40: =+'NOTAS ESF'!AD131 -> 2000000 | AI40: =+'NOTAS ESF'!AE131 -> 2000000 | AJ40: =+'NOTAS ESF'!AF131 -> 2000000 | AK40: =+'NOTAS ESF'!AG131 -> 2000000 | AL40: =+'NOTAS ESF'!AH131 -> 2000000 | AM40: =+'NOTAS ESF'!AI131 -> 2000000 | AN40: =+'NOTAS ESF'!AJ131 -> 2000000 | AO40: =+'NOTAS ESF'!AK131 -> 2000000 | ... AS40: =+'NOTAS ESF'!AO131 -> 2000000 | AU40: =+'NOTAS ESF'!AQ131 -> 2000000 | AV40: =+'NOTAS ESF'!AR131 -> 2000000 | AW40: =+'NOTAS ESF'!AS131 -> 2000000 | AX40: =+'NOTAS ESF'!AT131 -> 2000000 | AY40: =+'NOTAS ESF'!AU131 -> 2000000 | AZ40: =+'NOTAS ESF'!AV131 -> 2000000 | BA40: =+'NOTAS ESF'!AW131 -> 2000000 | BB40: =+'NOTAS ESF'!AX131 -> 2000000 | ... BF40: =+'NOTAS ESF'!BB131 -> 2000000 | BH40: =+'NOTAS ESF'!BD131 -> 2000000 | BI40: =+'NOTAS ESF'!BE131 -> 0 | BJ40: =+'NOTAS ESF'!BF131 -> 0 | BK40: =+'NOTAS ESF'!BG131 -> 0 | BL40: =+'NOTAS ESF'!BH131 -> 0 | BM40: =+'NOTAS ESF'!BI131 -> 0 | BO40: =+'NOTAS ESF'!BK131 -> 2000000
B41: Capital suscrito y Pagado
B42: Reservas | D42: 13 | F42: =+'NOTAS ESF'!B133 -> 129048 | H42: =+'NOTAS ESF'!D133 -> 129048 | I42: =+'NOTAS ESF'!E133 -> 129048 | J42: =+'NOTAS ESF'!F133 -> 129048 | K42: =+'NOTAS ESF'!G133 -> 129048 | L42: =+'NOTAS ESF'!H133 -> 129048 | M42: =+'NOTAS ESF'!I133 -> 129048 | N42: =+'NOTAS ESF'!J133 -> 129048 | O42: =+'NOTAS ESF'!K133 -> 129048 | ... S42: =+'NOTAS ESF'!O133 -> 129048 | U42: =+'NOTAS ESF'!Q133 -> 129048 | V42: =+'NOTAS ESF'!R133 -> 129048 | W42: =+'NOTAS ESF'!S133 -> 129048 | X42: =+'NOTAS ESF'!T133 -> 129048 | Y42: =+'NOTAS ESF'!U133 -> 129048 | Z42: =+'NOTAS ESF'!V133 -> 129048 | AA42: =+'NOTAS ESF'!W133 -> 129048 | AB42: =+'NOTAS ESF'!X133 -> 129048 | ... AF42: =+'NOTAS ESF'!AB133 -> 129048 | AH42: 129048 | AI42: =+'NOTAS ESF'!AE133 -> 117317 | AJ42: =+'NOTAS ESF'!AF133 -> 117317 | AK42: =+'NOTAS ESF'!AG133 -> 117317 | AL42: =+'NOTAS ESF'!AH133 -> 117317 | AM42: =+'NOTAS ESF'!AI133 -> 117317 | AN42: =+'NOTAS ESF'!AJ133 -> 117317 | AO42: =+'NOTAS ESF'!AK133 -> 117317 | AP42: =+'NOTAS ESF'!AL133 -> 117317 | ... AS42: =+'NOTAS ESF'!AO133 -> 117317 | AU42: =+'NOTAS ESF'!AQ133 -> 106651.5 | AV42: =+'NOTAS ESF'!AR133 -> 106651.5 | AW42: =+'NOTAS ESF'!AS133 -> 106651.5 | AX42: =+'NOTAS ESF'!AT133 -> 106651.5 | AY42: =+'NOTAS ESF'!AU133 -> 106651.5 | AZ42: =+'NOTAS ESF'!AV133 -> 106651.5 | BA42: =+'NOTAS ESF'!AW133 -> 106651.5 | BB42: =+'NOTAS ESF'!AX133 -> 106651.5 | ... BF42: =+'NOTAS ESF'!BB133 -> 0 | BH42: =+'NOTAS ESF'!BD133 -> 0 | BI42: =+'NOTAS ESF'!BE133 -> 0 | BJ42: =+'NOTAS ESF'!BF133 -> 0 | BK42: =+'NOTAS ESF'!BG133 -> 0 | BL42: =+'NOTAS ESF'!BH133 -> 0 | BM42: =+'NOTAS ESF'!BI133 -> 0 | BO42: =+'NOTAS ESF'!BK133 -> 0
B43: Donaciones en Bienes inmuebles
B44: Resultado de ejercicios anteriores | D44: 12 | F44: =+H44+H45 -> 47201868 | H44: =+I44 -> 15274236 | I44: =+J44 -> 15274236 | J44: =+K44 -> 15274236 | K44: =+L44 -> 15274236 | L44: =+M44 -> 15274236 | M44: =+N44 -> 15274236 | N44: =+O44 -> 15274236 | O44: =+P44 -> 15274236 | ... R44: =+S44 -> 15274236 | S44: =+U44+U45 -> 15274236 | U44: =+'NOTAS ESF'!Q135 -> 7057643.6 | V44: =+'NOTAS ESF'!R135 -> 7057643.6 | W44: =+'NOTAS ESF'!S135 -> 7057643.6 | X44: =+'NOTAS ESF'!T135 -> 7057643.6 | Y44: =+'NOTAS ESF'!U135 -> 7057643.6 | Z44: =+'NOTAS ESF'!V135 -> 7057643.6 | AA44: =+'NOTAS ESF'!W135 -> 7057643.6 | AB44: =+AC44 -> 7057643.6 | AC44: =+AD44 -> 7057643.6 | AD44: =+AE44 -> 7057643.6 | AE44: =+AF44 -> 7057643.6 | AF44: =+AH44+AH45 -> 7057643.6 | AH44: =+AU45+AU42+AU44-AH42 -> 1228743.5 | AI44: =+'NOTAS ESF'!AE135 -> 1114604.8 | AJ44: =+'NOTAS ESF'!AF135 -> 1114604.8 | AK44: =+'NOTAS ESF'!AG135 -> 1114604.8 | AL44: =+'NOTAS ESF'!AH135 -> 1114604.8 | AM44: =+'NOTAS ESF'!AI135 -> 1114604.8 | AN44: =+'NOTAS ESF'!AJ135 -> 1240474.5 | AO44: =+'NOTAS ESF'!AK135 -> 1240474.5 | AP44: =+'NOTAS ESF'!AL135 -> 1240474.5 | ... AS44: =+'NOTAS ESF'!AO135 -> 1240474.5 | AU44: =+'NOTAS ESF'!AQ135 -> 960703.5 | AV44: =+'NOTAS ESF'!AR135 -> 960703.5 | AW44: =+'NOTAS ESF'!AS135 -> 960703.5 | AX44: =+'NOTAS ESF'!AT135 -> 960703.5 | AY44: =+'NOTAS ESF'!AU135 -> 960703.5 | AZ44: =+'NOTAS ESF'!AV135 -> 960703.5 | BA44: =+'NOTAS ESF'!AW135 -> 960703.5 | BB44: =+'NOTAS ESF'!AX135 -> 960703.5 | ... BF44: =+'NOTAS ESF'!BB135 -> 1066515 | BH44: =+'NOTAS ESF'!BD135 -> 0 | BI44: =+'NOTAS ESF'!BE135 -> 0 | BJ44: =+'NOTAS ESF'!BF135 -> 0 | BK44: =+'NOTAS ESF'!BG135 -> 0 | BL44: =+'NOTAS ESF'!BH135 -> 0 | BM44: =+'NOTAS ESF'!BI135 -> 0 | BO44: =+'NOTAS ESF'!BK135 -> 0
B45: Resultado del ejercicio | D45: 12 | F45: =+ERI!Q51 -> -7746505 | H45: =+ERI!T51+I45 -> 31927632 | I45: =+ERI!U51+J45 -> 25819078 | J45: =+ERI!V51+K45 -> 18292156 | K45: =+ERI!W51+L45 -> 8635424.8 | L45: =+ERI!X51+M45 -> -1915776.3 | M45: =+ERI!Y51+N45 -> -4678299.4 | N45: =+ERI!Z51+O45 -> -5461225.1 | O45: =+ERI!AA51+P45 -> -6347508.5 | ... R45: =+ERI!AD51+S45 -> -7076854.4 | S45: =+ERI!AE51 -> -4014765.5 | U45: =+V45+ERI!AH51 -> 8216592.3 | V45: =+W45+ERI!AI51 -> 6650062.4 | W45: =+X45+ERI!AJ51 -> 4866090.6 | X45: =+ERI!AK51+ERI!AL51+ERI!AM51+ERI!AN51+ERI!AO51+ERI!AP51+ERI!AQ51+ERI!AR51+ERI!AS51 -> 3498580.3 | Y45: =+ERI!AS51+ERI!AR51+ERI!AQ51+ERI!AP51+ERI!AO51+ERI!AN51+ERI!AM51+ERI!AL51 -> 3214748 | Z45: =+ERI!AS51+ERI!AR51+ERI!AQ51+ERI!AP51+ERI!AO51+ERI!AN51+ERI!AM51 -> 2296135.5 | AA45: =+ERI!AS51+ERI!AR51+ERI!AQ51+ERI!AP51+ERI!AO51+ERI!AN51 -> 542079.42 | AB45: =+ERI!AS51+ERI!AR51+ERI!AQ51+ERI!AP51+ERI!AO51 -> 953136.17 | AC45: =+AD45+ERI!AP51 -> 153512.45 | AD45: =+ERI!AS51+ERI!AR51+ERI!AQ51 -> 1460856.1 | AE45: =+ERI!AS51+ERI!AR51 -> 459221.75 | AF45: =+ERI!AS51 -> 1130992.9 | AH45: =+ERI!AU51 -> 5828900.1 | AI45: =+AJ45+ERI!AW51 -> 9929259.6 | AJ45: =+AK45+ERI!AX51 -> 8668729.7 | AK45: =+AL45+ERI!AY51 -> 3595128.7 | AL45: =+AM45+ERI!AZ51 -> 7061106.7 | AM45: =+AN45+ERI!BA51 -> 8009431.9 | AN45: =+AO45+ERI!BB51 -> 8816965.9 | AO45: =+AP45+ERI!BC51 -> 9048605.9 | AP45: =+AQ45+ERI!BD47 -> -26187562 | AQ45: =+AR45+ERI!BE51 -> -23085129 | AR45: =+AS45+ERI!BF51 -> -11531482 | AS45: =+ERI!BG51 -> -6522272 | AU45: =+ERI!BI51 -> 290436.49 | AV45: =+'NOTAS ERI'!BH179 -> -5354177.5 | AW45: =+'NOTAS ERI'!BI179 -> -5366628.5 | AX45: =+'NOTAS ERI'!BJ179 -> 9843075.7 | AY45: =+'NOTAS ERI'!BK179 -> 6161651.3 | AZ45: =+ERI!BO51 -> #REF! | BA45: =+ERI!BP51 -> #REF! | BB45: =+ERI!BQ51 -> #REF! | BC45: =+ERI!BR51 -> #REF! | BD45: =+'NOTAS ERI'!BP175 -> 2369930 | BE45: =+ERI!BT51 -> #REF! | BF45: =+ERI!BU51 -> #REF! | BH45: =+ERI!BW51 -> 1066515 | BI45: =+ERI!#REF!+ERI!#REF!+ERI!#REF!+ERI!#REF!+ERI!CC47+ERI!CB47+ERI!CA47+ERI!BZ47+ERI!BY47 -> #REF! | BJ45: =+ERI!#REF!+ERI!#REF!+ERI!#REF!+ERI!#REF!+ERI!CC47+ERI!CB47+ERI!CA47+ERI!BZ47 -> #REF! | BK45: =+ERI!#REF!+ERI!#REF!+ERI!#REF!+ERI!#REF!+ERI!CC47+ERI!CB47+ERI!CA47 -> #REF! | BL45: =+'NOTAS ERI'!#REF!+'NOTAS ERI'!#REF!+'NOTAS ERI'!#REF!+'NOTAS ERI'!#REF!+'NOTAS ERI'!BZ175+'NOTAS ERI'!BY175 -> #REF! | BM45: =+'NOTAS ERI'!#REF!+'NOTAS ERI'!#REF!+'NOTAS ERI'!#REF!+'NOTAS ERI'!#REF!+'NOTAS ERI'!BZ175 -> #REF! | BO45: =+'NOTAS ESF'!BK134 -> 0
B47: Total Patrimonio | F47: =SUM(F40:F46) -> 41584411 | H47: =SUM(H40:H46) -> 49330916 | I47: =SUM(I40:I46) -> 43222362 | J47: =SUM(J40:J46) -> 35695440 | K47: =SUM(K40:K46) -> 26038709 | L47: =SUM(L40:L46) -> 15487508 | M47: =SUM(M40:M46) -> 12724984 | N47: =SUM(N40:N46) -> 11942059 | O47: =SUM(O40:O46) -> 11055775 | ... S47: =SUM(S40:S46) -> 13388518 | U47: =SUM(U40:U46) -> 17403284 | V47: =SUM(V40:V46) -> 15836754 | W47: =SUM(W40:W46) -> 14052782 | X47: =SUM(X40:X46) -> 12685272 | Y47: =SUM(Y40:Y46) -> 12401440 | Z47: =SUM(Z40:Z46) -> 11482827 | AA47: =SUM(AA40:AA46) -> 9728771 | AB47: =SUM(AB40:AB46) -> 10139828 | ... AF47: =SUM(AF40:AF46) -> 10317684 | AH47: =SUM(AH40:AH46) -> 9186691.6 | AI47: =SUM(AI40:AI46) -> 13161181 | AJ47: =SUM(AJ40:AJ46) -> 11900652 | AK47: =SUM(AK40:AK46) -> 6827050.6 | AL47: =SUM(AL40:AL46) -> 10293029 | AM47: =SUM(AM40:AM46) -> 11241354 | AN47: =SUM(AN40:AN46) -> 12174757 | AO47: =SUM(AO40:AO46) -> 12406397 | ... AS47: =SUM(AS40:AS46) -> -3164480.5 | AU47: =SUM(AU40:AU46) -> 3357791.5 | AV47: =SUM(AV40:AV46) -> -2286822.5 | AW47: =SUM(AW40:AW46) -> -2299273.5 | AX47: =SUM(AX40:AX46) -> 12910431 | AY47: =SUM(AY40:AY46) -> 9229006.3 | AZ47: =SUM(AZ40:AZ46) -> #REF! | BA47: =SUM(BA40:BA46) -> #REF! | BB47: =SUM(BB40:BB46) -> #REF! | ... BF47: =SUM(BF40:BF46) -> #REF! | BH47: =SUM(BH40:BH46) -> 3066515 | BI47: =SUM(BI40:BI46) -> #REF! | BJ47: =SUM(BJ40:BJ46) -> #REF! | BK47: =SUM(BK40:BK46) -> #REF! | BL47: =SUM(BL40:BL46) -> #REF! | BM47: =SUM(BM40:BM46) -> #REF! | BO47: =SUM(BO40:BO46) -> 2000000
B49: Total Pasivo + Patrimonio | F49: =F36+F47 -> 1.4061731e+08 | H49: =H36+H47 -> 1.458645e+08 | I49: =I36+I47 -> 1.4665313e+08 | J49: =J36+J47 -> 1.2134925e+08 | K49: =K36+K47 -> 1.2162471e+08 | L49: =L36+L47 -> 1.0368991e+08 | M49: =M36+M47 -> 1.0129416e+08 | N49: =N36+N47 -> 93443117 | O49: =O36+O47 -> 1.0192369e+08 | ... S49: =S36+S47 -> 69057330 | U49: =U36+U47 -> 74355715 | V49: =V36+V47 -> 68643331 | W49: =W36+W47 -> 66495137 | X49: =X36+X47 -> 71277754 | Y49: =Y36+Y47 -> 65849265 | Z49: =Z36+Z47 -> 62586229 | AA49: =AA36+AA47 -> 57761111 | AB49: =AB36+AB47 -> 63488667 | ... AF49: =AF36+AF47 -> 48427369 | AH49: =AH36+AH47 -> 40074048 | AI49: =AI36+AI47 -> 69673255 | AJ49: =AJ36+AJ47 -> 71617876 | AK49: =AK36+AK47 -> 54978369 | AL49: =AL36+AL47 -> 61863386 | AM49: =AM36+AM47 -> 63369374 | AN49: =AN36+AN47 -> 1.0299026e+08 | AO49: =AO36+AO47 -> 98234656 | ... AS49: =AS36+AS47 -> 37232001 | AU49: =AU36+AU47 -> 44054429 | AV49: =AV36+AV47 -> 10528394 | AW49: =AW36+AW47 -> 49996276 | AX49: =AX36+AX47 -> 64151629 | AY49: =AY36+AY47 -> 41459709 | AZ49: =AZ36+AZ47 -> #REF! | BA49: =BA36+BA47 -> #REF! | BB49: =BB36+BB47 -> #REF! | ... BF49: =BF36+BF47 -> #REF! | BH49: =BH36+BH47 -> 25306581 | BI49: =BI36+BI47 -> #REF! | BJ49: =BJ36+BJ47 -> #REF! | BK49: =BK36+BK47 -> #REF! | BL49: =BL36+BL47 -> #REF! | BM49: =BM36+BM47 -> #REF! | BO49: =BO36+BO47 -> #REF!
F51: =+F19-F49 -> 0 | H51: =+H19-H49 -> 0 | I51: =+I19-I49 -> 0 | J51: =+J19-J49 -> 0 | K51: =+K19-K49 -> 0 | L51: =+L19-L49 -> 0 | M51: =+M19-M49 -> 0 | N51: =+N19-N49 -> 0 | O51: =+O19-O49 -> 0 | ... S51: =+S19-S49 -> 0 | U51: =+U19-U49 -> 0 | V51: =+V19-V49 -> 0 | W51: =+W19-W49 -> 0 | X51: =+X19-X49 -> 0 | Y51: =+Y19-Y49 -> 0 | Z51: =+Z19-Z49 -> 0 | AA51: =+AA19-AA49 -> 0 | AB51: =+AB19-AB49 -> 0 | ... AF51: =+AF19-AF49 -> 0 | AH51: =+AH19-AH49 -> -0.47352006 | AI51: =+AI19-AI49 -> #REF! | AJ51: =+AJ19-AJ49 -> #REF! | AK51: =+AK19-AK49 -> #REF! | AL51: =+AL19-AL49 -> #REF! | AM51: =+AM19-AM49 -> #REF! | AN51: =+AN19-AN49 -> #REF! | AO51: =+AO19-AO49 -> #REF! | ... AS51: =+AS19-AS49 -> #REF! | AU51: =+AU19-AU49 -> 0 | AV51: =+AV19-AV49 -> 0 | AW51: =+AW19-AW49 -> 0 | AX51: =+AX19-AX49 -> 0 | AY51: =+AY19-AY49 -> 0 | AZ51: =+AZ19-AZ49 -> #REF! | BA51: =+BA19-BA49 -> #REF! | BB51: =+BB19-BB49 -> #REF! | ... BF51: =+BF19-BF49 -> #REF! | BH51: =+BH19-BH49 -> 3.3527613e-08 | BI51: =+BI19-BI49 -> #REF! | BJ51: =+BJ19-BJ49 -> #REF! | BK51: =+BK19-BK49 -> #REF! | BL51: =+BL19-BL49 -> #REF! | BM51: =+BM19-BM49 -> #REF! | BO51: =+BO19-BO49 -> #REF!
B53: Representante Legal
B54: Representante Legal
B58: JIMMY ARCHILA SILVA
B59: Representante Legal

Sheet ERI
B2: =+ESF!B2 -> JELCOM SOLUCIONES EMPRESARIALES SAS
B3: =+ESF!B3 -> NIT. 901360819
B4: ESTADO DE RESULTADOS
B5: PARA LOS PERIODOS TERMINADOS
B7: INGRESOS | C7: Nota | E7: 01.01.2025 | F7: 01.12.2026 | G7: 01.11.2026 | H7: 01.10.2026 | I7: 01.09.2026 | J7: 01.08.2026 | K7: 01.07.2026 | L7: 01.06.2026 | M7: 01.05.2026 | N7: 01.04.2026 | O7: 01.03.2026 | P7: 01.02.2026 | Q7: 01.01.2026 | S7: 01.01.2025 | T7: 01.12.2025 | U7: 01.11.2025 | V7: 01.10.2025 | W7: 01.09.2025 | X7: 01.08.2025 | Y7: 01.07.2025 | Z7: 01.06.2025 | AA7: 01.05.2025 | AB7: 01.04.2025 | AC7: 01.03.2025 | AD7: 01.02.2025 | AE7: 01.01.2025 | AG7: 01.01.2024 | AH7: 01.12.2024 | AI7: 01.11.2024 | AJ7: 01.10.2024 | AK7: 01.09.2024 | AL7: 01.08.2024 | AM7: 01.07.2024 | AN7: 01.06.2024 | AO7: 01.05.2024 | AP7: 01.04.2024 | AQ7: 01.03.2024 | AR7: 01.02.2024 | AS7: 01.01.2024 | AU7: 01.01.2023 | AV7: 01.12.2023 | AW7: 01.11.2023 | AX7: 01.10.2023 | AY7: 01.09.2023 | AZ7: 01.08.2023 | BA7: 01.07.2023 | BB7: 01.06.2023 | BC7: 01.05.2023 | BD7: 01.04.2023 | BE7: 01.03.2023 | BF7: 01.02.2023 | BG7: 01.01.2023 | BI7: 01.01.2022 | BJ7: 01.12.2022 | BK7: 01.11.2022 | BL7: 01.10.2022 | BM7: 01.09.2022 | BN7: 01.08.2022 | BO7: 01.07.2022 | BP7: 01.06.2022 | BQ7: 01.05.2022 | BR7: 01.04.2019 | BS7: 01.03.2020 | BT7: 01.02.2021 | BU7: 01.01.2022 | BW7: 01.01.2021 | BX7: 01.10.2021 | BY7: 01.09.2021 | BZ7: 01.08.2021 | CA7: 01.07.2021 | CB7: 01.06.2021 | CC7: 01.05.2021 | CE7: 01.12.2020 | CF7: 01.12.2017 | CH7: 01.12.2016
E8: 31.12.2025 | F8: 31.12.2026 | G8: 30.11.2026 | H8: 31.10.2026 | I8: 30.09.2026 | J8: 31.08.2026 | K8: 31.07.2026 | L8: 30.06.2026 | M8: 31.05.2026 | N8: 30.04.2026 | O8: 31.03.2026 | P8: 28.02.2026 | Q8: 31.01.2026 | S8: 31.12.2025 | T8: 31.12.2025 | U8: 30.11.2025 | V8: 31.10.2025 | W8: 30.09.2025 | X8: 31.08.2025 | Y8: 31.07.2025 | Z8: 30.06.2025 | AA8: 31.05.2025 | AB8: 30.04.2025 | AC8: 31.03.2025 | AD8: 28.02.2025 | AE8: 31.01.2025 | AG8: 31.12.2024 | AH8: 30.12.2024 | AI8: 30.11.2024 | AJ8: 31.10.2024 | AK8: 30.09.2024 | AL8: 31.08.2024 | AM8: 31.07.2024 | AN8: 30.06.2024 | AO8: 31.05.2024 | AP8: 30.04.2024 | AQ8: 31.03.2024 | AR8: 28.02.2024 | AS8: 31.01.2024 | AU8: 31.12.2023 | AV8: 31.12.2023 | AW8: 30.11.2023 | AX8: 31.10.2023 | AY8: 30.09.2023 | AZ8: 31.08.2023 | BA8: 31.07.2023 | BB8: 30.06.2023 | BC8: 31.05.2023 | BD8: 30.04.2023 | BE8: 31.03.2023 | BF8: 28.02.2023 | BG8: 01.01.2023 | BI8: 31.12.2022 | BJ8: 31.12.2022 | BK8: 30.11.2022 | BL8: 31.10.2022 | BM8: 30.09.2022 | BN8: 30.08.2022 | BO8: 31.07.2022 | BP8: 30.06.2022 | BQ8: 30.05.2022 | BR8: 30.04.2022 | BS8: 31.03.2022 | BT8: 28.02.2022 | BU8: 31.01.2022 | BW8: 31.12.2021 | BX8: 30.10.2021 | BY8: 30.09.2021 | BZ8: 30.08.2021 | CA8: 30.07.2021 | CB8: 30.06.2021 | CC8: 31.05.2021 | CE8: 31.12.2020 | CF8: 31.12.2017 | CH8: 31.12.2016
B10: INGRESOS OPERACIONALES | C10: 12 | E10: =SUM(E12:E13) -> 45023259 | F10: =SUM(F12:F13) -> 0 | G10: =SUM(G12:G13) -> 0 | H10: =SUM(H12:H13) -> 0 | I10: =SUM(I12:I13) -> 0 | J10: =SUM(J12:J13) -> 0 | K10: =SUM(K12:K13) -> 0 | L10: =SUM(L12:L13) -> 0 | ... Q10: =SUM(Q12:Q13) -> 45023259 | S10: =SUM(S12:S13) -> 370322671 | T10: =SUM(T12:T13) -> 41398469 | U10: =SUM(U12:U13) -> 42018469 | V10: =SUM(V12:V13) -> 43654871 | W10: =SUM(W12:W13) -> 42958469 | X10: =SUM(X12:X13) -> 31018469 | Y10: =SUM(Y12:Y13) -> 29178469 | Z10: =SUM(Z12:Z13) -> 28798469 | ... AE10: =SUM(AE12:AE13) -> 1510000 | AG10: =SUM(AG12:AG13) -> 95609587 | AH10: =+AH12+AH13 -> 6910000 | AI10: =+AI12+AI13 -> 7309587 | AJ10: =+AJ12+AJ13 -> 6910000 | AK10: =+AK12+AK13 -> 6910000 | AL10: =+AL12+AL13 -> 7910000 | AM10: =+AM12+AM13 -> 9270000 | AN10: =+AN12+AN13 -> 7020000 | AO10: =+AO12+AO13 -> 9740000 | ... AS10: =+AS12+AS13 -> 8230000 | AU10: =SUM(AU12:AU13) -> 102813014 | AV10: =SUM(AV12:AV13) -> 8185423 | AW10: =SUM(AW12:AW13) -> 8185423 | AX10: =SUM(AX12:AX13) -> 11760000 | AY10: =SUM(AY12:AY13) -> 2360000 | AZ10: =SUM(AZ12:AZ13) -> 5890000 | BA10: =SUM(BA12:BA13) -> 6360000 | BB10: =SUM(BB12:BB13) -> 7080000 | ... BG10: =SUM(BG12:BG13) -> 2940168 | BI10: =SUM(BI12:BI13) -> 47784225 | BJ10: =SUM(BJ12:BJ13) -> 6640168 | BK10: =SUM(BK12:BK13) -> 1970000 | BL10: =SUM(BL12:BL13) -> 3795000 | BM10: =SUM(BM12:BM13) -> 18668403 | BN10: =SUM(BN12:BN13) -> 11595735 | BO10: =SUM(BO12:BO13) -> 0 | BP10: =SUM(BP12:BP13) -> 0 | ... BU10: =SUM(BU12:BU13) -> 1000000 | BW10: =SUM(BW12:BW13) -> 18444000 | BX10: =SUM(BX12:BX13) -> #REF! | BY10: =SUM(BY12:BY13) -> #REF! | BZ10: =SUM(BZ12:BZ13) -> #REF! | CA10: =SUM(CA12:CA13) -> #REF! | CB10: =SUM(CB12:CB13) -> #REF! | CC10: =SUM(CC12:CC13) -> #REF! | CE10: =SUM(CE12:CE13) -> 0 | CF10: =SUM(CF12:CF13) -> #REF! | CH10: =SUM(CH12:CH13) -> #REF!
B12: =+'NOTAS ERI'!A37 -> Actividades de Centro de Llamadas | E12: =SUM(F12:Q12) -> 66237137 | F12: =+'NOTAS ERI'!C10 -> 0 | G12: =+'NOTAS ERI'!D10 -> 0 | H12: =+'NOTAS ERI'!E10 -> 0 | I12: =+'NOTAS ERI'!F10 -> 0 | J12: =+'NOTAS ERI'!G10 -> 0 | K12: =+'NOTAS ERI'!H10 -> 0 | L12: =+'NOTAS ERI'!I10 -> 0 | M12: =+'NOTAS ERI'!J10 -> 0 | ... Q12: =+'NOTAS ERI'!N10 -> 66237137 | S12: =SUM(T12:AE12) -> 399036750 | T12: =+'NOTAS ERI'!Q10 -> 41398469 | U12: =+'NOTAS ERI'!R10 -> 42018469 | V12: =+'NOTAS ERI'!S10 -> 43654871 | W12: =+'NOTAS ERI'!T10 -> 42958469 | X12: =+'NOTAS ERI'!U10 -> 31018469 | Y12: =+'NOTAS ERI'!V10 -> 56826938 | Z12: =+'NOTAS ERI'!W10 -> 28798469 | AA12: =+'NOTAS ERI'!X10 -> 26614079 | ... AE12: =+'NOTAS ERI'!AB10 -> 1510000 | AG12: =SUM(AH12:AS12) -> 96769587 | AH12: =+'NOTAS ERI'!AE10 -> 6910000 | AI12: =+'NOTAS ERI'!AF10 -> 7309587 | AJ12: =+'NOTAS ERI'!AG10 -> 7530000 | AK12: =+'NOTAS ERI'!AH10 -> 6910000 | AL12: =+'NOTAS ERI'!AI10 -> 7910000 | AM12: =+'NOTAS ERI'!AJ10 -> 9270000 | AN12: =+'NOTAS ERI'!AK10 -> 7020000 | AO12: =+'NOTAS ERI'!AL10 -> 9740000 | ... AS12: =+'NOTAS ERI'!AP10 -> 8230000 | AU12: =SUM(AV12:BG12) -> 105983014 | AV12: =+'NOTAS ERI'!AS10 -> 8185423 | AW12: =+'NOTAS ERI'!AT10 -> 8185423 | AX12: =+'NOTAS ERI'!AU10 -> 13260000 | AY12: =+'NOTAS ERI'!AV10 -> 2360000 | AZ12: =+'NOTAS ERI'!AW10 -> 6360000 | BA12: =+'NOTAS ERI'!AX10 -> 6360000 | BB12: =+'NOTAS ERI'!AY10 -> 7080000 | BC12: =+'NOTAS ERI'!AZ10 -> 42140000 | ... BG12: =+'NOTAS ERI'!BD10 -> 2940168 | BI12: =SUM(BJ12:BU12) -> 51027964 | BJ12: =+'NOTAS ERI'!BG10 -> 6640168 | BK12: =+'NOTAS ERI'!BH10 -> 1970000 | BL12: =+'NOTAS ERI'!BI10 -> 3795000 | BM12: =+'NOTAS ERI'!BJ10 -> 18668403 | BN12: =+'NOTAS ERI'!BK10 -> 12733235 | BO12: =+'NOTAS ERI'!BL10 -> 0 | BP12: =+'NOTAS ERI'!BM10 -> 0 | BQ12: =+'NOTAS ERI'!BN10 -> 1106239 | ... BU12: =+'NOTAS ERI'!BR10 -> 1000000 | BW12: =+'NOTAS ERI'!BT10 -> 29847361 | BX12: =+'NOTAS ERI'!BU37 -> 0 | BY12: =+'NOTAS ERI'!BV37 -> 0 | BZ12: =+'NOTAS ERI'!BW37 -> 0 | CA12: =+'NOTAS ERI'!BX37 -> 0 | CB12: =+'NOTAS ERI'!BY37 -> 0 | CC12: =+'NOTAS ERI'!BZ37 -> 0 | CE12: =+'NOTAS ERI'!CB37 -> 0 | CF12: =+'NOTAS ERI'!#REF! -> #REF! | CH12: =+'NOTAS ERI'!#REF! -> #REF!
B13: Devoluciones y Descuentos | E13: =SUM(F13:Q13) -> -21213878 | F13: =+'NOTAS ERI'!C38 -> 0 | G13: =+'NOTAS ERI'!D38 -> 0 | H13: =+'NOTAS ERI'!E38 -> 0 | I13: =+'NOTAS ERI'!F38 -> 0 | J13: =+'NOTAS ERI'!G38 -> 0 | K13: =+'NOTAS ERI'!H38 -> 0 | L13: =+'NOTAS ERI'!I38 -> 0 | M13: =+'NOTAS ERI'!J38 -> 0 | ... Q13: =+'NOTAS ERI'!N38 -> -21213878 | S13: =SUM(T13:AE13) -> -28714079 | T13: =+'NOTAS ERI'!Q38 -> 0 | U13: =+'NOTAS ERI'!R38 -> 0 | V13: =+'NOTAS ERI'!S38 -> 0 | W13: =+'NOTAS ERI'!T38 -> 0 | X13: =+'NOTAS ERI'!U38 -> 0 | Y13: =+'NOTAS ERI'!V38 -> -27648469 | Z13: =+'NOTAS ERI'!W38 -> 0 | AA13: =+'NOTAS ERI'!X38 -> 0 | ... AE13: =+'NOTAS ERI'!AB38 -> 0 | AG13: =+'NOTAS ERI'!AD38 -> -1160000 | AH13: =+'NOTAS ERI'!AE38 -> 0 | AI13: =+'NOTAS ERI'!AF38 -> 0 | AJ13: =+'NOTAS ERI'!AG38 -> -620000 | AK13: =+'NOTAS ERI'!AH38 -> 0 | AL13: =+'NOTAS ERI'!AI38 -> 0 | AM13: =+'NOTAS ERI'!AJ38 -> 0 | AN13: =+'NOTAS ERI'!AK38 -> 0 | ... AS13: =+'NOTAS ERI'!AP38 -> 0 | AU13: =SUM(AV13:BG13) -> -3170000 | AV13: =+'NOTAS ERI'!AS38 -> 0 | AW13: =+'NOTAS ERI'!AT38 -> 0 | AX13: =+'NOTAS ERI'!AU38 -> -1500000 | AY13: =+'NOTAS ERI'!AV38 -> 0 | AZ13: =+'NOTAS ERI'!AW38 -> -470000 | BA13: =+'NOTAS ERI'!AX38 -> 0 | BB13: =+'NOTAS ERI'!AY38 -> 0 | BC13: =+'NOTAS ERI'!AZ38 -> -200000 | ... BG13: =+'NOTAS ERI'!BD38 -> 0 | BI13: =SUM(BJ13:BU13) -> -3243739 | BJ13: =+'NOTAS ERI'!BG38 -> 0 | BK13: =+'NOTAS ERI'!BH38 -> 0 | BL13: =+'NOTAS ERI'!BI38 -> 0 | BM13: =+'NOTAS ERI'!BJ38 -> 0 | BN13: =+'NOTAS ERI'!BK38 -> -1137500 | BO13: =+'NOTAS ERI'!BL38 -> 0 | BP13: =+'NOTAS ERI'!BM38 -> 0 | BQ13: =+'NOTAS ERI'!BN38 -> -1106239 | ... BU13: =+'NOTAS ERI'!BR38 -> 0 | BW13: =+'NOTAS ERI'!BT38 -> -11403361 | BX13: =+'NOTAS ERI'!#REF! -> #REF! | BY13: =+'NOTAS ERI'!#REF! -> #REF! | BZ13: =+'NOTAS ERI'!#REF! -> #REF! | CA13: =+'NOTAS ERI'!#REF! -> #REF! | CB13: =+'NOTAS ERI'!#REF! -> #REF! | CC13: =+'NOTAS ERI'!#REF! -> #REF! | CE13: 0 | CF13: =+'NOTAS ERI'!#REF! -> #REF! | CH13: =+'NOTAS ERI'!#REF! -> #REF!
E14: =SUM(R14:AM14) -> 0 | F14: =SUM(H14:AC14) -> 0 | G14: =SUM(I14:AD14) -> 0 | H14: =SUM(J14:AE14) -> 0 | I14: =SUM(K14:AF14) -> 0 | J14: =SUM(L14:AG14) -> 0 | K14: =SUM(M14:AH14) -> 0 | L14: =SUM(N14:AI14) -> 0 | M14: =SUM(O14:AJ14) -> 0 | ... Q14: =SUM(S14:AN14) -> 0 | S14: =SUM(T14:AO14) -> 0 | T14: =SUM(U14:AF14) -> 0 | U14: =SUM(V14:AG14) -> 0 | V14: =SUM(W14:AH14) -> 0 | W14: =SUM(X14:AI14) -> 0 | X14: =SUM(Y14:AJ14) -> 0 | Y14: =SUM(Z14:AK14) -> 0 | Z14: =SUM(AA14:AL14) -> 0 | AA14: =SUM(AB14:AM14) -> 0 | ... AE14: =SUM(AF14:AQ14) -> 0 | AG14: =SUM(AH14:AS14) -> 0 | AU14: =SUM(BB14:BG14) -> 0
B15: INGRESOS NO OPERACIONALES | C15: 15 | E15: =SUM(E17) -> 0 | F15: =SUM(F17) -> 0 | G15: =SUM(G17) -> 0 | H15: =SUM(H17) -> 0 | I15: =SUM(I17) -> 0 | J15: =SUM(J17) -> 0 | K15: =SUM(K17) -> 0 | L15: =SUM(L17) -> 0 | ... Q15: =SUM(Q17) -> 0 | S15: =SUM(S17) -> 2492.75 | T15: =SUM(T17) -> 0 | U15: =SUM(U17) -> 0 | V15: =SUM(V17) -> 0 | W15: =SUM(W17) -> 0 | X15: =SUM(X17) -> 0 | Y15: =SUM(Y17) -> 0 | Z15: =SUM(Z17) -> 0 | ... AE15: =SUM(AE17) -> 840.75 | AG15: =SUM(AG17) -> 2182 | AH15: =+AH16+AH18+AH17 -> 638 | AI15: =+AI16+AI18+AI17 -> 0 | AJ15: =+AJ16+AJ18+AJ17 -> 0 | AK15: =+AK16+AK18+AK17 -> 879 | AL15: =+AL16+AL18+AL17 -> 0 | AM15: =+AM16+AM18+AM17 -> 0 | AN15: =+AN16+AN18+AN17 -> 369 | AO15: =+AO16+AO18+AO17 -> 296 | ... AS15: =+AS16+AS18+AS17 -> 0 | AU15: =SUM(AU17) -> 200 | AV15: =+AV16+AV18+AV17 -> 0 | AW15: =+AW16+AW18+AW17 -> 0 | AX15: =+AX16+AX18+AX17 -> 0 | AY15: =+AY16+AY18+AY17 -> 0 | AZ15: =+AZ16+AZ18+AZ17 -> 400 | BA15: =+BA16+BA18+BA17 -> 0 | BB15: =+BB16+BB18 -> 0 | BC15: =+BC16+BC18 -> 0 | BD15: =+BD16+BD18 -> 0 | BE15: =+BE16+BE18 -> 0 | BF15: =+BF16+BF18 -> 0 | BG15: =+BG16+BG18 -> 0 | BI15: =+BI16+BI18 -> 0 | BJ15: =+BJ16+BJ18 -> 0 | BK15: =+BK16+BK18 -> 0 | BL15: =+BL16+BL18 -> 0 | BM15: =+BM16+BM18 -> 0 | BN15: =+BN16+BN18 -> 0 | BO15: =+BO16+BO18 -> 0 | BP15: =+BP16+BP18 -> 0 | ... BU15: =+BU16+BU18 -> 0 | BW15: =+BW16+BW18 -> 0 | BX15: =+BX16+BX18 -> 0 | BY15: =+BY16+BY18 -> 0 | BZ15: =+BZ16+BZ18 -> 0 | CA15: =+CA16+CA18 -> 0 | CB15: =+CB16+CB18 -> 0 | CC15: =+CC16+CC18 -> 0 | CE15: =+CE16+CE18 -> #REF! | CF15: =+CF16+CF18 -> #REF! | CH15: =+CH16 -> #REF!
B16: Subsidio de Nomina | E16: =SUM(R16:AM16) -> 0 | F16: =SUM(H16:AC16) -> 0 | G16: =SUM(I16:AD16) -> 0 | H16: =SUM(J16:AE16) -> 0 | I16: =SUM(K16:AF16) -> 0 | J16: =SUM(L16:AG16) -> 0 | K16: =SUM(M16:AH16) -> 0 | L16: =SUM(N16:AI16) -> 0 | M16: =SUM(O16:AJ16) -> 0 | ... Q16: =SUM(S16:AN16) -> 0 | S16: =SUM(T16:AO16) -> 0 | T16: =SUM(U16:AF16) -> 0 | U16: =SUM(V16:AG16) -> 0 | V16: =SUM(W16:AH16) -> 0 | W16: =SUM(X16:AI16) -> 0 | X16: =SUM(Y16:AJ16) -> 0 | Y16: =SUM(Z16:AK16) -> 0 | Z16: =SUM(AA16:AL16) -> 0 | AA16: =SUM(AB16:AM16) -> 0 | ... AE16: =SUM(AF16:AQ16) -> 0 | AG16: =SUM(AH16:AS16) -> 0 | AU16: =SUM(BB16:BG16) -> 0 | AZ16: =+'NOTAS ERI'!AX41 -> 200 | BA16: =+'NOTAS ERI'!AY41 -> 0 | BB16: =+'NOTAS ERI'!AZ41 -> 0 | BC16: =+'NOTAS ERI'!BA41 -> 0 | BD16: =+'NOTAS ERI'!BB41 -> 0 | BE16: =+'NOTAS ERI'!BC41 -> 0 | BF16: =+'NOTAS ERI'!BD41 -> 0 | BG16: =+'NOTAS ERI'!BE41 -> 0 | BI16: =+'NOTAS ERI'!BF41 -> 0 | BJ16: =+'NOTAS ERI'!BG41 -> 0 | BK16: =+'NOTAS ERI'!BH41 -> 0 | BL16: =+'NOTAS ERI'!BI41 -> 0 | BM16: =+'NOTAS ERI'!BJ41 -> 0 | BN16: =+'NOTAS ERI'!BK41 -> 0 | BO16: =+'NOTAS ERI'!BL41 -> 0 | BP16: =+'NOTAS ERI'!BM41 -> 0 | ... BU16: =+'NOTAS ERI'!BR41 -> 0 | BW16: =+'NOTAS ERI'!BT41 -> 0 | BX16: =+'NOTAS ERI'!BU41 -> 0 | BY16: =+'NOTAS ERI'!BV41 -> 0 | BZ16: =+'NOTAS ERI'!BW41 -> 0 | CA16: =+'NOTAS ERI'!BX41 -> 0 | CB16: =+'NOTAS ERI'!BY41 -> 0 | CC16: =+'NOTAS ERI'!BZ41 -> 0 | CE16: =+'NOTAS ERI'!CB41 -> 0 | CF16: =+'NOTAS ERI'!#REF! -> #REF! | CH16: =+'NOTAS ERI'!#REF! -> #REF!
B17: Ajuste al peso | E17: =SUM(F17:Q17) -> 0 | F17: =+'NOTAS ERI'!C41 -> 0 | G17: =+'NOTAS ERI'!D41 -> 0 | H17: =+'NOTAS ERI'!E41 -> 0 | I17: =+'NOTAS ERI'!F41 -> 0 | J17: =+'NOTAS ERI'!G41 -> 0 | K17: =+'NOTAS ERI'!H41 -> 0 | L17: =+'NOTAS ERI'!I41 -> 0 | M17: =+'NOTAS ERI'!J41 -> 0 | ... Q17: =+'NOTAS ERI'!N41 -> 0 | S17: =SUM(T17:AE17) -> 2492.75 | T17: =+'NOTAS ERI'!Q41 -> 0 | U17: =+'NOTAS ERI'!R41 -> 0 | V17: =+'NOTAS ERI'!S41 -> 0 | W17: =+'NOTAS ERI'!T41 -> 0 | X17: =+'NOTAS ERI'!U41 -> 0 | Y17: =+'NOTAS ERI'!V41 -> 0 | Z17: =+'NOTAS ERI'!W41 -> 0 | AA17: =+'NOTAS ERI'!X41 -> 839 | ... AE17: =+'NOTAS ERI'!AB41 -> 840.75 | AG17: =SUM(AH17:AS17) -> 2182 | AH17: =+'NOTAS ERI'!AE41 -> 638 | AK17: =+'NOTAS ERI'!AH41 -> 879 | AN17: =+'NOTAS ERI'!AK41 -> 369 | AO17: =+'NOTAS ERI'!AL41 -> 296 | AU17: =SUM(AV17:BG17) -> 200 | AZ17: =+'NOTAS ERI'!AX42 -> 200
B18: Reintegro Costos y gastos | E18: =SUM(AE18:AM18) -> 0 | F18: =SUM(U18:AC18) -> 0 | G18: =SUM(V18:AD18) -> 0 | H18: =SUM(W18:AE18) -> 0 | I18: =SUM(X18:AF18) -> 0 | J18: =SUM(Y18:AG18) -> 0 | K18: =SUM(Z18:AH18) -> 0 | L18: =SUM(AA18:AI18) -> 0 | M18: =SUM(AB18:AJ18) -> 0 | ... Q18: =SUM(AF18:AN18) -> 0 | S18: =SUM(AG18:AO18) -> 0 | T18: =SUM(X18:AF18) -> 0 | U18: =SUM(Y18:AG18) -> 0 | V18: =SUM(Z18:AH18) -> 0 | W18: =SUM(AA18:AI18) -> 0 | X18: =SUM(AB18:AJ18) -> 0 | Y18: =SUM(AC18:AK18) -> 0 | Z18: =SUM(AD18:AL18) -> 0 | AA18: =SUM(AE18:AM18) -> 0 | ... AE18: =SUM(AI18:AQ18) -> 0 | AG18: =SUM(AK18:AS18) -> 0 | AH18: 0 | AI18: 0 | AJ18: 0 | AK18: 0 | AL18: 0 | AM18: 0 | AN18: 0 | AO18: 0 | AP18: 0 | AQ18: 0 | AR18: 0 | AS18: 0 | AU18: =SUM(BB18:BG18) -> 0 | AV18: 0 | AW18: 0 | AX18: 0 | AY18: 0 | AZ18: 0 | BA18: 0 | BB18: 0 | BC18: 0 | BD18: 0 | BE18: 0 | BF18: 0 | BG18: 0 | BI18: 0 | BJ18: 0 | BK18: 0 | BL18: 0 | BM18: 0 | BN18: 0 | BO18: 0 | BP18: 0 | BQ18: 0 | BR18: 0 | BS18: 0 | BT18: 0 | BU18: 0 | BW18: 0 | BX18: 0 | BY18: 0 | BZ18: 0 | CA18: 0 | CB18: 0 | CC18: 0 | CE18: =+'NOTAS ERI'!#REF! -> #REF! | CF18: 0
AU19: =SUM(BB19:BG19) -> 0
B20: TOTAL INGRESOS | E20: =+E10+E15 -> 45023259 | F20: =+F10+F15 -> 0 | G20: =+G10+G15 -> 0 | H20: =+H10+H15 -> 0 | I20: =+I10+I15 -> 0 | J20: =+J10+J15 -> 0 | K20: =+K10+K15 -> 0 | L20: =+L10+L15 -> 0 | ... Q20: =+Q10+Q15 -> 45023259 | S20: =+S10+S15 -> 3.7032516e+08 | T20: =+T10+T15 -> 41398469 | U20: =+U10+U15 -> 42018469 | V20: =+V10+V15 -> 43654871 | W20: =+W10+W15 -> 42958469 | X20: =+X10+X15 -> 31018469 | Y20: =+Y10+Y15 -> 29178469 | Z20: =+Z10+Z15 -> 28798469 | ... AE20: =+AE10+AE15 -> 1510840.8 | AG20: =+AG10+AG15 -> 95611769 | AH20: =+'NOTAS ERI'!AE44 -> 6910638 | AI20: =+'NOTAS ERI'!AF44 -> 7309587 | AJ20: =+'NOTAS ERI'!AG44 -> 6910000 | AK20: =+'NOTAS ERI'!AH44 -> 6910879 | AL20: =+'NOTAS ERI'!AI44 -> 7910000 | AM20: =+AM10+AM15 -> 9270000 | AN20: =+AN10+AN15 -> 7020369 | AO20: =+AO10+AO15 -> 9740296 | AP20: =+AP10+AP15 -> 7020000 | AQ20: =+AQ10+AQ15 -> 10820000 | AR20: =+AR10+AR15 -> 7560000 | AS20: =+AS10+AS15 -> 8230000 | AU20: =+AU10+AU15 -> 102813214 | AV20: =+AV10+AV15 -> 8185423 | AW20: =+AW10+AW15 -> 8185423 | AX20: =+AX10+AX15 -> 11760000 | AY20: =+AY10+AY15 -> 2360000 | AZ20: =+AZ10+AZ15 -> 5890400 | BA20: =+BA10+BA15 -> 6360000 | BB20: =+BB10+BB15 -> 7080000 | ... BG20: =+BG10+BG15 -> 2940168 | BI20: =+BI10+BI15 -> 47784225 | BJ20: =+BJ10+BJ15 -> 6640168 | BK20: =+BK10+BK15 -> 1970000 | BL20: =+BL10+BL15 -> 3795000 | BM20: =+BM10+BM15 -> 18668403 | BN20: =+BN10+BN15 -> 11595735 | BO20: =+BO10+BO15 -> 0 | BP20: =+BP10+BP15 -> 0 | ... BU20: =+BU10+BU15 -> 1000000 | BW20: =+BW10+BW15 -> 18444000 | BX20: =+BX10+BX15 -> #REF! | BY20: =+BY10+BY15 -> #REF! | BZ20: =+BZ10+BZ15 -> #REF! | CA20: =+CA10+CA15 -> #REF! | CB20: =+CB10+CB15 -> #REF! | CC20: =+CC10+CC15 -> #REF! | CE20: =+CE10+CE15 -> #REF! | CF20: =+CF10+CF15 -> #REF! | CH20: =+CH10+CH16 -> #REF!
AU21: =SUM(BB21:BG21) -> 0
AU22: =SUM(BB22:BG22) -> 0
B23: UTILIDAD OPERACIONAL | E23: =+E20 -> 45023259 | F23: =+F20 -> 0 | G23: =+G20 -> 0 | H23: =+H20 -> 0 | I23: =+I20 -> 0 | J23: =+J20 -> 0 | K23: =+K20 -> 0 | L23: =+L20 -> 0 | ... Q23: =+Q20 -> 45023259 | S23: =+S20 -> 3.7032516e+08 | T23: =+T20 -> 41398469 | U23: =+U20 -> 42018469 | V23: =+V20 -> 43654871 | W23: =+W20 -> 42958469 | X23: =+X20 -> 31018469 | Y23: =+Y20 -> 29178469 | Z23: =+Z20 -> 28798469 | ... AE23: =+AE20 -> 1510840.8 | AG23: =+AG20 -> 95611769 | AH23: =+AH20 -> 6910638 | AI23: =+AI20 -> 7309587 | AJ23: =+AJ20 -> 6910000 | AK23: =+AK20 -> 6910879 | AL23: =+AL20 -> 7910000 | AM23: =+AM20 -> 9270000 | AN23: =+AN20 -> 7020369 | ... AS23: =+AS20 -> 8230000 | AU23: =+AU20 -> 102813214 | AV23: =+AV20 -> 8185423 | AW23: =+AW20 -> 8185423 | AX23: =+AX20 -> 11760000 | AY23: =+AY20 -> 2360000 | AZ23: =+AZ20 -> 5890400 | BA23: =+BA20 -> 6360000 | BB23: =+BB20 -> 7080000 | ... BG23: =+BG20 -> 2940168 | BI23: =+BI20 -> 47784225 | BJ23: =+BJ20 -> 6640168 | BK23: =+BK20 -> 1970000 | BL23: =+BL20 -> 3795000 | BM23: =+BM20 -> 18668403 | BN23: =+BN20 -> 11595735 | BO23: =+BO20 -> 0 | BP23: =+BP20 -> 0 | ... BU23: =+BU20 -> 1000000 | BW23: =+BW20 -> 18444000 | BX23: =+BX20 -> #REF! | BY23: =+BY20 -> #REF! | BZ23: =+BZ20 -> #REF! | CA23: =+CA20 -> #REF! | CB23: =+CB20 -> #REF! | CC23: =+CC20 -> #REF! | CE23: =+CE20 -> #REF! | CF23: =+CF20 -> #REF! | CH23: =+CH20 -> #REF!
AU24: =SUM(BB24:BG24) -> 0
AU25: =SUM(BB25:BG25) -> 0
B26: GASTOS DE ADMINISTRACION | C26: 13 | E26: =SUM(E27:E39) -> 52324866 | F26: =SUM(F27:F39) -> 0 | G26: =SUM(G27:G39) -> 0 | H26: =SUM(H27:H39) -> 0 | I26: =SUM(I27:I39) -> 0 | J26: =SUM(J27:J39) -> 0 | K26: =SUM(K27:K39) -> 0 | L26: =SUM(L27:L39) -> 0 | ... Q26: =SUM(Q27:Q39) -> 52324866 | S26: =SUM(S27:S39) -> 307545073 | T26: =SUM(T27:T39) -> 31453969 | U26: =SUM(U27:U39) -> 30123840 | V26: =SUM(V27:V39) -> 28240530 | W26: =SUM(W27:W39) -> 26333745 | X26: =SUM(X27:X39) -> 26427628 | Y26: =SUM(Y27:Y39) -> 27604064 | Z26: =SUM(Z27:Z39) -> 27002069 | ... AE26: =SUM(AE27:AE39) -> 7496371 | AG26: =SUM(AG27:AG39) -> 79716729 | AH26: =SUM(AH27:AH38) -> 4303506 | AI26: =SUM(AI27:AI38) -> 4349284 | AJ26: =SUM(AJ27:AJ38) -> 4568899 | AK26: =SUM(AK27:AK38) -> 6292759 | AL26: =SUM(AL27:AL38) -> 6292759 | AM26: =SUM(AM27:AM38) -> 6386179.2 | AN26: =SUM(AN27:AN38) -> 6544793 | AO26: =SUM(AO27:AO38) -> 8358309.7 | ... AS26: =SUM(AS27:AS38) -> 6321076 | AU26: =SUM(AU27:AU39) -> 90396886 | AV26: =SUM(AV27:AV38) -> 8962817 | AW26: =SUM(AW27:AW38) -> 6730050.1 | AX26: =SUM(AX27:AX38) -> 6549541 | AY26: =SUM(AY27:AY38) -> 5670950 | AZ26: =SUM(AZ27:AZ38) -> 6701895.1 | BA26: =SUM(BA27:BA38) -> 6825244 | BB26: =SUM(BB27:BB38) -> 7165691 | BC26: =SUM(BC27:BC38) -> 6568550 | ... BG26: =SUM(BG27:BG38) -> 9316704 | BI26: =SUM(BI27:BI39) -> 47493789 | BJ26: =+BJ28+BJ33+BJ34+BJ36+BJ38 -> #REF! | BK26: =+BK28+BK33+BK34+BK36+BK38 -> #REF! | BL26: =+BL28+BL33+BL34+BL36+BL38 -> #REF! | BM26: =+BM28+BM33+BM34+BM36+BM38 -> #REF! | BN26: =+BN28+BN33+BN34+BN36+BN38 -> #REF! | BO26: =+BO28+BO33+BO34+BO36+BO38 -> #REF! | BP26: =+BP28+BP33+BP34+BP36+BP38 -> #REF! | BQ26: =+BQ28+BQ33+BQ34+BQ36+BQ38 -> #REF! | ... BT26: =+BT28+BT33+BT34+BT36+BT38 -> #REF! | BU26: =+BU28+BU33+BU34+BU36+BU38+BU35+BU37 -> #REF! | BW26: =SUM(BW27:BW38) -> #REF! | BX26: =SUM(BX27:BX38) -> #REF! | BY26: =SUM(BY27:BY38) -> #REF! | BZ26: =SUM(BZ27:BZ38) -> #REF! | CA26: =SUM(CA27:CA38) -> #REF! | CB26: =SUM(CB27:CB38) -> #REF! | CC26: =SUM(CC27:CC38) -> #REF! | CE26: =SUM(CE27:CE38) -> #REF! | CF26: =SUM(CF27:CF38) -> #REF! | CH26: =SUM(CH27:CH38) -> #REF!
B28: Gastos de Personal | E28: =SUM(F28:Q28) -> 28343153 | F28: =+'NOTAS ERI'!C48 -> 0 | G28: =+'NOTAS ERI'!D48 -> 0 | H28: =+'NOTAS ERI'!E48 -> 0 | I28: =+'NOTAS ERI'!F48 -> 0 | J28: =+'NOTAS ERI'!G48 -> 0 | K28: =+'NOTAS ERI'!H48 -> 0 | L28: =+'NOTAS ERI'!I48 -> 0 | M28: =+'NOTAS ERI'!J48 -> 0 | ... Q28: =+'NOTAS ERI'!N48 -> 28343153 | S28: =SUM(T28:AE28) -> 274839697 | T28: =+'NOTAS ERI'!Q48 -> 25704974 | U28: =+'NOTAS ERI'!R48 -> 25253559 | V28: =+'NOTAS ERI'!S48 -> 25200857 | W28: =+'NOTAS ERI'!T48 -> 24705084 | X28: =+'NOTAS ERI'!U48 -> 25034984 | Y28: =+'NOTAS ERI'!V48 -> 25453384 | Z28: =+'NOTAS ERI'!W48 -> 24717866 | AA28: =+'NOTAS ERI'!X48 -> 25225031 | ... AE28: =+'NOTAS ERI'!AB48 -> 4734864 | AG28: =SUM(AH28:AS28) -> 78133865 | AH28: =+'NOTAS ERI'!AE48 -> 4303506 | AI28: =+'NOTAS ERI'!AF48 -> 4303506 | AJ28: =+'NOTAS ERI'!AG48 -> 4568899 | AK28: =+'NOTAS ERI'!AH48 -> 6292759 | AL28: =+'NOTAS ERI'!AI48 -> 6292759 | AM28: =+'NOTAS ERI'!AJ48 -> 6292759 | AN28: =+'NOTAS ERI'!AK48 -> 6528793 | AO28: =+'NOTAS ERI'!AL48 -> 8282012 | ... AS28: =+'NOTAS ERI'!AP48 -> 6292760 | AU28: =SUM(AV28:BG28) -> 61808180 | AV28: =+'NOTAS ERI'!AS48 -> 5656536 | AW28: =+'NOTAS ERI'!AT48 -> 5587989 | AX28: =+'NOTAS ERI'!AU48 -> 5678706 | AY28: =+'NOTAS ERI'!AV48 -> 5204740 | AZ28: =+'NOTAS ERI'!AW48 -> 5628594 | BA28: =+'NOTAS ERI'!AX48 -> 3793838 | BB28: =+'NOTAS ERI'!AY48 -> 4758686 | BC28: =+'NOTAS ERI'!AZ48 -> 3793838 | ... BG28: =+'NOTAS ERI'!BD48 -> 5232130 | BI28: =+'NOTAS ERI'!BF48 -> 44303847 | BJ28: =+'NOTAS ERI'!BG48 -> 1751117.4 | BK28: =+'NOTAS ERI'!BH48 -> 7284177.5 | BL28: =+'NOTAS ERI'!BI48 -> 8335077.5 | BM28: =+'NOTAS ERI'!BJ48 -> 8396593.7 | BN28: =+'NOTAS ERI'!BK48 -> 5226039.7 | BO28: =+'NOTAS ERI'!BL48 -> 672313.55 | BP28: =+'NOTAS ERI'!BM48 -> 0 | ... BU28: =+'NOTAS ERI'!BR48 -> 3042927.4 | BW28: =+'NOTAS ERI'!BT48 -> 17377485 | BX28: =+'NOTAS ERI'!BU48 -> 17377485 | BY28: =+'NOTAS ERI'!BV48 -> 0 | BZ28: =+'NOTAS ERI'!BW48 -> 0 | CA28: =+'NOTAS ERI'!BX48 -> 0 | CB28: =+'NOTAS ERI'!BY48 -> 0 | CC28: =+'NOTAS ERI'!BZ48 -> 0 | CE28: =+'NOTAS ERI'!CB48 -> 0 | CF28: =+'NOTAS ERI'!#REF! -> #REF! | CH28: =+'NOTAS ERI'!#REF! -> #REF!
B29: Contribuciones y afiliaciones | E29: =SUM(F29:Q29) -> 0 | F29: =+'NOTAS ERI'!C83 -> 0 | G29: =+'NOTAS ERI'!D83 -> 0 | H29: =+'NOTAS ERI'!E83 -> 0 | I29: =+'NOTAS ERI'!F83 -> 0 | J29: =+'NOTAS ERI'!G83 -> 0 | K29: =+'NOTAS ERI'!H83 -> 0 | L29: =+'NOTAS ERI'!I83 -> 0 | M29: =+'NOTAS ERI'!J83 -> 0 | ... Q29: =+'NOTAS ERI'!N83 -> 0 | S29: =SUM(T29:AE29) -> 94000 | T29: =+'NOTAS ERI'!Q83 -> 0 | U29: =+'NOTAS ERI'!R83 -> 0 | V29: =+'NOTAS ERI'!S83 -> 0 | W29: =+'NOTAS ERI'!T83 -> 0 | X29: =+'NOTAS ERI'!U83 -> 0 | Y29: =+'NOTAS ERI'!V83 -> 0 | Z29: =+'NOTAS ERI'!W83 -> 0 | AA29: =+'NOTAS ERI'!X83 -> 0 | ... AE29: =+'NOTAS ERI'!AB83 -> 44000 | AG29: =SUM(AH29:AS29) -> 0 | AH29: =+'NOTAS ERI'!AE84 -> 0 | AI29: =+'NOTAS ERI'!AF84 -> 0 | AJ29: =+'NOTAS ERI'!AG84 -> 0 | AK29: =+'NOTAS ERI'!AH84 -> 0 | AL29: =+'NOTAS ERI'!AI84 -> 0 | AM29: =+'NOTAS ERI'!AJ84 -> 0 | AN29: =+'NOTAS ERI'!AK84 -> 0 | AO29: =+'NOTAS ERI'!AL84 -> 0 | ... AS29: =+'NOTAS ERI'!AP84 -> 0 | AU29: =SUM(AV29:BG29) -> 480000 | AV29: =+'NOTAS ERI'!AS84 -> 40000 | AW29: =+'NOTAS ERI'!AT84 -> 40000 | AX29: =+'NOTAS ERI'!AU84 -> 40000 | AY29: =+'NOTAS ERI'!AV84 -> 40000 | AZ29: =+'NOTAS ERI'!AW84 -> 40000 | BA29: =+'NOTAS ERI'!AX84 -> 40000 | BB29: =+'NOTAS ERI'!AY84 -> 40000 | BC29: =+'NOTAS ERI'!AZ84 -> 40000 | ... BG29: =+'NOTAS ERI'!BD84 -> 40000 | BI29: =SUM(BJ29:BU29) -> 480000 | BJ29: =+'NOTAS ERI'!BG83 -> 40000 | BK29: =+'NOTAS ERI'!BH83 -> 40000 | BL29: =+'NOTAS ERI'!BI83 -> 40000 | BM29: =+'NOTAS ERI'!BJ83 -> 40000 | BN29: =+'NOTAS ERI'!BK83 -> 40000 | BO29: =+'NOTAS ERI'!BL83 -> 40000 | BP29: =+'NOTAS ERI'!BM83 -> 40000 | BQ29: =+'NOTAS ERI'!BN83 -> 40000 | ... BU29: =+'NOTAS ERI'!BR83 -> 40000 | BW29: =+'NOTAS ERI'!BT72 -> 0 | BX29: =+'NOTAS ERI'!BU72 -> 0 | BY29: =+'NOTAS ERI'!BV72 -> 0 | BZ29: =+'NOTAS ERI'!BW72 -> 0 | CA29: =+'NOTAS ERI'!BX72 -> 0 | CB29: =+'NOTAS ERI'!BY72 -> 0 | CC29: =+'NOTAS ERI'!BZ72 -> 0 | CE29: =+'NOTAS ERI'!CB72 -> 0 | CF29: =+'NOTAS ERI'!#REF! -> #REF! | CH29: =+'NOTAS ERI'!#REF! -> #REF!
B30: Impuestos | E30: =SUM(F30:Q30) -> 0 | F30: =+'NOTAS ERI'!C74 -> 0 | G30: =+'NOTAS ERI'!D74 -> 0 | H30: =+'NOTAS ERI'!E74 -> 0 | I30: =+'NOTAS ERI'!F74 -> 0 | J30: =+'NOTAS ERI'!G74 -> 0 | K30: =+'NOTAS ERI'!H74 -> 0 | L30: =+'NOTAS ERI'!I74 -> 0 | M30: =+'NOTAS ERI'!J74 -> 0 | ... Q30: =+'NOTAS ERI'!N74 -> 0 | S30: =SUM(T30:AE30) -> 478000 | T30: =+'NOTAS ERI'!Q74 -> 0 | U30: =+'NOTAS ERI'!R74 -> 0 | V30: =+'NOTAS ERI'!S74 -> 0 | W30: =+'NOTAS ERI'!T74 -> 0 | X30: =+'NOTAS ERI'!U74 -> 0 | Y30: =+'NOTAS ERI'!V74 -> 0 | Z30: =+'NOTAS ERI'!W74 -> 0 | AA30: =+'NOTAS ERI'!X74 -> 0 | ... AE30: =+'NOTAS ERI'!AB74 -> 0 | AG30: =SUM(AH30:AS30) -> 514000 | AH30: =+'NOTAS ERI'!AE74 -> 0 | AI30: =+'NOTAS ERI'!AF74 -> 0 | AJ30: =+'NOTAS ERI'!AG74 -> 0 | AK30: =+'NOTAS ERI'!AH74 -> 0 | AL30: =+'NOTAS ERI'!AI74 -> 0 | AM30: =+'NOTAS ERI'!AJ74 -> 0 | AN30: =+'NOTAS ERI'!AK74 -> 0 | AO30: =+'NOTAS ERI'!AL74 -> 0 | ... AS30: =+'NOTAS ERI'!AP74 -> 0 | AU30: =+'NOTAS ERI'!AR74 -> 104000 | AV30: =+'NOTAS ERI'!AS74 -> 0 | AW30: =+'NOTAS ERI'!AT74 -> 0 | AX30: =+'NOTAS ERI'!AU74 -> 0 | AY30: =+'NOTAS ERI'!AV74 -> 0 | AZ30: =+'NOTAS ERI'!AW74 -> 0 | BA30: =+'NOTAS ERI'!AX74 -> 0 | BB30: =+'NOTAS ERI'!AY74 -> 0 | ... BG30: =+'NOTAS ERI'!BD74 -> 0 | BI30: 0 | BJ30: =+'NOTAS ERI'!BG74 -> 0 | BK30: =+'NOTAS ERI'!BH74 -> 0 | BL30: =+'NOTAS ERI'!BI74 -> 0 | BM30: =+'NOTAS ERI'!BJ74 -> 0 | BN30: =+'NOTAS ERI'!BK74 -> 0 | BO30: =+'NOTAS ERI'!BL74 -> 0 | BP30: =+'NOTAS ERI'!BM74 -> 0 | BQ30: =+'NOTAS ERI'!BN74 -> 0 | ... BU30: =+'NOTAS ERI'!BR74 -> 0 | BW30: =+'NOTAS ERI'!BT74 -> 0 | BX30: =+'NOTAS ERI'!BU68 -> 0 | BY30: =+'NOTAS ERI'!BV68 -> 0 | BZ30: =+'NOTAS ERI'!BW68 -> 0 | CA30: =+'NOTAS ERI'!BX68 -> 0 | CB30: =+'NOTAS ERI'!BY68 -> 0 | CC30: =+'NOTAS ERI'!BZ68 -> 0 | CE30: =+'NOTAS ERI'!CB74 -> 0 | CF30: =+'NOTAS ERI'!#REF! -> #REF! | CH30: =+'NOTAS ERI'!#REF! -> #REF!
B31: Arrendamientos | E31: =SUM(F31:Q31) -> 909260 | F31: =+'NOTAS ERI'!C78 -> 0 | G31: =+'NOTAS ERI'!D78 -> 0 | H31: =+'NOTAS ERI'!E78 -> 0 | I31: =+'NOTAS ERI'!F78 -> 0 | J31: =+'NOTAS ERI'!G78 -> 0 | K31: =+'NOTAS ERI'!H78 -> 0 | L31: =+'NOTAS ERI'!I78 -> 0 | M31: =+'NOTAS ERI'!J78 -> 0 | ... Q31: =+'NOTAS ERI'!N78 -> 909260 | S31: =SUM(T31:AE31) -> 10135254 | T31: =+'NOTAS ERI'!Q78 -> 909260 | U31: =+'NOTAS ERI'!R78 -> 909260 | V31: =+'NOTAS ERI'!S78 -> 909260 | W31: =+'NOTAS ERI'!T78 -> 824386 | X31: =+'NOTAS ERI'!U78 -> 824386 | Y31: =+'NOTAS ERI'!V78 -> 824386 | Z31: =+'NOTAS ERI'!W78 -> 824386 | AA31: =+'NOTAS ERI'!X78 -> 824386 | ... AE31: =+'NOTAS ERI'!AB78 -> 812386 | AG31: =SUM(AH31:AS31) -> 0 | AH31: =+'NOTAS ERI'!AE78 -> 0 | AI31: =+'NOTAS ERI'!AF78 -> 0 | AJ31: =+'NOTAS ERI'!AG78 -> 0 | AK31: =+'NOTAS ERI'!AH78 -> 0 | AL31: =+'NOTAS ERI'!AI78 -> 0 | AM31: =+'NOTAS ERI'!AJ78 -> 0 | AN31: =+'NOTAS ERI'!AK78 -> 0 | AO31: =+'NOTAS ERI'!AL78 -> 0 | ... AS31: =+'NOTAS ERI'!AP78 -> 0 | AU31: =SUM(AV31:BG31) -> 16929629 | AV31: =+'NOTAS ERI'!AS78 -> 750370 | AW31: =+'NOTAS ERI'!AT78 -> 0 | AX31: =+'NOTAS ERI'!AU78 -> 750370 | AY31: =+'NOTAS ERI'!AV78 -> 0 | AZ31: =+'NOTAS ERI'!AW78 -> 0 | BA31: =+'NOTAS ERI'!AX78 -> 2226440 | BB31: =+'NOTAS ERI'!AY78 -> 2166005 | BC31: =+'NOTAS ERI'!AZ78 -> 2214628 | ... BG31: =+'NOTAS ERI'!BD78 -> 2245054 | BI31: 0 | BJ31: =+'NOTAS ERI'!BG78 -> 0 | BK31: =+'NOTAS ERI'!BH78 -> 0 | BL31: =+'NOTAS ERI'!BI78 -> 0 | BM31: =+'NOTAS ERI'!BJ78 -> 0 | BN31: =+'NOTAS ERI'!BK78 -> 0 | BO31: =+'NOTAS ERI'!BL78 -> 0 | BP31: =+'NOTAS ERI'!BM78 -> 0 | BQ31: =+'NOTAS ERI'!BN78 -> 0 | ... BU31: =+'NOTAS ERI'!BR78 -> 0 | BW31: =+'NOTAS ERI'!BT78 -> 0 | BX31: =+'NOTAS ERI'!#REF! -> #REF! | BY31: =+'NOTAS ERI'!#REF! -> #REF! | BZ31: =+'NOTAS ERI'!#REF! -> #REF! | CA31: =+'NOTAS ERI'!#REF! -> #REF! | CB31: =+'NOTAS ERI'!#REF! -> #REF! | CC31: =+'NOTAS ERI'!#REF! -> #REF! | CE31: =+'NOTAS ERI'!CB78 -> 0
B32: Seguros | E32: =SUM(F32:Q32) -> 949627 | F32: =+'NOTAS ERI'!C86 -> 0 | G32: =+'NOTAS ERI'!D86 -> 0 | H32: =+'NOTAS ERI'!E86 -> 0 | I32: =+'NOTAS ERI'!F86 -> 0 | J32: =+'NOTAS ERI'!G86 -> 0 | K32: =+'NOTAS ERI'!H86 -> 0 | L32: =+'NOTAS ERI'!I86 -> 0 | M32: =+'NOTAS ERI'!J86 -> 0 | ... Q32: =+'NOTAS ERI'!N86 -> 949627 | S32: =SUM(T32:AE32) -> 991600 | T32: =+'NOTAS ERI'!Q86 -> 128248 | U32: =+'NOTAS ERI'!R86 -> 0 | V32: =+'NOTAS ERI'!S86 -> 159389 | W32: =+'NOTAS ERI'!T86 -> 0 | X32: =+'NOTAS ERI'!U86 -> 93188 | Y32: =+'NOTAS ERI'!V86 -> 0 | Z32: =+'NOTAS ERI'!W86 -> 60612 | AA32: =+'NOTAS ERI'!X86 -> 0 | ... AE32: =+'NOTAS ERI'!AB86 -> 550163 | AG32: =SUM(AH32:AS32) -> 0 | AH32: =+'NOTAS ERI'!AE86 -> 0 | AI32: =+'NOTAS ERI'!AF86 -> 0 | AJ32: =+'NOTAS ERI'!AG86 -> 0 | AK32: =+'NOTAS ERI'!AH86 -> 0 | AL32: =+'NOTAS ERI'!AI86 -> 0 | AM32: =+'NOTAS ERI'!AJ86 -> 0 | AN32: =+'NOTAS ERI'!AK86 -> 0 | AO32: =+'NOTAS ERI'!AL86 -> 0 | ... AS32: =+'NOTAS ERI'!AP86 -> 0 | AU32: =+'NOTAS ERI'!AR86 -> 113321 | AV32: =+'NOTAS ERI'!AS86 -> 0 | AW32: =+'NOTAS ERI'!AT86 -> 0 | AX32: =+'NOTAS ERI'!AU86 -> 0 | AY32: =+'NOTAS ERI'!AV86 -> 0 | AZ32: =+'NOTAS ERI'!AW86 -> 0 | BA32: =+'NOTAS ERI'!AX86 -> 0 | BB32: =+'NOTAS ERI'!AY86 -> 0 | ... BF32: =+'NOTAS ERI'!BC86 -> 113321 | BG32: =+'NOTAS ERI'!BD70 -> 0 | BJ32: =+'NOTAS ERI'!BG86 -> 0 | BK32: =+'NOTAS ERI'!BH86 -> 0 | BL32: =+'NOTAS ERI'!BI86 -> 0 | BM32: =+'NOTAS ERI'!BJ86 -> 0 | BN32: =+'NOTAS ERI'!BK86 -> 0 | BO32: =+'NOTAS ERI'!BL86 -> 0 | BP32: =+'NOTAS ERI'!BM86 -> 0 | BQ32: =+'NOTAS ERI'!BN86 -> 0 | ... BU32: =+'NOTAS ERI'!BR86 -> 0 | BW32: =+'NOTAS ERI'!BT86 -> 0 | BX32: =+'NOTAS ERI'!BU86 -> 0 | BY32: =+'NOTAS ERI'!BV86 -> 0 | BZ32: =+'NOTAS ERI'!BW86 -> 0 | CA32: =+'NOTAS ERI'!BX86 -> 0 | CB32: =+'NOTAS ERI'!BY86 -> 0 | CC32: =+'NOTAS ERI'!BZ86 -> 0 | CE32: =+'NOTAS ERI'!CB86 -> 0 | CF32: =+'NOTAS ERI'!#REF! -> #REF! | CH32: =+'NOTAS ERI'!#REF! -> #REF!
B33: Servicios | E33: =SUM(F33:Q33) -> 21464990 | F33: =+'NOTAS ERI'!C91 -> 0 | G33: =+'NOTAS ERI'!D91 -> 0 | H33: =+'NOTAS ERI'!E91 -> 0 | I33: =+'NOTAS ERI'!F91 -> 0 | J33: =+'NOTAS ERI'!G91 -> 0 | K33: =+'NOTAS ERI'!H91 -> 0 | L33: =+'NOTAS ERI'!I91 -> 0 | M33: =+'NOTAS ERI'!J91 -> 0 | ... Q33: =+'NOTAS ERI'!N91 -> 21464990 | S33: =SUM(T33:AE33) -> 19109537 | T33: =+'NOTAS ERI'!Q91 -> 4372739 | U33: =+'NOTAS ERI'!R91 -> 3935643 | V33: =+'NOTAS ERI'!S91 -> 1899134 | W33: =+'NOTAS ERI'!T91 -> 479275 | X33: =+'NOTAS ERI'!U91 -> 454062 | Y33: =+'NOTAS ERI'!V91 -> 1326294 | Z33: =+'NOTAS ERI'!W91 -> 1298437 | AA33: =+'NOTAS ERI'!X91 -> 1017823 | ... AE33: =+'NOTAS ERI'!AB91 -> 1338235 | AG33: =SUM(AH33:AS33) -> 0 | AH33: =+'NOTAS ERI'!AE91 -> 0 | AI33: =+'NOTAS ERI'!AF91 -> 0 | AJ33: =+'NOTAS ERI'!AG91 -> 0 | AK33: =+'NOTAS ERI'!AH91 -> 0 | AL33: =+'NOTAS ERI'!AI91 -> 0 | AM33: =+'NOTAS ERI'!AJ91 -> 0 | AN33: =+'NOTAS ERI'!AK91 -> 0 | AO33: =+'NOTAS ERI'!AL91 -> 0 | ... AS33: =+'NOTAS ERI'!AP91 -> 0 | AU33: =SUM(AV33:BG33) -> 9676305.3 | AV33: =+'NOTAS ERI'!AS91 -> 2515911 | AW33: =+'NOTAS ERI'!AT91 -> 1079541.1 | AX33: =+'NOTAS ERI'!AU91 -> 13015 | AY33: =+'NOTAS ERI'!AV91 -> 195210 | AZ33: =+'NOTAS ERI'!AW91 -> 969993.14 | BA33: =+'NOTAS ERI'!AX91 -> 764966 | BB33: =+'NOTAS ERI'!AY91 -> 170000 | BC33: =+'NOTAS ERI'!AZ91 -> 520084 | ... BG33: =+'NOTAS ERI'!BD91 -> 1799520 | BI33: =+'NOTAS ERI'!BF99+'NOTAS ERI'!BF97 -> 1887269 | BJ33: =+'NOTAS ERI'!BG91 -> 211991 | BK33: =+'NOTAS ERI'!BH91 -> 0 | BL33: =+'NOTAS ERI'!BI91 -> 490000 | BM33: =+'NOTAS ERI'!BJ91 -> 83978 | BN33: =+'NOTAS ERI'!BK91 -> 168044 | BO33: =+'NOTAS ERI'!BL91 -> 142487 | BP33: =+'NOTAS ERI'!BM91 -> 126055 | BQ33: =+'NOTAS ERI'!BN91 -> 183525 | ... BU33: =+'NOTAS ERI'!BR91 -> 145101 | BW33: =+'NOTAS ERI'!BT91 -> 0 | BX33: =+'NOTAS ERI'!BU91 -> 0 | BY33: =+'NOTAS ERI'!BV91 -> 0 | BZ33: =+'NOTAS ERI'!BW91 -> 0 | CA33: =+'NOTAS ERI'!BX91 -> 0 | CB33: =+'NOTAS ERI'!BY91 -> 0 | CC33: =+'NOTAS ERI'!BZ91 -> 0 | CE33: =+'NOTAS ERI'!CB91 -> 0 | CF33: =+'NOTAS ERI'!#REF! -> #REF! | CH33: =+'NOTAS ERI'!#REF! -> #REF!
B34: Gastos Legales | E34: =SUM(F34:Q34) -> 0 | F34: =+'NOTAS ERI'!C107 -> 0 | G34: =+'NOTAS ERI'!D107 -> 0 | H34: =+'NOTAS ERI'!E107 -> 0 | I34: =+'NOTAS ERI'!F107 -> 0 | J34: =+'NOTAS ERI'!G107 -> 0 | K34: =+'NOTAS ERI'!H107 -> 0 | L34: =+'NOTAS ERI'!I107 -> 0 | M34: =+'NOTAS ERI'!J107 -> 0 | ... Q34: =+'NOTAS ERI'!N107 -> 0 | S34: =SUM(T34:AE34) -> 1037700 | T34: =+'NOTAS ERI'!Q107 -> 0 | U34: =+'NOTAS ERI'!R107 -> 0 | V34: =+'NOTAS ERI'!S107 -> 0 | W34: =+'NOTAS ERI'!T107 -> 325000 | X34: =+'NOTAS ERI'!U107 -> 0 | Y34: =+'NOTAS ERI'!V107 -> 0 | Z34: =+'NOTAS ERI'!W107 -> 80600 | AA34: =+'NOTAS ERI'!X107 -> 632100 | ... AE34: =+'NOTAS ERI'!AB107 -> 0 | AG34: =SUM(AH34:AS34) -> 818900 | AH34: =+'NOTAS ERI'!AE107 -> 0 | AI34: =+'NOTAS ERI'!AF107 -> 0 | AJ34: =+'NOTAS ERI'!AG107 -> 0 | AK34: =+'NOTAS ERI'!AH107 -> 0 | AL34: =+'NOTAS ERI'!AI107 -> 0 | AM34: =+'NOTAS ERI'!AJ107 -> 0 | AN34: =+'NOTAS ERI'!AK107 -> 0 | AO34: =+'NOTAS ERI'!AL107 -> 65900 | ... AS34: =+'NOTAS ERI'!AP107 -> 0 | AU34: =SUM(AV34:BG34) -> 382938 | AV34: =+'NOTAS ERI'!AS107 -> 0 | AW34: =+'NOTAS ERI'!AT107 -> 0 | AX34: =+'NOTAS ERI'!AU107 -> 0 | AY34: =+'NOTAS ERI'!AV107 -> 0 | AZ34: =+'NOTAS ERI'!AW107 -> 0 | BA34: =+'NOTAS ERI'!AX107 -> 0 | BB34: =+'NOTAS ERI'!AY107 -> 0 | BC34: =+'NOTAS ERI'!AZ107 -> 0 | ... BG34: =+'NOTAS ERI'!BD107 -> 0 | BI34: =+'NOTAS ERI'!BF107 -> 365434 | BJ34: =+'NOTAS ERI'!BG107 -> 0 | BK34: =+'NOTAS ERI'!BH107 -> 0 | BL34: =+'NOTAS ERI'!BI107 -> 226534 | BM34: =+'NOTAS ERI'!BJ107 -> 6500 | BN34: =+'NOTAS ERI'!BK107 -> 0 | BO34: =+'NOTAS ERI'!BL107 -> 6500 | BP34: =+'NOTAS ERI'!BM107 -> 0 | ... BU34: =+'NOTAS ERI'!BR107 -> 0 | BW34: =+'NOTAS ERI'!BT107 -> 0 | BX34: =+'NOTAS ERI'!BU107 -> 0 | BY34: =+'NOTAS ERI'!BV107 -> 0 | BZ34: =+'NOTAS ERI'!BW107 -> 0 | CA34: =+'NOTAS ERI'!BX107 -> 0 | CB34: =+'NOTAS ERI'!BY107 -> 0 | CC34: =+'NOTAS ERI'!BZ107 -> 0 | CE34: =+'NOTAS ERI'!CB107 -> 0 | CF34: =+'NOTAS ERI'!#REF! -> #REF! | CH34: =+'NOTAS ERI'!#REF! -> #REF!
B35: Mantenimiento y reparacion | E35: =SUM(F35:Q35) -> 0 | F35: 0 | G35: 0 | H35: 0 | I35: 0 | J35: 0 | K35: 0 | L35: 0 | M35: 0 | N35: 0 | O35: 0 | P35: 0 | Q35: 0 | S35: =SUM(T35:AE35) -> 0 | T35: =+'NOTAS ERI'!Q114 -> 0 | U35: =+'NOTAS ERI'!R114 -> 0 | V35: =+'NOTAS ERI'!S114 -> 0 | W35: =+'NOTAS ERI'!T114 -> 0 | X35: =+'NOTAS ERI'!U114 -> 0 | Y35: =+'NOTAS ERI'!V114 -> 0 | Z35: =+'NOTAS ERI'!W114 -> 0 | AA35: =+'NOTAS ERI'!X114 -> 0 | ... AE35: =+'NOTAS ERI'!AB114 -> 0 | AG35: =SUM(AH35:AS35) -> 0 | AH35: =+'NOTAS ERI'!AE114 -> 0 | AI35: =+'NOTAS ERI'!AF114 -> 0 | AJ35: =+'NOTAS ERI'!AG114 -> 0 | AK35: =+'NOTAS ERI'!AH114 -> 0 | AL35: =+'NOTAS ERI'!AI114 -> 0 | AM35: =+'NOTAS ERI'!AJ114 -> 0 | AN35: =+'NOTAS ERI'!AK114 -> 0 | AO35: =+'NOTAS ERI'!AL114 -> 0 | ... AS35: =+'NOTAS ERI'!AP114 -> 0 | AU35: =SUM(AV35:BG35) -> 184941 | AV35: =+'NOTAS ERI'!AS114 -> 0 | AW35: =+'NOTAS ERI'!AT114 -> 0 | AX35: =+'NOTAS ERI'!AU114 -> 0 | AY35: =+'NOTAS ERI'!AV114 -> 0 | AZ35: =+'NOTAS ERI'!AW114 -> 0 | BA35: =+'NOTAS ERI'!AX114 -> 0 | BB35: =+'NOTAS ERI'!AY114 -> 0 | BC35: =+'NOTAS ERI'!AZ114 -> 0 | ... BF35: =+'NOTAS ERI'!BC114 -> 21008 | BG35: =+'NOTAS ERI'!BD73 -> 0 | BI35: =SUM(BJ35:BU35) -> 0 | BJ35: =+'NOTAS ERI'!BG114 -> 0 | BK35: =+'NOTAS ERI'!BH114 -> 0 | BL35: =+'NOTAS ERI'!BI114 -> 0 | BM35: =+'NOTAS ERI'!BJ114 -> 0 | BN35: =+'NOTAS ERI'!BK114 -> 0 | BO35: =+'NOTAS ERI'!BL114 -> 0 | BP35: =+'NOTAS ERI'!BM114 -> 0 | BQ35: =+'NOTAS ERI'!BN114 -> 0 | ... BU35: =+'NOTAS ERI'!BR114 -> 0 | BW35: =+'NOTAS ERI'!BT114 -> 0 | BX35: =+'NOTAS ERI'!BU114 -> 0 | BY35: =+'NOTAS ERI'!BV114 -> 0 | BZ35: =+'NOTAS ERI'!BW114 -> 0 | CA35: =+'NOTAS ERI'!BX114 -> 0 | CB35: =+'NOTAS ERI'!BY114 -> 0 | CC35: =+'NOTAS ERI'!BZ114 -> 0 | CE35: =+'NOTAS ERI'!CB114 -> 0 | CF35: =+'NOTAS ERI'!#REF! -> #REF! | CH35: =+'NOTAS ERI'!#REF! -> #REF!
B36: Gastos de Viaje | E36: =SUM(F36:Q36) -> 0 | F36: 0 | G36: 0 | H36: 0 | I36: 0 | J36: 0 | K36: 0 | L36: 0 | M36: 0 | N36: 0 | O36: 0 | P36: 0 | Q36: 0 | S36: =SUM(T36:AE36) -> 0 | T36: =+'NOTAS ERI'!Q121 -> 0 | U36: =+'NOTAS ERI'!R121 -> 0 | V36: =+'NOTAS ERI'!S121 -> 0 | W36: =+'NOTAS ERI'!T121 -> 0 | X36: =+'NOTAS ERI'!U121 -> 0 | Y36: =+'NOTAS ERI'!V121 -> 0 | Z36: =+'NOTAS ERI'!W121 -> 0 | AA36: =+'NOTAS ERI'!X121 -> 0 | ... AE36: =+'NOTAS ERI'!AB121 -> 0 | AG36: =SUM(AH36:AS36) -> 0 | AH36: =+'NOTAS ERI'!AE121 -> 0 | AI36: =+'NOTAS ERI'!AF121 -> 0 | AJ36: =+'NOTAS ERI'!AG121 -> 0 | AK36: =+'NOTAS ERI'!AH121 -> 0 | AL36: =+'NOTAS ERI'!AI121 -> 0 | AM36: =+'NOTAS ERI'!AJ121 -> 0 | AN36: =+'NOTAS ERI'!AK121 -> 0 | AO36: =+'NOTAS ERI'!AL121 -> 0 | ... AS36: =+'NOTAS ERI'!AP121 -> 0 | AU36: =SUM(AV36:BG36) -> 0 | AV36: =+'NOTAS ERI'!AS121 -> 0 | AW36: =+'NOTAS ERI'!AT121 -> 0 | AX36: =+'NOTAS ERI'!AU121 -> 0 | AY36: =+'NOTAS ERI'!AV121 -> 0 | AZ36: =+'NOTAS ERI'!AW121 -> 0 | BA36: =+'NOTAS ERI'!AX121 -> 0 | BB36: =+'NOTAS ERI'!AY121 -> 0 | BC36: =+'NOTAS ERI'!AZ121 -> 0 | ... BG36: =+'NOTAS ERI'!BD121 -> 0 | BI36: =+'NOTAS ERI'!BF109 -> 0 | BJ36: =+'NOTAS ERI'!BG121 -> 0 | BK36: =+'NOTAS ERI'!BH121 -> 0 | BL36: =+'NOTAS ERI'!BI121 -> 0 | BM36: =+'NOTAS ERI'!BJ121 -> 0 | BN36: =+'NOTAS ERI'!BK121 -> 0 | BO36: =+'NOTAS ERI'!BL121 -> 0 | BP36: =+'NOTAS ERI'!BM121 -> 0 | BQ36: =+'NOTAS ERI'!BN121 -> 0 | ... BU36: =+'NOTAS ERI'!BR121 -> 0 | BW36: =+'NOTAS ERI'!BT121 -> 0 | BX36: =+'NOTAS ERI'!#REF! -> #REF! | BY36: =+'NOTAS ERI'!#REF! -> #REF! | BZ36: =+'NOTAS ERI'!#REF! -> #REF! | CA36: =+'NOTAS ERI'!#REF! -> #REF! | CB36: =+'NOTAS ERI'!#REF! -> #REF! | CC36: =+'NOTAS ERI'!#REF! -> #REF! | CE36: =+'NOTAS ERI'!CB121 -> 0 | CF36: =+'NOTAS ERI'!#REF! -> #REF! | CH36: =+'NOTAS ERI'!#REF! -> #REF!
B37: Depreciacion | E37: =SUM(F37:Q37) -> 0 | F37: 0 | G37: 0 | H37: 0 | I37: 0 | J37: 0 | K37: 0 | L37: 0 | M37: 0 | N37: 0 | O37: 0 | P37: 0 | Q37: 0 | S37: =SUM(T37:AE37) -> 0 | T37: =+'NOTAS ERI'!Q129 -> 0 | U37: =+'NOTAS ERI'!R129 -> 0 | V37: =+'NOTAS ERI'!S129 -> 0 | W37: =+'NOTAS ERI'!T129 -> 0 | X37: =+'NOTAS ERI'!U129 -> 0 | Y37: =+'NOTAS ERI'!V129 -> 0 | Z37: =+'NOTAS ERI'!W129 -> 0 | AA37: =+'NOTAS ERI'!X129 -> 0 | ... AE37: =+'NOTAS ERI'!AB129 -> 0 | AG37: =SUM(AH37:AS37) -> 0 | AH37: =+'NOTAS ERI'!AE129 -> 0 | AI37: =+'NOTAS ERI'!AF129 -> 0 | AJ37: =+'NOTAS ERI'!AG129 -> 0 | AK37: =+'NOTAS ERI'!AH129 -> 0 | AL37: =+'NOTAS ERI'!AI129 -> 0 | AM37: =+'NOTAS ERI'!AJ129 -> 0 | AN37: =+'NOTAS ERI'!AK129 -> 0 | AO37: =+'NOTAS ERI'!AL129 -> 0 | ... AS37: =+'NOTAS ERI'!AP129 -> 0 | AU37: =SUM(AV37:BG37) -> 0 | AV37: 0 | AW37: 0 | AX37: 0 | AY37: 0 | AZ37: 0 | BA37: 0 | BB37: 0 | BC37: 0 | BD37: 0 | BE37: 0 | BF37: 0 | BG37: =+'NOTAS ERI'!BD75 -> 0 | BI37: =+'NOTAS ERI'!BF110 -> 0 | BJ37: =+'NOTAS ERI'!BG129 -> 0 | BK37: =+'NOTAS ERI'!BH129 -> 0 | BL37: =+'NOTAS ERI'!BI129 -> 0 | BM37: =+'NOTAS ERI'!BJ129 -> 0 | BN37: =+'NOTAS ERI'!BK129 -> 0 | BO37: =+'NOTAS ERI'!BL129 -> 0 | BP37: =+'NOTAS ERI'!BM129 -> 0 | BQ37: =+'NOTAS ERI'!BN129 -> 0 | ... BU37: =+'NOTAS ERI'!BR129 -> 0 | BW37: =+'NOTAS ERI'!BT129 -> 0 | BX37: =+'NOTAS ERI'!#REF! -> #REF! | BY37: =+'NOTAS ERI'!#REF! -> #REF! | BZ37: =+'NOTAS ERI'!#REF! -> #REF! | CA37: =+'NOTAS ERI'!#REF! -> #REF! | CB37: =+'NOTAS ERI'!#REF! -> #REF! | CC37: =+'NOTAS ERI'!#REF! -> #REF! | CE37: =+'NOTAS ERI'!#REF! -> #REF! | CF37: =+'NOTAS ERI'!#REF! -> #REF! | CH37: =+'NOTAS ERI'!#REF! -> #REF!
B38: Diversos | E38: =SUM(F38:Q38) -> 657836 | F38: =+'NOTAS ERI'!C134 -> 0 | G38: =+'NOTAS ERI'!D134 -> 0 | H38: =+'NOTAS ERI'!E134 -> 0 | I38: =+'NOTAS ERI'!F134 -> 0 | J38: =+'NOTAS ERI'!G134 -> 0 | K38: =+'NOTAS ERI'!H134 -> 0 | L38: =+'NOTAS ERI'!I134 -> 0 | M38: =+'NOTAS ERI'!J134 -> 0 | ... Q38: =+'NOTAS ERI'!N134 -> 657836 | S38: =SUM(T38:AE38) -> 859285 | T38: =+'NOTAS ERI'!Q134 -> 338748 | U38: =+'NOTAS ERI'!R134 -> 25378 | V38: =+'NOTAS ERI'!S134 -> 71890 | W38: =+'NOTAS ERI'!T134 -> 0 | X38: =+'NOTAS ERI'!U134 -> 21008 | Y38: =+'NOTAS ERI'!V134 -> 0 | Z38: =+'NOTAS ERI'!W134 -> 20168 | AA38: =+'NOTAS ERI'!X134 -> 33521 | ... AE38: =+'NOTAS ERI'!AB134 -> 16723 | AG38: =SUM(AH38:AS38) -> 249963.82 | AH38: =+'NOTAS ERI'!AE134 -> 0 | AI38: =+'NOTAS ERI'!AF134 -> 45778 | AJ38: =+'NOTAS ERI'!AG134 -> 0 | AK38: =+'NOTAS ERI'!AH134 -> 0 | AL38: =+'NOTAS ERI'!AI134 -> 0 | AM38: =+'NOTAS ERI'!AJ134 -> 93420.16 | AN38: =+'NOTAS ERI'!AK134 -> 16000 | AO38: =+'NOTAS ERI'!AL134 -> 10397.66 | ... AS38: =+'NOTAS ERI'!AP134 -> 28316 | AU38: =SUM(AV38:BG38) -> 717572 | AV38: =+'NOTAS ERI'!AS134 -> 0 | AW38: =+'NOTAS ERI'!AT134 -> 22520 | AX38: =+'NOTAS ERI'!AU134 -> 67450 | AY38: =+'NOTAS ERI'!AV134 -> 231000 | AZ38: =+'NOTAS ERI'!AW134 -> 63308 | BA38: =+'NOTAS ERI'!AX134 -> 0 | BB38: =+'NOTAS ERI'!AY134 -> 31000 | BC38: =+'NOTAS ERI'!AZ134 -> 0 | ... BG38: =+'NOTAS ERI'!BD134 -> 0 | BI38: =+'NOTAS ERI'!BF137+'NOTAS ERI'!BF138 -> 457239 | BJ38: =SUM(#REF!) -> #REF! | BK38: =SUM(#REF!) -> #REF! | BL38: =SUM(#REF!) -> #REF! | BM38: =SUM(#REF!) -> #REF! | BN38: =SUM(#REF!) -> #REF! | BO38: =SUM(#REF!) -> #REF! | BP38: =SUM(#REF!) -> #REF! | BQ38: =SUM(#REF!) -> #REF! | ... BU38: =SUM(#REF!) -> #REF! | BW38: =SUM(#REF!) -> #REF! | BX38: =SUM(#REF!) -> #REF! | BY38: =SUM(#REF!) -> #REF! | BZ38: =SUM(#REF!) -> #REF! | CA38: =SUM(#REF!) -> #REF! | CB38: =SUM(#REF!) -> #REF! | CC38: =SUM(#REF!) -> #REF! | CE38: =SUM(#REF!) -> #REF! | CF38: =+'NOTAS ERI'!#REF! -> #REF! | CH38: =+'NOTAS ERI'!#REF! -> #REF!
B40: GASTOS NO OPERACIONALES | C40: 14 | E40: =SUM(E42:E43) -> 444898 | F40: =SUM(F42:F43) -> 0 | G40: =SUM(G42:G43) -> 0 | H40: =SUM(H42:H43) -> 0 | I40: =SUM(I42:I43) -> 0 | J40: =SUM(J42:J43) -> 0 | K40: =SUM(K42:K43) -> 0 | L40: =SUM(L42:L43) -> 0 | ... Q40: =SUM(Q42:Q43) -> 444898 | S40: =SUM(S42:S43) -> 13660657 | T40: =SUM(T42:T43) -> 546725 | U40: =SUM(U42:U43) -> 314748 | V40: =SUM(V42:V43) -> 557832 | W40: =SUM(W42:W43) -> 392107 | X40: =SUM(X42:X43) -> 340805.33 | Y40: =SUM(Y42:Y43) -> 369904 | Z40: =SUM(Z42:Z43) -> 432887 | ... AE40: =SUM(AE42:AE43) -> 191032 | AG40: =SUM(AG42:AG43) -> 3254129 | AH40: =SUM(AH41:AH43) -> 197086 | AI40: =SUM(AI41:AI43) -> 215731 | AJ40: =SUM(AJ41:AJ43) -> 237239 | AK40: =SUM(AK41:AK43) -> 181455 | AL40: =SUM(AL41:AL43) -> 203991 | AM40: =SUM(AM41:AM43) -> 185273 | AN40: =SUM(AN41:AN43) -> 1107971 | AO40: =SUM(AO41:AO43) -> 151796 | ... AS40: =SUM(AS41:AS43) -> 168935 | AU40: =SUM(AU42:AU43) -> 3448789 | AV40: =SUM(AV41:AV43) -> 184127 | AW40: =SUM(AW41:AW43) -> 194843 | AX40: =SUM(AX41:AX43) -> 136858 | AY40: =SUM(AY41:AY43) -> 155028 | AZ40: =SUM(AZ41:AZ43) -> 136830 | BA40: =SUM(BA41:BA43) -> 342290 | BB40: =SUM(BB41:BB43) -> 145949 | BC40: =SUM(BC41:BC43) -> 135282 | ... BG40: =SUM(BG41:BG43) -> 145736 | BI40: =SUM(BI42:BI43) -> 0 | BJ40: =SUM(BJ41:BJ43) -> 0 | BK40: =SUM(BK41:BK43) -> 0 | BL40: =SUM(BL41:BL43) -> 0 | BM40: =SUM(BM41:BM43) -> 533.59 | BN40: =SUM(BN41:BN43) -> 0 | BO40: =SUM(BO41:BO43) -> 0 | BP40: =SUM(BP41:BP43) -> 0 | BQ40: =SUM(BQ41:BQ43) -> 0 | ... BU40: =SUM(BU41:BU43) -> 0 | BW40: =SUM(BW41:BW43) -> 0 | BX40: =SUM(BX41:BX43) -> 0 | BY40: =SUM(BY41:BY43) -> 0 | BZ40: =SUM(BZ41:BZ43) -> 0 | CA40: =SUM(CA41:CA43) -> 0 | CB40: =SUM(CB41:CB43) -> 0 | CC40: =SUM(CC41:CC43) -> 0 | CE40: =SUM(CE41:CE43) -> 0 | CF40: =SUM(CF41:CF43) -> #REF! | CH40: =SUM(CH41:CH43) -> #REF!
B42: Financieros | E42: =SUM(F42:Q42) -> 444898 | F42: =+'NOTAS ERI'!C156 -> 0 | G42: =+'NOTAS ERI'!D156 -> 0 | H42: =+'NOTAS ERI'!E156 -> 0 | I42: =+'NOTAS ERI'!F156 -> 0 | J42: =+'NOTAS ERI'!G156 -> 0 | K42: =+'NOTAS ERI'!H156 -> 0 | L42: =+'NOTAS ERI'!I156 -> 0 | M42: =+'NOTAS ERI'!J156 -> 0 | ... Q42: =+'NOTAS ERI'!N156 -> 444898 | S42: =SUM(T42:AE42) -> 13660657 | T42: =+'NOTAS ERI'!Q156 -> 546725 | U42: =+'NOTAS ERI'!R156 -> 314748 | V42: =+'NOTAS ERI'!S156 -> 557832 | W42: =+'NOTAS ERI'!T156 -> 392107 | X42: =+'NOTAS ERI'!U156 -> 340805.33 | Y42: =+'NOTAS ERI'!V156 -> 369904 | Z42: =+'NOTAS ERI'!W156 -> 432887 | AA42: =+'NOTAS ERI'!X156 -> 396592 | ... AE42: =+'NOTAS ERI'!AB156 -> 191032 | AG42: =SUM(AH42:AS42) -> 3254129 | AH42: =+'NOTAS ERI'!AE156 -> 197086 | AI42: =+'NOTAS ERI'!AF156 -> 215731 | AJ42: =+'NOTAS ERI'!AG156 -> 237239 | AK42: =+'NOTAS ERI'!AH156 -> 181455 | AL42: =+'NOTAS ERI'!AI156 -> 203991 | AM42: =+'NOTAS ERI'!AJ156 -> 185273 | AN42: =+'NOTAS ERI'!AK156 -> 1107971 | AO42: =+'NOTAS ERI'!AL156 -> 151796 | ... AS42: =+'NOTAS ERI'!AP156 -> 168935 | AU42: =SUM(AV42:BG42) -> 3448789 | AV42: =+'NOTAS ERI'!AS156 -> 184127 | AW42: =+'NOTAS ERI'!AT156 -> 194843 | AX42: =+'NOTAS ERI'!AU156 -> 136858 | AY42: =+'NOTAS ERI'!AV156 -> 155028 | AZ42: =+'NOTAS ERI'!AW156 -> 136830 | BA42: =+'NOTAS ERI'!AX156 -> 342290 | BB42: =+'NOTAS ERI'!AY156 -> 145949 | BC42: =+'NOTAS ERI'!AZ156 -> 135282 | ... BG42: =+'NOTAS ERI'!BD156 -> 145736 | BI42: 0 | BJ42: =+'NOTAS ERI'!BG156 -> 0 | BK42: =+'NOTAS ERI'!BH156 -> 0 | BL42: =+'NOTAS ERI'!BI156 -> 0 | BM42: =+'NOTAS ERI'!BJ156 -> 533.59 | BN42: =+'NOTAS ERI'!BK156 -> 0 | BO42: =+'NOTAS ERI'!BL156 -> 0 | BP42: =+'NOTAS ERI'!BM156 -> 0 | BQ42: =+'NOTAS ERI'!BN156 -> 0 | ... BU42: =+'NOTAS ERI'!BR156 -> 0 | BW42: =+'NOTAS ERI'!BT156 -> 0 | BX42: =+'NOTAS ERI'!BU156 -> 0 | BY42: =+'NOTAS ERI'!BV156 -> 0 | BZ42: =+'NOTAS ERI'!BW156 -> 0 | CA42: =+'NOTAS ERI'!BX156 -> 0 | CB42: =+'NOTAS ERI'!BY156 -> 0 | CC42: =+'NOTAS ERI'!BZ156 -> 0 | CE42: =+'NOTAS ERI'!CB156 -> 0 | CF42: =+'NOTAS ERI'!#REF! -> #REF! | CH42: =+'NOTAS ERI'!#REF! -> #REF!
B43: Gastos Extraordinarios | E43: =SUM(R43:AC43) -> 0 | F43: =SUM(H43:S43) -> 0 | G43: =SUM(I43:T43) -> 0 | H43: =SUM(J43:U43) -> 0 | I43: =SUM(K43:V43) -> 0 | J43: =SUM(L43:W43) -> 0 | K43: =SUM(M43:X43) -> 0 | L43: =SUM(N43:Y43) -> 0 | M43: =SUM(O43:Z43) -> 0 | ... Q43: =SUM(S43:AD43) -> 0 | S43: =SUM(T43:AE43) -> 0 | T43: =+'NOTAS ERI'!Q165 -> 0 | U43: =+'NOTAS ERI'!R165 -> 0 | V43: =+'NOTAS ERI'!S165 -> 0 | W43: =+'NOTAS ERI'!T165 -> 0 | X43: =+'NOTAS ERI'!U165 -> 0 | Y43: =+'NOTAS ERI'!V165 -> 0 | Z43: =+'NOTAS ERI'!W165 -> 0 | AA43: =+'NOTAS ERI'!X165 -> 0 | ... AE43: =+'NOTAS ERI'!AB165 -> 0 | AG43: =SUM(AH43:AS43) -> 0 | AH43: =+'NOTAS ERI'!AE165 -> 0 | AI43: =+'NOTAS ERI'!AF165 -> 0 | AJ43: =+'NOTAS ERI'!AG165 -> 0 | AK43: =+'NOTAS ERI'!AH165 -> 0 | AL43: =+'NOTAS ERI'!AI165 -> 0 | AM43: =+'NOTAS ERI'!AJ165 -> 0 | AN43: =+'NOTAS ERI'!AK165 -> 0 | AO43: =+'NOTAS ERI'!AL165 -> 0 | ... AS43: =+'NOTAS ERI'!AP165 -> 0 | AU43: =SUM(BB43:BG43) -> 0 | AV43: 0 | AW43: 0 | AX43: 0 | AY43: 0 | AZ43: 0 | BA43: 0 | BB43: 0 | BC43: 0 | BD43: 0 | BE43: 0 | BF43: 0 | BG43: 0 | BI43: 0 | BJ43: 0 | BK43: 0 | BL43: 0 | BM43: 0 | BN43: 0 | BO43: 0 | BP43: 0 | BQ43: 0 | BR43: 0 | BS43: 0 | BT43: 0 | BU43: 0 | BW43: 0 | BX43: 0 | BY43: 0 | BZ43: 0 | CA43: 0 | CB43: 0 | CC43: 0 | CE43: =+'NOTAS ERI'!CB169 -> 0 | CF43: =+'NOTAS ERI'!#REF! -> #REF! | CH43: =+'NOTAS ERI'!#REF! -> #REF!
B45: TOTAL GASTOS | E45: =+E28+E29+E31+E33+E34+E35+E36+E37+E38+E40+E32+E30 -> 52769764 | F45: =+F28+F29+F31+F33+F34+F35+F36+F37+F38+F40+F32+F30 -> 0 | G45: =+G28+G29+G31+G33+G34+G35+G36+G37+G38+G40+G32+G30 -> 0 | H45: =+H28+H29+H31+H33+H34+H35+H36+H37+H38+H40+H32+H30 -> 0 | I45: =+I28+I29+I31+I33+I34+I35+I36+I37+I38+I40+I32+I30 -> 0 | J45: =+J28+J29+J31+J33+J34+J35+J36+J37+J38+J40+J32+J30 -> 0 | K45: =+K28+K29+K31+K33+K34+K35+K36+K37+K38+K40+K32+K30 -> 0 | L45: =+L28+L29+L31+L33+L34+L35+L36+L37+L38+L40+L32+L30 -> 0 | ... Q45: =+Q28+Q29+Q31+Q33+Q34+Q35+Q36+Q37+Q38+Q40+Q32+Q30 -> 52769764 | S45: =+S28+S29+S31+S33+S34+S35+S36+S37+S38+S40+S32+S30 -> 3.2120573e+08 | T45: =+T28+T29+T31+T33+T34+T35+T36+T37+T38+T40+T32+T30 -> 32000694 | U45: =+U28+U29+U31+U33+U34+U35+U36+U37+U38+U40+U32+U30 -> 30438588 | V45: =+V28+V29+V31+V33+V34+V35+V36+V37+V38+V40+V32+V30 -> 28798362 | W45: =+W28+W29+W31+W33+W34+W35+W36+W37+W38+W40+W32+W30 -> 26725852 | X45: =+X28+X29+X31+X33+X34+X35+X36+X37+X38+X40+X32+X30 -> 26768433 | Y45: =+Y28+Y29+Y31+Y33+Y34+Y35+Y36+Y37+Y38+Y40+Y32+Y30 -> 27973968 | Z45: =+Z28+Z29+Z31+Z33+Z34+Z35+Z36+Z37+Z38+Z40+Z32+Z30 -> 27434956 | ... AE45: =+AE28+AE29+AE31+AE33+AE34+AE35+AE36+AE37+AE38+AE40+AE32+AE30 -> 7687403 | AG45: =+AG28+AG29+AG31+AG33+AG34+AG35+AG36+AG37+AG38+AG40+AG32+AG30 -> 82970858 | AH45: =+AH28+AH29+AH31+AH33+AH34+AH35+AH36+AH37+AH38+AH40+AH32 -> 4500592 | AI45: =+AI28+AI29+AI31+AI33+AI34+AI35+AI36+AI37+AI38+AI40+AI32 -> 4565015 | AJ45: =+AJ28+AJ29+AJ31+AJ33+AJ34+AJ35+AJ36+AJ37+AJ38+AJ40+AJ32 -> 4806138 | AK45: =+AK28+AK29+AK31+AK33+AK34+AK35+AK36+AK37+AK38+AK40+AK32 -> 6474214 | AL45: =+AL28+AL29+AL31+AL33+AL34+AL35+AL36+AL37+AL38+AL40+AL32 -> 6496750 | AM45: =+AM28+AM29+AM31+AM33+AM34+AM35+AM36+AM37+AM38+AM40+AM32 -> 6571452.2 | AN45: =+AN28+AN29+AN31+AN33+AN34+AN35+AN36+AN37+AN38+AN40+AN32 -> 7652764 | AO45: =+AO28+AO29+AO31+AO33+AO34+AO35+AO36+AO37+AO38+AO40+AO32+AO30 -> 8510105.7 | AP45: =+AP28+AP29+AP31+AP33+AP34+AP35+AP36+AP37+AP38+AP40+AP32+AP30 -> 9031298 | AQ45: =+AQ28+AQ29+AQ31+AQ33+AQ34+AQ35+AQ36+AQ37+AQ38+AQ40+AQ32+AQ30 -> 9279024 | AR45: =+AR28+AR29+AR31+AR33+AR34+AR35+AR36+AR37+AR38+AR40+AR32+AR30 -> 8593494 | AS45: =+AS28+AS29+AS31+AS33+AS34+AS35+AS36+AS37+AS38+AS40+AS32+AS30 -> 6490011 | AU45: =+AU28+AU29+AU31+AU33+AU34+AU35+AU36+AU37+AU38+AU40+AU32+AU30 -> 93845675 | AV45: =+AV28+AV29+AV31+AV33+AV34+AV35+AV36+AV37+AV38+AV40+AV32 -> 9146944 | AW45: =+AW28+AW29+AW31+AW33+AW34+AW35+AW36+AW37+AW38+AW40+AW32 -> 6924893.1 | AX45: =+AX28+AX29+AX31+AX33+AX34+AX35+AX36+AX37+AX38+AX40+AX32 -> 6686399 | AY45: =+AY28+AY29+AY31+AY33+AY34+AY35+AY36+AY37+AY38+AY40+AY32 -> 5825978 | AZ45: =+AZ28+AZ29+AZ31+AZ33+AZ34+AZ35+AZ36+AZ37+AZ38+AZ40+AZ32 -> 6838725.1 | BA45: =+BA28+BA29+BA31+BA33+BA34+BA35+BA36+BA37+BA38+BA40+BA32 -> 7167534 | BB45: =+BB28+BB29+BB31+BB33+BB34+BB35+BB36+BB37+BB38+BB40+BB32 -> 7311640 | BC45: =+BC28+BC29+BC31+BC33+BC34+BC35+BC36+BC37+BC38+BC40+BC32 -> 6703832 | BD45: =+BD28+BD29+BD31+BD33+BD34+BD35+BD36+BD37+BD38+BD40+BD32 -> 7614433.3 | BE45: =+BE28+BE29+BE31+BE33+BE34+BE35+BE36+BE37+BE38+BE40+BE32+BE30 -> 13073647 | BF45: =+BF28+BF29+BF31+BF33+BF34+BF35+BF36+BF37+BF38+BF40+BF32 -> 7089209.8 | BG45: =+BG28+BG29+BG31+BG33+BG34+BG35+BG36+BG37+BG38+BG40 -> 9462440 | BI45: =+BI28+BI29+BI31+BI33+BI34+BI35+BI36+BI37+BI38+BI40 -> 47493789 | BJ45: =+BJ28+BJ29+BJ31+BJ33+BJ34+BJ35+BJ36+BJ37+BJ38+BJ40 -> #REF! | BK45: =+BK28+BK29+BK31+BK33+BK34+BK35+BK36+BK37+BK38+BK40 -> #REF! | BL45: =+BL28+BL29+BL31+BL33+BL34+BL35+BL36+BL37+BL38+BL40 -> #REF! | BM45: =+BM28+BM29+BM31+BM33+BM34+BM35+BM36+BM37+BM38+BM40 -> #REF! | BN45: =+BN28+BN29+BN31+BN33+BN34+BN35+BN36+BN37+BN38+BN40 -> #REF! | BO45: =+BO28+BO29+BO31+BO33+BO34+BO35+BO36+BO37+BO38+BO40 -> #REF! | BP45: =+BP28+BP29+BP31+BP33+BP34+BP35+BP36+BP37+BP38+BP40 -> #REF! | ... BU45: =+BU28+BU29+BU31+BU33+BU34+BU35+BU36+BU37+BU38+BU40 -> #REF! | BW45: =+BW26+BW40 -> #REF! | BX45: =+BX26+BX40 -> #REF! | BY45: =+BY26+BY40 -> #REF! | BZ45: =+BZ26+BZ40 -> #REF! | CA45: =+CA26+CA40 -> #REF! | CB45: =+CB26+CB40 -> #REF! | CC45: =+CC26+CC40 -> #REF! | CE45: =+CE26+CE40 -> #REF! | CF45: =+CF40+CF26 -> #REF! | CH45: =+CH40+CH26 -> #REF!
E46: =SUM(AE46:AM46) -> 0 | F46: =SUM(U46:AC46) -> 0 | G46: =SUM(V46:AD46) -> 0 | H46: =SUM(W46:AE46) -> 0 | I46: =SUM(X46:AF46) -> 0 | J46: =SUM(Y46:AG46) -> 0 | K46: =SUM(Z46:AH46) -> 0 | L46: =SUM(AA46:AI46) -> 0 | M46: =SUM(AB46:AJ46) -> 0 | ... Q46: =SUM(AF46:AN46) -> 0 | S46: =SUM(AG46:AO46) -> 0 | T46: =SUM(X46:AF46) -> 0 | U46: =SUM(Y46:AG46) -> 0 | V46: =SUM(Z46:AH46) -> 0 | W46: =SUM(AA46:AI46) -> 0 | X46: =SUM(AB46:AJ46) -> 0 | Y46: =SUM(AC46:AK46) -> 0 | Z46: =SUM(AD46:AL46) -> 0 | AA46: =SUM(AE46:AM46) -> 0 | ... AE46: =SUM(AI46:AQ46) -> 0 | AG46: =SUM(AK46:AS46) -> 0
B47: GANANCIA ANTES DE IMPUESTOS. | E47: =+E20-E45 -> -7746505 | F47: =+F20-F45 -> 0 | G47: =+G20-G45 -> 0 | H47: =+H20-H45 -> 0 | I47: =+I20-I45 -> 0 | J47: =+J20-J45 -> 0 | K47: =+K20-K45 -> 0 | L47: =+L20-L45 -> 0 | ... Q47: =+Q20-Q45 -> -7746505 | S47: =+S20-S45 -> 49119434 | T47: =+T20-T45 -> 9397775 | U47: =+U20-U45 -> 11579881 | V47: =+V20-V45 -> 14856509 | W47: =+W20-W45 -> 16232617 | X47: =+X20-X45 -> 4250035.7 | Y47: =+Y20-Y45 -> 1204501 | Z47: =+Z20-Z45 -> 1363513 | ... AE47: =+AE20-AE45 -> -6176562.2 | AG47: =+AG20-AG45 -> 12640911 | AH47: =+AH20-AH45 -> 2410046 | AI47: =+AI20-AI45 -> 2744572 | AJ47: =+AJ20-AJ45 -> 2103862 | AK47: =+AK20-AK45 -> 436665 | AL47: =+AL20-AL45 -> 1413250 | AM47: =+AM20-AM45 -> 2698547.8 | AN47: =+AN20-AN45 -> -632395 | ... AS47: =+AS20-AS45 -> 1739989 | AU47: =+AU20-AU45 -> 8967538.6 | AV47: =+AV20-AV45 -> -961521 | AW47: =+AW20-AW45 -> 1260529.9 | AX47: =+AX20-AX45 -> 5073601 | AY47: =+AY20-AY45 -> -3465978 | AZ47: =+AZ20-AZ45 -> -948325.14 | BA47: =+BA20-BA45 -> -807534 | BB47: =+BB20-BB45 -> -231640 | ... BG47: =+BG20-BG45 -> -6522272 | BI47: =+BI20-BI45 -> 290436.49 | BJ47: =+BJ20-BJ45 -> #REF! | BK47: =+BK20-BK45 -> #REF! | BL47: =+BL20-BL45 -> #REF! | BM47: =+BM20-BM45 -> #REF! | BN47: =+BN20-BN45 -> #REF! | BO47: =+BO20-BO45 -> #REF! | BP47: =+BP20-BP45 -> #REF! | ... BU47: =+BU20-BU45 -> #REF! | BW47: =+'NOTAS ERI'!BT175 -> 1066515 | BX47: =+'NOTAS ERI'!BU175 -> #REF! | BY47: =+'NOTAS ERI'!BV175 -> #REF! | BZ47: =+'NOTAS ERI'!BW175 -> #REF! | CA47: =+'NOTAS ERI'!BX175 -> #REF! | CB47: =+'NOTAS ERI'!BY175 -> #REF! | CC47: =+'NOTAS ERI'!BZ175 -> #REF! | CE47: =+CE20-CE45 -> #REF! | CF47: =+CF23-CF45 -> #REF! | CH47: =+CH23-CH45 -> #REF!
AU48: =SUM(BB48:BG48) -> 0
B49: =+'NOTAS ERI'!A177 -> PROVISION IMP. RENTA | E49: =+'NOTAS ERI'!N177 -> 0 | F49: =+'NOTAS ERI'!D177 -> 0 | G49: =+'NOTAS ERI'!E177 -> 0 | H49: =+'NOTAS ERI'!F177 -> 0 | I49: =+'NOTAS ERI'!G177 -> 0 | J49: =+'NOTAS ERI'!H177 -> 0 | K49: =+'NOTAS ERI'!I177 -> 0 | L49: =+'NOTAS ERI'!J177 -> 0 | M49: =+'NOTAS ERI'!K177 -> 0 | ... Q49: =+'NOTAS ERI'!O177 -> 0 | S49: =+'NOTAS ERI'!P177 -> 17191802 | T49: =+'NOTAS ERI'!Q177 -> 3289221.2 | U49: =+'NOTAS ERI'!R177 -> 4052958.3 | V49: =+'NOTAS ERI'!S177 -> 5199778.1 | W49: =+'NOTAS ERI'!T177 -> 5681415.9 | X49: =+'NOTAS ERI'!U177 -> 1487512.5 | Y49: =+'NOTAS ERI'!V177 -> 421575.35 | Z49: =+'NOTAS ERI'!W177 -> 477229.55 | ... AE49: =+'NOTAS ERI'!AB177 -> -2161796.8 | AG49: =+AG47*35% -> 4424318.9 | AH49: =+AH47*35% -> 843516.1 | AI49: =+AI47*35% -> 960600.2 | AJ49: =+AJ47*35% -> 736351.7 | AK49: =+AK47*35% -> 152832.75 | AL49: =+AL47*35% -> 494637.5 | AM49: =+AM47*35% -> 944491.74 | AN49: =+AN47*35% -> -221338.25 | ... AS49: =+AS47*35% -> 608996.15 | AU49: =+AU47*35% -> 3138638.5 | AV49: =+'NOTAS ERI'!AT177 -> 0 | AW49: =+'NOTAS ERI'!AU177 -> 0 | AX49: =+'NOTAS ERI'!AV177 -> 0 | AY49: =+'NOTAS ERI'!AW177 -> 0 | AZ49: =+'NOTAS ERI'!AX177 -> 0 | BA49: =+'NOTAS ERI'!AY177 -> 0 | BB49: =+'NOTAS ERI'!AZ177 -> 0 | BC49: =+'NOTAS ERI'!BA177 -> 0 | ... BG49: =+'NOTAS ERI'!BE177 -> 0 | BI49: =+'NOTAS ERI'!BF177 -> 0 | BJ49: =+'NOTAS ERI'!BG177 -> 0 | BK49: =+'NOTAS ERI'!BH177 -> 0 | BL49: =+'NOTAS ERI'!BI177 -> 0 | BM49: =+'NOTAS ERI'!BJ177 -> 0 | BN49: =+'NOTAS ERI'!BK177 -> 0 | BO49: =+'NOTAS ERI'!BL177 -> 0 | BP49: =+'NOTAS ERI'!BM177 -> 0 | ... BU49: =+'NOTAS ERI'!BR177 -> 0 | BW49: =+'NOTAS ERI'!BT177 -> 0 | BX49: =+'NOTAS ERI'!BU177 -> 0 | BY49: =+'NOTAS ERI'!BV177 -> #REF! | BZ49: =+'NOTAS ERI'!BW177 -> #REF! | CA49: =+'NOTAS ERI'!BX177 -> #REF! | CB49: =+'NOTAS ERI'!BY177 -> #REF! | CC49: =+'NOTAS ERI'!BZ177 -> #REF! | CE49: =+'NOTAS ERI'!CB177 -> #REF! | CF49: =+'NOTAS ERI'!#REF! -> #REF! | CH49: =+'NOTAS ERI'!#REF! -> #REF!
AU50: =SUM(BB50:BG50) -> 0
B51: RESULTADO TOTAL DEL PERIODO. | E51: =+E47-E49 -> -7746505 | F51: =+F47-F49 -> 0 | G51: =+G47-G49 -> 0 | H51: =+H47-H49 -> 0 | I51: =+I47-I49 -> 0 | J51: =+J47-J49 -> 0 | K51: =+K47-K49 -> 0 | L51: =+L47-L49 -> 0 | ... Q51: =+Q47-Q49 -> -7746505 | S51: =+S47-S49 -> 31927632 | T51: =+T47-T49 -> 6108553.8 | U51: =+U47-U49 -> 7526922.7 | V51: =+V47-V49 -> 9656730.9 | W51: =+W47-W49 -> 10551201 | X51: =+X47-X49 -> 2762523.2 | Y51: =+Y47-Y49 -> 782925.65 | Z51: =+Z47-Z49 -> 886283.45 | ... AE51: =+AE47-AE49 -> -4014765.5 | AG51: =+AG47-AG49 -> 8216592.3 | AH51: =+AH47-AH49 -> 1566529.9 | AI51: =+AI47-AI49 -> 1783971.8 | AJ51: =+AJ47-AJ49 -> 1367510.3 | AK51: =+AK47-AK49 -> 283832.25 | AL51: =+AL47-AL49 -> 918612.5 | AM51: =+AM47-AM49 -> 1754056.1 | AN51: =+AN47-AN49 -> -411056.75 | ... AS51: =+AS47-AS49 -> 1130992.9 | AU51: =+AU47-AU49 -> 5828900.1 | AV51: =+AV47-AV49 -> -961521 | AW51: =+AW47-AW49 -> 1260529.9 | AX51: =+AX47-AX49 -> 5073601 | AY51: =+AY47-AY49 -> -3465978 | AZ51: =+AZ47-AZ49 -> -948325.14 | BA51: =+BA47-BA49 -> -807534 | BB51: =+BB47-BB49 -> -231640 | ... BG51: =+BG47-BG49 -> -6522272 | BI51: =+BI47-BI49 -> 290436.49 | BJ51: =+BJ47-BJ49 -> #REF! | BK51: =+BK47-BK49 -> #REF! | BL51: =+BL47-BL49 -> #REF! | BM51: =+BM47-BM49 -> #REF! | BN51: =+BN47-BN49 -> #REF! | BO51: =+BO47-BO49 -> #REF! | BP51: =+BP47-BP49 -> #REF! | ... BU51: =+BU47-BU49 -> #REF! | BW51: =+BW47-BW49 -> 1066515 | BX51: =+BX47-BX49 -> #REF! | BY51: =+BY47-BY49 -> #REF! | BZ51: =+BZ47-BZ49 -> #REF! | CA51: =+CA47-CA49 -> #REF! | CB51: =+CB47-CB49 -> #REF! | CC51: =+CC47-CC49 -> #REF! | CE51: =+CE47-CE49 -> #REF! | CF51: =+CF47-CF49 -> #REF! | CH51: =+CH47-CH49 -> #REF!
B56: EDGAR ORLANDO LESMEZ
B57: =+ESF!B54 -> Representante Legal

Sheet NOTAS ESF
A2: =+ESF!B2 -> JELCOM SOLUCIONES EMPRESARIALES SAS
A3: =+ESF!B3 -> NIT. 901360819
A4: NOTAS A LOS ESTADOS FINANCIEROS
A6: CONCEPTO | B6: 2026 | D6: 2025 | E6: 2025 | F6: 2025 | G6: 2025 | H6: 2025 | I6: 2025 | J6: 2025 | K6: 2025 | L6: 2025 | M6: 2025 | N6: 2025 | O6: 2025 | Q6: 2024 | R6: 2024 | S6: 2024 | T6: 2024 | U6: 2024 | V6: 2024 | W6: 2024 | X6: 2024 | Y6: 2024 | Z6: 2024 | AA6: 2024 | AB6: 2024 | AD6: 2023 | AE6: 2023 | AF6: 2023 | AG6: 2023 | AH6: 2023 | AI6: 2023 | AJ6: 2023 | AK6: 2023 | AL6: 2023 | AM6: 2023 | AN6: 2023 | AO6: 2023 | AQ6: 2022 | AR6: 2022 | AS6: 2022 | AT6: 2022 | AU6: 2022 | AV6: 2022 | AW6: 2022 | AX6: 2022 | AY6: 2022 | AZ6: 2022 | BA6: 2022 | BB6: 2022 | BD6: 2021 | BE6: 2021 | BF6: 2021 | BG6: 2021 | BH6: 2021 | BI6: 2021 | BK6: 2020
B7: ENERO | D7: DICIEMBRE | E7: NOVIEMBRE | F7: OCTUBRE | G7: SEPTIEMBRE | H7: AGOSTO | I7: JULIO | J7: JUNIO | K7: MAYO | L7: ABRIL | M7: MARZO | N7: FEBRERO | O7: ENERO | Q7: DICIEMBRE | R7: NOVIEMBRE | S7: OCTUBRE | T7: SEPTIEMBRE | U7: AGOSTO | V7: JULIO | W7: JUNIO | X7: MAYO | Y7: ABRIL | Z7: MARZO | AA7: FEBRERO | AB7: ENERO | AD7: DICIEMBRE | AE7: NOVIEMBRE | AF7: OCTUBRE | AG7: SEPTIEMBRE | AH7: AGOSTO | AI7: JULIO | AJ7: JUNIO | AK7: MAYO | AL7: ABRIL | AM7: MARZO | AN7: FEBRERO | AO7: ENERO | AQ7: DICIEMBRE | AR7: NOVIEMBRE | AS7: OCTUBRE | AT7: SEPTIEMBRE | AU7: AGOSTO | AV7: JULIO | AW7: JUNIO | AX7: MAYO | AY7: ABRIL | AZ7: MARZO | BA7: FEBERERO | BB7: ENERO | BD7: DICIEMBRE | BE7: SEPTIEMBRE | BF7: AGOSTO | BG7: JULIO | BH7: JUNIO | BI7: MAYO | BK7: DICIEMBRE
A8: ACTIVO
A10: =+ESF!B10 -> Efectivo y Equivalentes al Efectivo | B10: =SUM(B11:B12) -> 26352599 | D10: =SUM(D11:D12) -> 65794723 | E10: =SUM(E11:E12) -> 29244298 | F10: =SUM(F11:F12) -> 21098136 | G10: =SUM(G11:G12) -> 14529916 | H10: =SUM(H11:H12) -> 10355964 | I10: =SUM(I11:I12) -> 11927408 | J10: =SUM(J11:J12) -> 5739207.5 | K10: =SUM(K11:K12) -> 16777658 | ... O10: =SUM(O11:O12) -> 7199659.9 | Q10: =SUM(Q11:Q12) -> 5382680.7 | R10: =SUM(R11:R12) -> 5032561 | S10: =SUM(S11:S12) -> 4883116.8 | T10: =SUM(T11:T12) -> 4072200.8 | U10: =SUM(U11:U12) -> -4649353.1 | V10: =SUM(V11:V12) -> -5795604.9 | W10: =SUM(W11:W12) -> -3994354.1 | X10: =SUM(X11:X12) -> -1573955.3 | ... AB10: =SUM(AB11:AB12) -> 6342950.9 | AD10: =SUM(AD11:AD12) -> 1846377.4 | AE10: =SUM(AE11:AE12) -> -16503757 | AF10: =SUM(AF11:AF12) -> -15088454 | AG10: =SUM(AG11:AG12) -> -16610194 | AH10: =SUM(AH11:AH12) -> -16113342 | AI10: =SUM(AI11:AI12) -> -13926093 | AJ10: =SUM(AJ11:AJ12) -> -15129335 | AK10: =SUM(AK11:AK12) -> -12473354 | ... AO10: =SUM(AO11:AO12) -> -4863415.3 | AQ10: =SUM(AQ11:AQ12) -> 3821900.2 | AR10: =SUM(AR11:AR12) -> 89923 | AS10: =SUM(AS11:AS12) -> 3267146 | AT10: =SUM(AT11:AT12) -> 1261066 | AU10: =SUM(AU11:AU12) -> 102040 | AV10: =SUM(AV11:AV12) -> 0 | AW10: =SUM(AW11:AW12) -> 0 | AX10: =SUM(AX11:AX12) -> 0 | ... BB10: =SUM(BB11:BB12) -> 0 | BD10: =SUM(BD11:BD12) -> 15221800 | BE10: =SUM(BE11:BE12) -> 0 | BF10: =SUM(BF11:BF12) -> 0 | BG10: =SUM(BG11:BG12) -> 0 | BH10: =SUM(BH11:BH12) -> 0 | BI10: =SUM(BI11:BI12) -> 0 | BK10: =SUM(BK11:BK12) -> 2000000
A11: Caja | B11: 25998487 | D11: 25997315 | E11: =-405821.87747997+8830+317000 -> -79991.877 | F11: =-370685.877479956+8830+317000 -> -44855.877 | G11: =-1876839.87747996+8830+317000 -> -1551009.9 | H11: =-1973987.89747995+8830+317000 -> -1648157.9 | I11: =-1949467.89747995+8830+317000 -> -1623637.9 | J11: =-1750737.89747995+8830 -> -1741907.9 | K11: =-630699.547479957+8830 -> -621869.55 | L11: =-3843031.63447995+1519000+2000000 -> -324031.63 | M11: =1664220.36552005+1519000+2000000 -> 5183220.4 | N11: =1763302.01552007+1519000+2000000 -> 5282302 | O11: =3270302.01552006+1519000+2000000 -> 6789302 | Q11: 3820798.8 | R11: =2205793-5200 -> 2200593 | S11: =2317529.84-5200 -> 2312329.8 | T11: =4036144.84-5200 -> 4030944.8 | U11: =-7451579.98447994-5200 -> -7456780 | V11: =-6366357.16-5200 -> -6371557.2 | W11: =-4503093-5200 -> -4508293 | X11: -2623768.2 | Y11: -933035.16 | Z11: 835750.84 | AA11: 2368265.1 | AB11: 4232966.1 | AD11: 290000.44 | AE11: -18234844 | AF11: -15090673 | AG11: -18113640 | AH11: -18142176 | AI11: -14351355 | AJ11: -15251386 | AK11: -14349220 | AL11: -14914912 | AM11: -12512629 | AN11: -10435360 | AO11: -6432878 | AQ11: =150302.152279995+840 -> 151142.15 | BD11: 15200930 | BK11: 2000000
A12: Banco BBVA | B12: 354112 | D12: 39797408 | E12: 29324290 | F12: 21142992 | G12: 16080926 | H12: 12004122 | I12: 13551046 | J12: 7481115.3 | K12: 17399528 | L12: 20319774 | M12: 403421 | N12: 432089.86 | O12: 410357.86 | Q12: 1561881.9 | R12: 2831968 | S12: 2570787 | T12: 41256 | U12: 2807426.9 | V12: 575952.22 | W12: 513938.86 | X12: 1049812.9 | Y12: 2380443 | Z12: 382064 | AA12: 3987838.9 | AB12: 2109984.9 | AD12: 1556377 | AE12: 1731086.7 | AF12: 2218.72 | AG12: 1503445.7 | AH12: 2028833.7 | AI12: 425261.86 | AJ12: 122050.86 | AK12: 1875866 | AL12: 2730721 | AM12: 9185204 | AN12: 2599168 | AO12: 1569462.8 | AQ12: 3670758 | AR12: 89923 | AS12: 3267146 | AT12: 1261066 | AU12: 102040 | AV12: 0 | AW12: 0 | AX12: 0 | AY12: 0 | AZ12: 0 | BA12: 0 | BB12: 0 | BD12: 20870 | BK12: 0
A14: Instrumentos Financieros Cuentas Por Cobrar | B14: =+B15+B47+B40 -> 60550558 | D14: =+D15+D47+D40 -> 26355626 | E14: =+E15+E47+E40 -> 63694677 | F14: =+F15+F47+F40 -> 46536961 | G14: =+G15+G47+G40 -> 53380639 | H14: =+H15+H47+H40 -> 39619796 | I14: =+I15+I47+I40 -> 35652593 | J14: =+J15+J47+J40 -> 33989755 | K14: =+K15+K47+K40 -> 31431872 | ... N14: =+N15+N47+N40 -> 33658111 | O14: =+O15+O47 -> 8143514.7 | Q14: =+Q15+Q47 -> 15258879 | R14: =+R15+R47 -> 14415869 | S14: =+S15+S47 -> 14986890 | T14: =+T15+T47 -> 23162180 | U14: =+U15+U47 -> 28904093 | V14: =+V15+V47 -> 29247383 | W14: =+W15+W47 -> 25029313 | X14: =+X15+X47 -> 33443093 | ... AB14: =+AB15+AB47 -> 21982196 | AD14: =+AD15+AD47 -> 20841140 | AE14: =SUM(AE48:AE53) -> 4765667.3 | AF14: =SUM(AF48:AF53) -> 4380307.3 | AG14: =SUM(AG48:AG53) -> 3878887.7 | AH14: =SUM(AH48:AH53) -> 3706628 | AI14: =SUM(AI48:AI53) -> 3427628 | AJ14: =SUM(AJ48:AJ53) -> 3133668 | AK14: =SUM(AK48:AK53) -> 2794188 | AL14: =SUM(AL48:AL53) -> 2292848 | ... AO14: =SUM(AO48:AO53) -> 1765095 | AQ14: =+AQ15+AQ47 -> 2543848 | AR14: =+AR15+AR50+AR51+AR53+AR48 -> 797739 | AS14: =+AS15+AS50+AS51+AS53+AS48 -> 36875345 | AT14: =+AT15+AT50+AT51+AT53+AT48 -> 52823725 | AU14: =+AU15+AU50+AU51+AU53+AU48 -> 31077778 | AV14: =+AV15+AV50+AV51+AV53+AV48 -> 17206089 | AW14: =+AW15+AW50+AW51+AW53+AW48 -> 17206089 | AX14: =+AX15+AX50+AX51+AX53+AX48 -> 17206089 | AY14: =+AY15+AY50+AY51+AY53+AY48 -> 17806261 | ... BB14: =+BB15+BB50+BB51+BB53+BB48 -> 11686588 | BD14: =+BD15+BD47 -> 501588 | BE14: =SUM(BE15:BE51) -> 0 | BF14: =SUM(BF15:BF51) -> 0 | BG14: =SUM(BG15:BG51) -> 0 | BH14: =SUM(BH15:BH51) -> 0 | BI14: =SUM(BI15:BI51) -> 0 | BK14: =+BK15+BK47 -> 0
A15: Clientes Nacionales | B15: =SUM(B16:B33) -> 49899431 | D15: =SUM(D16:D33) -> 14105655 | E15: =SUM(E16:E33) -> 46074189 | F15: =SUM(F16:F33) -> 36275152 | G15: =SUM(G16:G33) -> 46174034 | H15: =SUM(H16:H33) -> 33787334 | I15: =SUM(I16:I33) -> 30341334 | J15: =SUM(J16:J33) -> 29262159 | K15: =SUM(K16:K33) -> 27169659 | ... O15: =SUM(O16:O33) -> 2080600 | Q15: =SUM(Q16:Q33) -> 8811554 | R15: =SUM(R16:R33) -> 8314574 | S15: =SUM(S16:S33) -> 9236020 | T15: =SUM(T16:T33) -> 17757340 | U15: =SUM(U16:U33) -> 23845283 | V15: =SUM(V16:V33) -> 24585603 | W15: =SUM(W16:W33) -> 20801143 | X15: =SUM(X16:X33) -> 29580543 | ... AB15: =SUM(AB16:AB33) -> 16607923 | AD15: =SUM(AD16:AD33) -> 15737723 | AE15: =SUM(AE16:AE33) -> 17267934 | AF15: =SUM(AF16:AF33) -> 21876481 | AG15: =SUM(AG16:AG33) -> 9035880.8 | AH15: =SUM(AH16:AH33) -> 15089781 | AI15: =SUM(AI16:AI33) -> 15577681 | AJ15: =SUM(AJ16:AJ33) -> 58168881 | AK15: =SUM(AK16:AK33) -> 52844881 | ... AO15: =SUM(AO16:AO33) -> 2268800.8 | AQ15: =SUM(AQ16:AQ33) -> 500000 | AR15: =SUM(AR16:AR33) -> 0 | AS15: =SUM(AS16:AS33) -> 36093366 | AT15: =SUM(AT16:AT33) -> 52072106 | AU15: =SUM(AU16:AU33) -> 30475506 | AV15: =SUM(AV16:AV33) -> 16676582 | AW15: =SUM(AW16:AW33) -> 16676582 | AX15: =SUM(AX16:AX33) -> 16676582 | ... BB15: =SUM(BB16:BB33) -> 11190000 | BD15: =SUM(BD16:BD33) -> 0 | BE15: =SUM(BE16:BE33) -> 0 | BF15: =SUM(BF16:BF33) -> 0 | BG15: =SUM(BG16:BG33) -> 0 | BH15: =SUM(BH16:BH33) -> 0 | BI15: =SUM(BI16:BI33) -> 0 | BK15: =SUM(BK16:BK33) -> 0
A16: Departamento de Santander | AS16: 10000000 | AT16: 10000000 | AU16: 10000000 | AV16: 10000000 | AW16: 10000000 | AX16: 10000000 | AY16: 10000000 | AZ16: 10000000 | BA16: 10000000 | BB16: 10000000
A17: Noriega Campiño y CIA S en C | B17: 540500 | D17: 540500 | E17: 540500 | F17: 1621500 | G17: 1621500 | H17: =1137400-37600-18800 -> 1081000 | I17: =1677900-37600-18800 -> 1621500 | J17: =1118600-37600 -> 1081000 | K17: 0 | L17: 1081000 | M17: 1081000 | N17: 540500 | O17: 1081000 | Q17: 1634354 | R17: 1637174 | S17: 1559020 | T17: 2102340 | U17: 2105160 | V17: 2107480 | W17: =+X17 -> 1032120 | X17: 1032120 | Y17: =+Z17 -> 1075360 | Z17: =1081000-2820-2820 -> 1075360 | AA17: 0 | AB17: 559300 | AD17: 0 | AE17: 1119600 | AF17: 560300 | AG17: 1000 | AI17: 559300 | AJ17: 1081000 | AK17: 1190000 | AL17: 1190000 | AM17: 2300000 | AN17: 1150000 | AO17: 1150000 | AQ17: 0 | AS17: 4060875 | AT17: 1353625 | AU17: 1353625 | BD17: 0 | BK17: 0
A18: Cajasan | B18: 12584000 | D18: 12584000 | E18: 12584000 | F18: 0 | G18: 12584000 | H18: 0 | I18: 0 | J18: 0 | K18: 0 | L18: 0 | M18: 0 | N18: 0 | O18: 0 | Q18: 6177600 | R18: 6177600 | S18: 6177600 | T18: 12355200 | U18: =6426000-248400 -> 6177600 | V18: =6426000-248400 -> 6177600 | W18: =6426000-248400 -> 6177600 | X18: =12603600-248400 -> 12355200 | Y18: =6426000-248400 -> 6177600 | Z18: 12355200 | AA18: =6426000-248400 -> 6177600 | AB18: =6426000-248400 -> 6177600 | AD18: 6426000 | AE18: 56400 | AF18: 4600000 | AH18: 4576000 | AI18: 4576000 | AJ18: 4576000 | AL18: 0 | AM18: 0 | AN18: 0 | AO18: 0 | AQ18: 0 | AS18: 10704700 | AT18: 29809500 | AU18: 9936500 | BD18: 0 | BK18: 0
A19: Camara de Comercio de Bucaramanga | B19: 0 | D19: 0 | E19: 0 | F19: 0 | G19: 0 | H19: 0 | I19: 0 | J19: 0 | K19: 0 | L19: 0 | M19: 0 | N19: 0 | O19: 0 | Q19: 0 | R19: 0 | S19: 0 | T19: 0 | U19: =+V19 -> 4400000 | V19: =+W19 -> 4400000 | W19: =+X19 -> 4400000 | X19: =+Y19 -> 4400000 | Y19: =+Z19 -> 4400000 | Z19: =+AA19 -> 4400000 | AA19: =+AB19 -> 4400000 | AB19: =+AD19 -> 4400000 | AD19: 4400000 | AE19: 4400000 | AF19: 4400000 | AG19: 4400000 | AH19: 4400000 | AI19: 4400000 | AJ19: 47600000 | AK19: 47600000 | AL19: 0 | AM19: 0 | AN19: 0 | AO19: 0 | AQ19: 0 | BD19: 0 | BK19: 0
A20: Cubik Construcciones SAS | U20: =+V20 -> 0 | X20: =+Y20 -> 0 | AL20: 0 | AM20: 0 | AN20: 0 | AO20: 0 | AQ20: 0 | AS20: 428400 | AT20: 428400 | BD20: 0 | BK20: 0
A21: Centro Comercial San Gil Plaza | B21: 981155 | D21: 981155 | E21: 981155 | F21: 981155 | G21: 0 | H21: 0 | I21: 0 | J21: 473025 | K21: 473025 | L21: 473025 | U21: =+V21 -> 0 | X21: =+Y21 -> 0 | AD21: 0 | AE21: 782333.37 | AF21: 276080 | AG21: 276080 | AH21: 276080 | AI21: 276080 | AJ21: 276080 | AK21: 276080 | AL21: 276080 | AM21: 0 | AN21: 0 | AO21: 0 | AQ21: 0 | AS21: 24000 | AT21: 714000 | BD21: 0 | BK21: 0
A22: Jhoan Sebastian Dueñas Gomez (Duoptica) | B22: 0 | D22: 0 | E22: 0 | F22: 0 | G22: 0 | H22: 0 | I22: 0 | J22: 0 | K22: 0 | L22: 0 | M22: 0 | N22: 0 | O22: 0 | Q22: 0 | R22: 0 | S22: 0 | T22: 0 | U22: =+V22 -> 0 | V22: =+W22 -> 0 | W22: =+X22 -> 0 | X22: =+Y22 -> 0 | Y22: =+Z22 -> 0 | Z22: =+AA22 -> 0 | AA22: =+AB22 -> 0 | AB22: =+AC22 -> 0 | AD22: 0 | AE22: 50000.76 | AF22: 50000.76 | AG22: 50000.76 | AH22: 50000.76 | AI22: 50000.76 | AJ22: 50000.76 | AK22: 50001 | AL22: 50000.76 | AM22: 500001 | AN22: 500000.76 | AO22: 500000.76 | AQ22: 500000 | AS22: 499999.92 | AT22: 499999.92 | BD22: 0 | BK22: 0
A23: Faustino Tapias | B23: 0 | D23: 0 | E23: 0 | F23: 0 | G23: 0 | H23: 0 | I23: 0 | J23: 0 | K23: 0 | L23: 0 | M23: 0 | N23: 0 | O23: 0 | Q23: 0 | R23: 0 | S23: 0 | T23: 0 | U23: =+V23 -> 1285200 | V23: =+W23 -> 1285200 | W23: =+X23 -> 1285200 | X23: =+Y23 -> 1285200 | Y23: =+Z23 -> 1285200 | Z23: 1285200 | AA23: 642600 | AB23: =+AC23 -> 0 | AD23: 0
A24: Jose Alberto Bastilla Hernandez | B24: 0 | D24: 0 | E24: 0 | F24: 0 | G24: 0 | H24: 0 | I24: 0 | J24: 499600 | K24: 499600 | L24: 499600 | M24: =499600+499600 -> 999200 | N24: 499600 | O24: 999600 | Q24: 999600 | R24: 499800 | S24: 1499400 | T24: 999800 | U24: =+V24 -> 999600 | V24: =499800+499800 -> 999600 | W24: 0 | X24: 999600 | Y24: 499800 | Z24: 999600 | AA24: 499800 | AB24: 499800 | AD24: 499800 | AF24: 499800 | AG24: 499800 | AI24: 499800 | AJ24: 499800 | AK24: 499600 | AL24: 499800 | AM24: 0 | AN24: 0 | AO24: 0 | AQ24: 0 | BD24: 0 | BK24: 0
A25: Antonio Maria Bravo Rodriguez | B25: 0 | D25: 0 | E25: 0 | F25: 0 | G25: 0 | H25: 0 | I25: 0 | J25: 0 | K25: 0 | L25: 0 | M25: 0 | N25: 0 | O25: 0 | Q25: 0 | R25: 0 | S25: 0 | T25: 0 | U25: =+V25 -> 425423 | V25: 425423 | W25: 425423 | X25: =+Y25 -> 425423 | Y25: 425423 | Z25: 425423 | AA25: =+AB25 -> 425423 | AB25: =+AD25 -> 425423 | AD25: 425423 | AE25: 476000 | AF25: 476000 | AG25: 714000 | AH25: 952000 | AI25: 952000 | AJ25: 952000 | AK25: 714000 | AL25: 476000 | AM25: 0 | AN25: 0 | AO25: 0 | AQ25: 0 | BD25: 0 | BK25: 0
A26: Gustavo Benitez Verdugo | B26: 0 | D26: 0 | E26: 0 | F26: 0 | G26: 0 | H26: 0 | I26: 0 | J26: 0 | K26: 0 | L26: 0 | M26: 0 | N26: 0 | O26: 0 | Q26: 0 | R26: 0 | S26: 0 | T26: 0 | U26: =+V26 -> 0 | X26: =+Y26 -> 0 | AS26: 700009.3 | AT26: 1399999.3 | AU26: 699999.65
A27: Metrogas de Colombia S.A | B27: 0 | D27: 0 | E27: 0 | F27: 0 | G27: 0 | H27: 0 | I27: 0 | J27: 0 | K27: 0 | L27: 0 | M27: 0 | N27: 0 | O27: 0 | Q27: 0 | R27: 0 | S27: 0 | T27: 0 | U27: =+V27 -> 0 | X27: =+Y27 -> 0 | AS27: 1316424.4 | AT27: 1316424.4 | AU27: 1316424.4 | AV27: 1316424.4 | AW27: 1316424.4 | AX27: 1316424.4 | AY27: 1316424.4 | AZ27: 1316424.4
A28: Federacion Nacional de Comerciantes | B28: 0 | D28: 0 | E28: 0 | F28: 0 | G28: 0 | H28: 0 | I28: 0 | J28: 0 | K28: 0 | L28: 0 | M28: 0 | N28: 0 | O28: 0 | Q28: 0 | R28: 0 | S28: 0 | T28: 0 | U28: =+V28 -> 6152300 | V28: 6152300 | W28: =+X28 -> 5593000 | X28: 5593000 | Y28: 4474400 | Z28: =+AA28+1118600 -> 4474400 | AA28: =+AB28 -> 3355800 | AB28: =+AD28+559300 -> 3355800 | AD28: 2796500 | AE28: 4213600 | AF28: 3654300 | AG28: 3095000 | AH28: 2535700 | AI28: 3114500 | AJ28: 3134000 | AK28: 2515200 | AL28: 2475200 | AM28: 1237600 | AN28: 618800 | AO28: 618800 | AQ28: 0 | AS28: 1218957.2 | AT28: 600157.2 | AU28: 1218957.2 | AV28: 600157.2 | AW28: 600157.2 | AX28: 600157.2 | AY28: 1200329.2 | AZ28: 599617.2 | BD28: 0 | BK28: 0
A29: Faustino Tapias | B29: 0 | D29: 0 | E29: 0 | F29: 0 | G29: 0 | H29: 0 | I29: 0 | J29: 0 | K29: 0 | L29: 0 | M29: 0 | N29: 0 | O29: 0 | Q29: 0 | R29: 0 | S29: 0 | T29: 0 | U29: =+V29 -> 0 | X29: =+Y29 -> 0 | Y29: 0 | AA29: 0
A30: Empresa Social del Estado Hospital Regional de San Gil | B30: 35793776 | D30: 0 | E30: =34813534-2845000 -> 31968534 | F30: =34455534-2487000 -> 31968534 | G30: =34186534-2218000 -> 31968534 | H30: =33828534-1860000 -> 31968534 | I30: =30399834-1680000 -> 28719834 | J30: =28660534-1452000 -> 27208534 | K30: =27538034-1341000 -> 26197034 | L30: =27427033-1230000 -> 26197033 | M30: =26197033+N30 -> 52394066 | N30: 26197033 | O30: 0 | Q30: 0 | AD30: 0 | AQ30: 0
A31: Alirio Salazar Bayona | B31: 0 | D31: 0 | E31: 0 | F31: 737800 | G31: 0 | H31: 737800 | I31: 0 | J31: 0 | K31: 0 | L31: 0 | M31: 0 | N31: 0 | O31: 0 | Q31: 0 | R31: 0 | S31: 0 | T31: 0 | U31: 0 | V31: 738000 | W31: 737800 | X31: =+Y31 -> 0 | Y31: =+Z31 -> 0 | Z31: =+AA31 -> 0 | AA31: =+AB31 -> 0 | AB31: =+AC31 -> 0 | AD31: 0 | AQ31: 0
A32: Edwin Leonardo Vincherry Valbuena | U32: =+V32 -> 0 | X32: =+Y32 -> 0
A33: Centro Comercial El Puente | B33: 0 | D33: 0 | E33: 0 | F33: 966163 | G33: 0 | H33: 0 | I33: 0 | J33: 0 | K33: 0 | L33: 0 | M33: 0 | N33: 0 | O33: 0 | Q33: 0 | R33: 0 | S33: 0 | T33: =+U33 -> 2300000 | U33: =+V33 -> 2300000 | V33: 2300000 | W33: 1150000 | X33: 3490000 | Y33: =+Z33 -> 2340000 | Z33: =+AA33 -> 2340000 | AA33: 2340000 | AB33: 1190000 | AD33: 1190000 | AE33: 6170000 | AF33: 7360000 | AH33: 2300000 | AI33: 1150000 | AQ33: 0 | AS33: 7140000 | AT33: 5950000 | AU33: 5950000 | AV33: 4760000 | AW33: 4760000 | AX33: 4760000 | AY33: 4760000 | AZ33: 3570000 | BA33: 2380000 | BB33: 1190000 | BD33: 0 | BK33: 0
A34: Cuentas por cobrar a socios
A35: Credito personal (Edgar lezmez)
A36: Seguros Generales Suramericana SA
A37: Ana Milena Valdes | BJ37: 0 | BK37: 0
A38: Cuentas por cobrar a trabajadores
A39: Otros Anticipos
A40: Anticipos y avances | B40: =SUM(B41:B46) -> 0 | D40: =SUM(D41:D46) -> 752100 | E40: =SUM(E41:E46) -> 7800000 | F40: =SUM(F41:F46) -> 1800000 | G40: =+G41 -> 0 | H40: =+H41 -> 0 | I40: =+I41 -> 0 | J40: =+J41 -> 0 | K40: =+K41 -> 0 | L40: =+L41 -> 600000 | M40: =+M41 -> 0 | N40: =+N41 -> 70210 | O40: 0 | Q40: 0 | AD40: 0 | AQ40: 0
A41: Proveedor | L41: 600000 | M41: 0 | N41: 70210 | O41: 0 | Q41: 0 | AD41: 0 | AQ41: 0
A42: Prestamos a Particulares
A45: Supermercado multihogar (Ricrado Cobos) | B45: 0 | D45: 752100 | Q45: 0 | AD45: 0
A46: Otros (Milton Ruiz) | B46: 0 | D46: 0 | E46: =1800000+6000000 -> 7800000 | F46: 1800000
A47: Anticipo de Impuestos | B47: =SUM(B48:B53) -> 10651127 | D47: =SUM(D48:D53) -> 11497871 | E47: =SUM(E48:E53) -> 9820487.7 | F47: =SUM(F48:F53) -> 8461808.7 | G47: =SUM(G48:G53) -> 7206604.7 | H47: =SUM(H48:H53) -> 5832461.7 | I47: =SUM(I48:I53) -> 5311258.7 | J47: =SUM(J48:J53) -> 4727595.7 | K47: =SUM(K48:K53) -> 4262212.7 | ... O47: =SUM(O48:O53) -> 6062914.7 | Q47: =SUM(Q48:Q53) -> 6447325.1 | R47: =SUM(R48:R53) -> 6101294.8 | S47: =SUM(S48:S53) -> 5750870 | T47: =SUM(T48:T53) -> 5404840 | U47: =SUM(U48:U53) -> 5058809.7 | V47: =SUM(V48:V53) -> 4661779.5 | W47: =SUM(W48:W53) -> 4228169.9 | X47: =SUM(X48:X53) -> 3862550 | ... AB47: =SUM(AB48:AB53) -> 5374273 | AD47: =SUM(AD48:AD53) -> 5103417.3 | AE47: =SUM(AE48:AE53) -> 4765667.3 | AF47: =SUM(AF48:AF53) -> 4380307.3 | AG47: =SUM(AG48:AG53) -> 3878887.7 | AH47: =SUM(AH48:AH53) -> 3706628 | AI47: =SUM(AI48:AI53) -> 3427628 | AJ47: =SUM(AJ48:AJ53) -> 3133668 | AK47: =SUM(AK48:AK53) -> 2794188 | ... AO47: =SUM(AO48:AO53) -> 1765095 | AQ47: =SUM(AQ48:AQ53) -> 2043848 | AR47: =SUM(AR48:AR53) -> 797739 | AS47: =SUM(AS48:AS53) -> 781979 | AT47: =SUM(AT48:AT53) -> 751619 | AU47: =SUM(AU48:AU53) -> 602272 | AV47: =SUM(AV48:AV53) -> 529507 | AW47: =SUM(AW48:AW53) -> 529507 | AX47: =SUM(AX48:AX53) -> 529507 | ... BB47: =SUM(BB48:BB53) -> 496588 | BD47: =SUM(BD48:BD53) -> 501588 | BE47: =SUM(BE48:BE53) -> 0 | BF47: =SUM(BF48:BF53) -> 0 | BG47: =SUM(BG48:BG53) -> 0 | BH47: =SUM(BH48:BH53) -> 0 | BI47: =SUM(BI48:BI53) -> 0 | BK47: =SUM(BK48:BK53) -> 0
A48: Impuesto de Renta y Complementarios | B48: =+D48 -> 1604000 | D48: =+E48 -> 1604000 | E48: =+F48 -> 1604000 | F48: =+G48 -> 1604000 | G48: =+H48 -> 1604000 | H48: =+I48 -> 1604000 | I48: =+J48 -> 1604000 | J48: 1604000 | K48: 1604000 | L48: =+M48 -> 1857000 | M48: =+N48 -> 1857000 | N48: =+O48 -> 1857000 | O48: =+Q48 -> 1857000 | Q48: =+R48 -> 1857000 | R48: =+S48 -> 1857000 | S48: 1857000 | T48: 1857000 | U48: 1857000 | V48: 1857000 | W48: =+X48 -> 1857000 | X48: =1857000 -> 1857000 | Y48: 1906000 | Z48: 1906000 | AA48: 1906000 | AB48: 1906000 | AD48: 1906000 | AE48: 1906000 | AF48: 1906000 | AG48: 1906000 | AH48: 1906000 | AI48: 1906000 | AJ48: 1906000 | AK48: 1906000 | AL48: 1906000 | AM48: 135000 | AN48: 135000 | AO48: 135000 | AQ48: 135000 | AR48: 135000 | AS48: 135000 | AT48: 135000 | AU48: 135000 | AV48: 135000 | AW48: 135000 | AX48: 135000 | AY48: 135000 | AZ48: 135000 | BA48: 135000 | BB48: 135000 | BD48: 0
A49: Saldo de Retencion
A50: Retencion en la Fuente | B50: =+D50+440000 -> 4148322 | D50: =+E50+440000+244000 -> 3708322 | E50: =+F50+472476+122000 -> 3024322 | F50: =+G50+440000+33000 -> 2429846 | G50: =+H50+477600+122000 -> 1956846 | H50: =92946+15900+37600+18800+1036000+14000+14000+106000+22000 -> 1357246 | I50: =92946+15900+37600+18800+1036000+14000+14000+106000 -> 1335246 | J50: =92946+37600+1036000+14000+14000 -> 1194546 | K50: =92946+1036000+14000 -> 1142946 | L50: =+M50+18800+1036000 -> 4230000 | M50: =+N50+18800+18800 -> 3175200 | N50: =+O50 -> 3137600 | O50: =+Q50+18800 -> 3137600 | Q50: =+R50+18800+216000 -> 3118800 | R50: =+S50+18800+216000 -> 2884000 | S50: =+T50+18800+216000 -> 2649200 | T50: =+U50+18800+216000 -> 2414400 | U50: =+V50+256000+18800 -> 2179600 | V50: =+W50+216000+40000+37600 -> 1904800 | W50: =+X50+256000 -> 1611200 | X50: =1280000+37600+37600 -> 1355200 | Y50: =+Z50+256000 -> 3020000 | Z50: =+AA50+256000+37600 -> 2764000 | AA50: =+AB50+256000 -> 2470400 | AB50: 2214400 | AD50: 1958400 | AE50: 1656400 | AF50: 1400400 | AG50: 984400 | AH50: 906800 | AI50: 706800 | AJ50: 506800 | AK50: 269200 | AL50: 229200 | AM50: 1679700 | AN50: 1639700 | AO50: 1570500 | AQ50: 1490500 | AR50: 317780 | AS50: 317780 | AT50: 317780 | AU50: 317780 | AV50: 317780 | AW50: 317780 | AX50: 317780 | AY50: 317780 | AZ50: 317780 | BA50: 317780 | BB50: 317780 | BD50: 317780 | BK50: 0
A51: Auto-Renta | B51: =+D51+495256 -> 4568804.7 | D51: =+E51+455383 -> 4073548.7 | E51: =+F51+462203 -> 3618165.7 | F51: =+G51+480204 -> 3155962.7 | G51: =+H51+472543 -> 2675758.7 | H51: =+I51+341203 -> 2203215.7 | I51: =+J51+320963 -> 1862012.7 | J51: =+K51+316783 -> 1541049.7 | K51: =+L51+292755-1051705 -> 1224266.7 | L51: =+M51+302016 -> 1983216.7 | M51: =+N51+325033 -> 1681200.7 | N51: =+O51+287853 -> 1356167.7 | O51: =+Q51+16610 -> 1068314.7 | Q51: =+R51+76010 -> 1051704.7 | R51: =+S51+80405 -> 975694.69 | S51: =+T51+76010 -> 895289.69 | T51: =+U51+76010 -> 819279.69 | U51: =+V51+87010 -> 743269.69 | V51: =+W51+101970 -> 656259.69 | W51: =+X51+77220 -> 554289.69 | X51: 477069.69 | Y51: =+Z51+83160 -> 1500873 | Z51: =+AA51+113080 -> 1417713 | AA51: =+AB51+83160 -> 1304633 | AB51: =1130943+90530 -> 1221473 | AD51: 1130943.3 | AE51: 1095193.3 | AF51: 965833.31 | AG51: 880413.65 | AH51: 785754 | AI51: 730754 | AJ51: 660794 | AK51: 582914 | AL51: 121574 | AM51: 52321 | AN51: 40161 | AO51: 23521 | AQ51: 382274 | AR51: 309151 | AS51: 293391 | AT51: 263031 | AU51: 113684 | AV51: 40919 | AW51: 40919 | AX51: 40919 | AY51: 40919 | AZ51: 36881 | BA51: 16000 | BB51: 8000 | BD51: 148000 | BK51: 0
A52: Rete Iva 15% | D52: =+E52+236000+236000 -> 1848000 | E52: =+F52+236000 -> 1376000 | F52: =+G52+236000 -> 1140000 | G52: =+H52+236000 -> 904000 | H52: =+I52+158000 -> 668000 | I52: =+J52+122000 -> 510000 | J52: =+K52+97000 -> 388000 | K52: =+L52+97000 -> 291000 | L52: 194000
A53: Rete Ica | B53: =+D53+66000 -> 330000 | D53: =+E53+66000 -> 264000 | E53: =+F53+66000 -> 198000 | F53: =+G53+66000 -> 132000 | G53: 66000 | H53: =+I53 -> 0 | I53: =+J53 -> 0 | J53: =+K53 -> 0 | K53: =+L53 -> 0 | L53: =+M53 -> 0 | M53: =+N53 -> 0 | N53: 0 | O53: 0 | Q53: 419820.43 | R53: 384600.13 | S53: 349380.29 | T53: 314160.29 | U53: 278940 | V53: 243719.82 | W53: 205680.18 | X53: 173280.34 | Y53: 135240.07 | Z53: 102840.07 | AA53: 64800 | AB53: 32400 | AD53: 108074 | AE53: 108074 | AF53: 108074 | AG53: 108074 | AH53: 108074 | AI53: 84074 | AJ53: 60074 | AK53: 36074 | AL53: 36074 | AM53: 36074 | AN53: 36074 | AO53: 36074 | AQ53: 36074 | AR53: 35808 | AS53: 35808 | AT53: 35808 | AU53: 35808 | AV53: 35808 | AW53: 35808 | AX53: 35808 | AY53: 35808 | AZ53: 35808 | BA53: 35808 | BB53: 35808 | BD53: 35808 | BK53: 0
A55: INVENTARIOS
A56: Mercancias no fabricadas
A57: Ajuste Inventario final
A58: TOTAL INVENTARIOS | B58: =+B56+B57 -> 0 | D58: =+D56+D57 -> 0 | E58: =+E56+E57 -> 0 | F58: =+F56+F57 -> 0 | G58: =+G56+G57 -> 0 | H58: =+H56+H57 -> 0 | I58: =+I56+I57 -> 0 | J58: =+J56+J57 -> 0 | K58: =+K56+K57 -> 0 | ... O58: =+O56+O57 -> 0 | Q58: =+Q56+Q57 -> 0 | R58: =+R56+R57 -> 0 | S58: =+S56+S57 -> 0 | T58: =+T56+T57 -> 0 | U58: =+U56+U57 -> 0 | V58: =+V56+V57 -> 0 | W58: =+W56+W57 -> 0 | X58: =+X56+X57 -> 0 | ... AB58: =+AB56+AB57 -> 0 | AD58: =+AD56+AD57 -> 0 | AE58: =+AE56+AE57 -> 0 | AF58: =+AF56+AF57 -> 0 | AG58: =+AG56+AG57 -> 0 | AH58: =+AH56+AH57 -> 0 | AI58: =+AI56+AI57 -> 0 | AJ58: =+AJ56+AJ57 -> 0 | AK58: =+AK56+AK57 -> 0 | ... AO58: =+AO56+AO57 -> 0 | AQ58: =+AQ56+AQ57 -> 0 | AR58: =+AR56+AR57 -> 0 | AS58: =+AS56+AS57 -> 0 | AT58: =+AT56+AT57 -> 0 | AU58: =+AU56+AU57 -> 0 | AV58: =+AV56+AV57 -> 0 | AW58: =+AW56+AW57 -> 0 | AX58: =+AX56+AX57 -> 0 | ... BB58: =+BB56+BB57 -> 0 | BD58: =+BD56+BD57 -> 0 | BE58: =+BE56+BE57 -> 0 | BF58: =+BF56+BF57 -> 0 | BG58: =+BG56+BG57 -> 0 | BH58: =+BH56+BH57 -> 0 | BI58: =+BI56+BI57 -> 0 | BK58: =+BK56+BK57 -> 0
A61: Propiedad Planta Y Equipo | B61: =+B62+B65 -> 17386530 | D61: =+D62+D65 -> 17386530 | E61: =+E62+E65 -> 17386530 | F61: =+F62+F65 -> 17386530 | G61: =+G62+G65 -> 17386530 | H61: =+H62+H65 -> 17386530 | I61: =+I62+I65 -> 17386530 | J61: =+J62+J65 -> 17386530 | K61: =+K62+K65 -> 17386530 | ... O61: =+O62+O65 -> 17386530 | Q61: =+Q62+Q65 -> 17386530 | R61: =+R62+R65 -> 17386530 | S61: =+S62+S65 -> 17386530 | T61: =+T62+T65 -> 17386530 | U61: =+U62+U65 -> 17386530 | V61: =+V62+V65 -> 17386530 | W61: =+W62+W65 -> 17386530 | X61: =+X62+X65 -> 17386530 | ... AB61: =+AB62+AB65 -> 17386530 | AD61: =+AD62+AD65 -> 17386530 | AE61: =+AE62+AE65 -> 13183193 | AF61: =+AF62+AF65 -> 13183193 | AG61: =+AG62+AG65 -> 13183193 | AH61: =+AH62+AH65 -> 13183193 | AI61: =+AI62+AI65 -> 13183193 | AJ61: =+AJ62+AJ65 -> 13183193 | AK61: =+AK62+AK65 -> 13183193 | ... AO61: =+AO62+AO65 -> 13183193 | AQ61: =+AQ62+AQ65 -> 13183193 | AR61: =+AR62+AR65 -> 9640732 | AS61: =+AS62+AS65 -> 9853785 | AT61: =+AT62+AT65 -> 10066838 | AU61: =+AU62+AU65 -> 10279891 | AV61: =+AV62+AV65 -> 6892944 | AW61: =+AW62+AW65 -> 7105997 | AX61: =+AX62+AX65 -> 7319050 | ... BB61: =+BB62+BB65 -> 8171262 | BD61: =+BD62+BD65 -> 9583193 | BE61: =+BE62+BE65 -> 0 | BF61: =+BF62+BF65 -> 0 | BG61: =+BG62+BG65 -> 0 | BH61: =+BH62+BH65 -> 0 | BI61: =+BI62+BI65 -> 0 | BK61: =+BK62+BK65 -> 0
A62: Equipo de Oficina | B62: =SUM(B63:B64) -> 8986530 | D62: =SUM(D63:D64) -> 8986530 | E62: =SUM(E63:E64) -> 8986530 | F62: =SUM(F63:F64) -> 8986530 | G62: =SUM(G63:G64) -> 8986530 | H62: =SUM(H63:H64) -> 8986530 | I62: =SUM(I63:I64) -> 8986530 | J62: =SUM(J63:J64) -> 8986530 | K62: =SUM(K63:K64) -> 8986530 | ... O62: =SUM(O63:O64) -> 8986530 | Q62: =SUM(Q63:Q64) -> 8986530 | R62: =SUM(R63:R64) -> 8986530 | S62: =SUM(S63:S64) -> 8986530 | T62: =SUM(T63:T64) -> 8986530 | U62: =SUM(U63:U64) -> 8986530 | V62: =SUM(V63:V64) -> 8986530 | W62: =SUM(W63:W64) -> 8986530 | X62: =SUM(X63:X64) -> 8986530 | ... AB62: =SUM(AB63:AB64) -> 8986530 | AD62: =SUM(AD63:AD64) -> 8986530 | AE62: =SUM(AE63:AE64) -> 4783193 | AF62: =SUM(AF63:AF64) -> 4783193 | AG62: =SUM(AG63:AG64) -> 4783193 | AH62: =SUM(AH63:AH64) -> 4783193 | AI62: =SUM(AI63:AI64) -> 4783193 | AJ62: =SUM(AJ63:AJ64) -> 4783193 | AK62: =SUM(AK63:AK64) -> 4783193 | ... AO62: =SUM(AO63:AO64) -> 4783193 | AQ62: =SUM(AQ63:AQ64) -> 4783193 | AR62: =SUM(AR63:AR64) -> 4783193 | AS62: =SUM(AS63:AS64) -> 4783193 | AT62: =SUM(AT63:AT64) -> 4783193 | AU62: =SUM(AU63:AU64) -> 4783193 | AV62: =SUM(AV63:AV64) -> 4783193 | AW62: =SUM(AW63:AW64) -> 4783193 | AX62: =SUM(AX63:AX64) -> 4783193 | ... BB62: =SUM(BB63:BB64) -> 4783193 | BD62: =SUM(BD63:BD64) -> 4783193 | BE62: =SUM(BE63:BE64) -> 0 | BF62: =SUM(BF63:BF64) -> 0 | BG62: =SUM(BG63:BG64) -> 0 | BH62: =SUM(BH63:BH64) -> 0 | BI62: =SUM(BI63:BI64) -> 0 | BK62: =SUM(BK63:BK64) -> 0
A63: Muebles y Enseres | B63: 8986530 | D63: 8986530 | E63: 8986530 | F63: 8986530 | G63: 8986530 | H63: 8986530 | I63: 8986530 | J63: 8986530 | K63: 8986530 | L63: 8986530 | M63: 8986530 | N63: 8986530 | O63: 8986530 | Q63: 8986530 | R63: 8986530 | S63: 8986530 | T63: 8986530 | U63: 8986530 | V63: 8986530 | W63: 8986530 | X63: =4783193+20000000-11130000-4666663 -> 8986530 | Y63: =4783193+20000000-11130000-4666663 -> 8986530 | Z63: =4783193+20000000-11130000-4666663 -> 8986530 | AA63: =4783193+20000000-11130000-4666663 -> 8986530 | AB63: =4783193+20000000-11130000-4666663 -> 8986530 | AD63: =4783193+20000000-11130000-4666663 -> 8986530 | AE63: 4783193 | AF63: 4783193 | AG63: 4783193 | AH63: 4783193 | AI63: 4783193 | AJ63: 4783193 | AK63: 4783193 | AL63: 4783193 | AM63: 4783193 | AN63: 4783193 | AO63: 4783193 | AQ63: 4783193 | AR63: 4783193 | AS63: 4783193 | AT63: 4783193 | AU63: 4783193 | AV63: 4783193 | AW63: 4783193 | AX63: 4783193 | AY63: 4783193 | AZ63: 4783193 | BA63: 4783193 | BB63: 4783193 | BD63: 4783193 | BK63: 0
A64: Depreciación | B64: 0 | D64: 0 | E64: 0 | F64: 0 | G64: 0 | H64: 0 | I64: 0 | J64: 0 | K64: 0 | L64: 0 | M64: 0 | N64: 0 | O64: 0 | Q64: 0 | AE64: 0 | AF64: 0 | AG64: 0 | AH64: 0 | AI64: 0 | AJ64: 0 | AK64: 0 | AL64: 0 | AM64: 0 | AN64: 0 | AO64: 0 | AQ64: 0 | BD64: 0 | BK64: 0
A65: Equipo de Comp. Y Comunicación | B65: =SUM(B66:B67) -> 8400000 | D65: =SUM(D66:D67) -> 8400000 | E65: =SUM(E66:E67) -> 8400000 | F65: =SUM(F66:F67) -> 8400000 | G65: =SUM(G66:G67) -> 8400000 | H65: =SUM(H66:H67) -> 8400000 | I65: =SUM(I66:I67) -> 8400000 | J65: =SUM(J66:J67) -> 8400000 | K65: =SUM(K66:K67) -> 8400000 | ... O65: =SUM(O66:O67) -> 8400000 | Q65: =SUM(Q66:Q67) -> 8400000 | R65: =SUM(R66:R67) -> 8400000 | S65: =SUM(S66:S67) -> 8400000 | T65: =SUM(T66:T67) -> 8400000 | U65: =SUM(U66:U67) -> 8400000 | V65: =SUM(V66:V67) -> 8400000 | W65: =SUM(W66:W67) -> 8400000 | X65: =SUM(X66:X67) -> 8400000 | ... AB65: =SUM(AB66:AB67) -> 8400000 | AD65: =SUM(AD66:AD67) -> 8400000 | AE65: =SUM(AE66:AE67) -> 8400000 | AF65: =SUM(AF66:AF67) -> 8400000 | AG65: =SUM(AG66:AG67) -> 8400000 | AH65: =SUM(AH66:AH67) -> 8400000 | AI65: =SUM(AI66:AI67) -> 8400000 | AJ65: =SUM(AJ66:AJ67) -> 8400000 | AK65: =SUM(AK66:AK67) -> 8400000 | ... AO65: =SUM(AO66:AO67) -> 8400000 | AQ65: =SUM(AQ66:AQ67) -> 8400000 | AR65: =SUM(AR66:AR67) -> 4857539 | AS65: =SUM(AS66:AS67) -> 5070592 | AT65: =SUM(AT66:AT67) -> 5283645 | AU65: =SUM(AU66:AU67) -> 5496698 | AV65: =SUM(AV66:AV67) -> 2109751 | AW65: =SUM(AW66:AW67) -> 2322804 | AX65: =SUM(AX66:AX67) -> 2535857 | ... BB65: =SUM(BB66:BB67) -> 3388069 | BD65: =SUM(BD66:BD67) -> 4800000 | BE65: =SUM(BE66:BE67) -> 0 | BF65: =SUM(BF66:BF67) -> 0 | BG65: =SUM(BG66:BG67) -> 0 | BH65: =SUM(BH66:BH67) -> 0 | BI65: =SUM(BI66:BI67) -> 0 | BK65: =SUM(BK66:BK67) -> 0
A66: Equipo de Procesamiento de datos | B66: 8400000 | D66: 8400000 | E66: 8400000 | F66: 8400000 | G66: 8400000 | H66: 8400000 | I66: 8400000 | J66: 8400000 | K66: 8400000 | L66: 8400000 | M66: 8400000 | N66: 8400000 | O66: 8400000 | Q66: 8400000 | R66: 8400000 | S66: 8400000 | T66: 8400000 | U66: 8400000 | V66: 8400000 | W66: 8400000 | X66: 8400000 | Y66: 8400000 | Z66: 8400000 | AA66: 8400000 | AB66: 8400000 | AD66: =8400000+4505488-4505488 -> 8400000 | AE66: 8400000 | AF66: 8400000 | AG66: 8400000 | AH66: 8400000 | AI66: 8400000 | AJ66: 8400000 | AK66: 8400000 | AL66: 8400000 | AM66: 8400000 | AN66: 8400000 | AO66: 8400000 | AQ66: 8400000 | AR66: 8400000 | AS66: 8400000 | AT66: 8400000 | AU66: 8400000 | AV66: 4800000 | AW66: 4800000 | AX66: 4800000 | AY66: 4800000 | AZ66: 4800000 | BA66: 4800000 | BB66: 4800000 | BD66: 4800000 | BK66: 0
A67: Depreciación | B67: 0 | D67: 0 | E67: 0 | F67: 0 | G67: 0 | H67: 0 | I67: 0 | J67: 0 | K67: 0 | L67: 0 | M67: 0 | N67: 0 | O67: 0 | Q67: 0 | AD67: 0 | AE67: 0 | AF67: 0 | AG67: 0 | AH67: 0 | AI67: 0 | AJ67: 0 | AK67: 0 | AL67: 0 | AM67: 0 | AN67: 0 | AO67: 0 | AQ67: 0 | AR67: -3542461 | AS67: -3329408 | AT67: -3116355 | AU67: -2903302 | AV67: -2690249 | AW67: -2477196 | AX67: -2264143 | AY67: -2051090 | AZ67: -1838037 | BA67: -1624984 | BB67: -1411931 | BD67: 0 | BK67: 0
A69: Activos Diferidos | B69: =+B70 -> 36327625 | D69: =+D70 -> 36327625 | E69: =+E70 -> 36327625 | F69: =+F70 -> 36327625 | G69: =+G70 -> 36327625 | H69: =+H70 -> 36327625 | I69: =+I70 -> 36327625 | J69: =+J70 -> 36327625 | K69: =+K70 -> 36327625 | ... O69: =+O70 -> 36327625 | Q69: =+Q70 -> 36327625 | R69: =+R70 -> 31808371 | S69: =+S70 -> 29238600 | T69: =+T70 -> 26656843 | U69: =+U70 -> 24207995 | V69: =+V70 -> 21747921 | W69: =+W70 -> 19339622 | X69: =+X70 -> 14232999 | ... AB69: =+AB70 -> 2715692 | AD69: =+AD68 -> 0 | AE69: =+AE68 -> 0 | AF69: =+AF68 -> 0 | AG69: =+AG68 -> 0 | AH69: =+AH68 -> 0 | AI69: =+AI68 -> 0 | AJ69: =+AJ68 -> 0 | AK69: =+AK68 -> 0 | ... AO69: =+AO68 -> 0 | AQ69: =+AQ70 -> 24505488 | BD69: =SUM(BD68:BO68) -> 0
A70: Otros Activos | B70: =+D70 -> 36327625 | D70: =+E70 -> 36327625 | E70: =+F70 -> 36327625 | F70: =+G70 -> 36327625 | G70: =+H70 -> 36327625 | H70: =+I70 -> 36327625 | I70: =+J70 -> 36327625 | J70: =+K70 -> 36327625 | K70: =+L70 -> 36327625 | ... N70: =+O70 -> 36327625 | O70: =+Q70 -> 36327625 | Q70: 36327625 | R70: 31808371 | S70: 29238600 | T70: 26656843 | U70: 24207995 | V70: 21747921 | W70: 19339622 | X70: 14232999 | Y70: 13215750 | Z70: 7067100 | AA70: 5376575 | AB70: 2715692 | AD70: 0 | AE70: 24505488 | AF70: 24505488 | AG70: 24505488 | AH70: 24505488 | AI70: 24505488 | AJ70: 24505488 | AK70: 24505488 | AL70: 24505488 | AM70: 24505488 | AN70: 24505488 | AO70: 24505488 | AQ70: 24505488 | BD70: 0 | BK70: 0
A75: TOTAL ACTIVOS | B75: =+B10+B14+B61+B69 -> 1.4061731e+08 | D75: =+D10+D14+D61+D69 -> 1.458645e+08 | E75: =+E10+E14+E61+E69 -> 1.4665313e+08 | F75: =+F10+F14+F61+F69 -> 1.2134925e+08 | G75: =+G10+G14+G61+G69 -> 1.2162471e+08 | H75: =+H10+H14+H61+H69 -> 1.0368991e+08 | I75: =+I10+I14+I61+I69 -> 1.0129416e+08 | J75: =+J10+J14+J61+J69 -> 93443117 | K75: =+K10+K14+K61+K69 -> 1.0192369e+08 | ... O75: =+O10+O14+O61+O69 -> 69057330 | Q75: =+Q10+Q14+Q61+Q69 -> 74355715 | R75: =+R10+R14+R61+R69 -> 68643331 | S75: =+S10+S14+S61+S69 -> 66495137 | T75: =+T10+T14+T61+T69 -> 71277754 | U75: =+U10+U14+U61+U69 -> 65849265 | V75: =+V10+V14+V61+V69 -> 62586229 | W75: =+W10+W14+W61+W69 -> 57761111 | X75: =+X10+X14+X61+X69 -> 63488667 | ... AB75: =+AB10+AB14+AB61+AB69 -> 48427369 | AD75: =+AD10+AD15+AD14+AD61+AD69 -> 55811771 | AE75: =+AE10+AE15+AE14+AE61+#REF! -> #REF! | AF75: =+AF10+AF15+AF14+AF61+#REF! -> #REF! | AG75: =+AG10+AG15+AG14+AG61+#REF! -> #REF! | AH75: =+AH10+AH15+AH14+AH61+#REF! -> #REF! | AI75: =+AI10+AI15+AI14+AI61+#REF! -> #REF! | AJ75: =+AJ10+AJ15+AJ14+AJ61+#REF! -> #REF! | AK75: =+AK10+AK15+AK14+AK61+#REF! -> #REF! | AL75: =+AL10+AL15+AL14+AL61+#REF! -> #REF! | ... AO75: =+AO10+AO15+AO14+AO61+#REF! -> #REF! | AQ75: =+AQ10+AQ15+AQ14+AQ61+AQ69 -> 44554429 | AR75: =+AR61+AR14+AR10 -> 10528394 | AS75: =+AS61+AS14+AS10 -> 49996276 | AT75: =+AT61+AT14+AT10 -> 64151629 | AU75: =+AU61+AU14+AU10 -> 41459709 | AV75: =+AV61+AV14+AV10 -> 24099033 | AW75: =+AW61+AW14+AW10 -> 24312086 | AX75: =+AX61+AX14+AX10 -> 24525139 | AY75: =+AY61+AY14+AY10 -> 25338364 | ... BB75: =+BB61+BB14+BB10 -> 19857850 | BD75: =+BD10+BD15+BD14+BD61+BD69 -> 25306581 | BE75: =+BE61+BE14+BE10 -> 0 | BF75: =+BF61+BF14+BF10 -> 0 | BG75: =+BG61+BG14+BG10 -> 0 | BH75: =+BH61+BH14+BH10 -> 0 | BI75: =+BI61+BI14+BI10 -> 0 | BK75: =+BK61+BK14+BK10+#REF! -> #REF!
A77: PASIVO
A79: Costos y Gastos por pagar | B79: =SUM(B80:B93) -> 4558817 | D79: =SUM(D80:D93) -> 10155997 | E79: =SUM(E80:E93) -> 9427003 | F79: =SUM(F80:F93) -> 13568568 | G79: =SUM(G80:G93) -> 13337057 | H79: =SUM(H80:H93) -> 16305931 | I79: =SUM(I80:I93) -> 19749101 | J79: =SUM(J80:J93) -> 17140322 | K79: =SUM(K80:K93) -> 20848428 | ... O79: =SUM(O80:O93) -> 7877156 | Q79: =SUM(Q80:Q93) -> 6941830 | R79: =SUM(R80:R93) -> 2593000 | S79: =SUM(S80:S93) -> 3691704 | T79: =SUM(T80:T93) -> 4055497 | U79: =SUM(U80:U93) -> 2763553 | V79: =SUM(V80:V93) -> 2996811 | W79: =SUM(W80:W93) -> 2161391 | X79: =SUM(X80:X93) -> 3213352 | ... AB79: =SUM(AB80:AB93) -> 1329009 | AD79: =SUM(AD80:AD93) -> 40000 | AE79: =SUM(AE80:AE93) -> 29910000 | AF79: =SUM(AF80:AF93) -> 33910000 | AG79: =SUM(AG80:AG93) -> 29910000 | AH79: =SUM(AH80:AH93) -> 34210385 | AI79: =SUM(AI80:AI93) -> 36724324 | AJ79: =SUM(AJ80:AJ93) -> 75507001 | AK79: =SUM(AK80:AK93) -> 71511775 | ... AO79: =SUM(AO80:AO93) -> 35845172 | AQ79: =SUM(AQ80:AQ93) -> 32460000 | AR79: =SUM(AR80:AR93) -> 1694936.5 | AS79: =SUM(AS80:AS93) -> 42400371 | AT79: =SUM(AT80:AT93) -> 43938473 | AU79: =SUM(AU80:AU93) -> 27215890 | AV79: =SUM(AV80:AV93) -> 18825168 | AW79: =SUM(AW80:AW93) -> 18846889 | AX79: =SUM(AX80:AX93) -> 18760643 | ... BB79: =SUM(BB80:BB93) -> 17136601 | BD79: =SUM(BD80:BD93) -> 20000000 | BK79: =SUM(BK80:BK93) -> 0
A80: Edgar Orlando Lezmes | B80: 0 | D80: 0 | E80: =-4008620-1679650-3920000 -> -9608270 | F80: =-4008620-1679650 -> -5688270 | G80: -4008620 | H80: -4008620 | I80: =2150000+762000+3000000-6000000 -> -88000 | J80: =2150000+762000 -> 2912000 | K80: =762000+15050000-5000000-2700000 -> 8112000 | L80: =762000+15050000-5000000 -> 10812000 | M80: =762000+15050000 -> 15812000 | N80: 762000 | O80: 0 | Q80: 0 | R80: 0 | S80: 0 | T80: 0 | U80: 0 | V80: 0 | W80: 0 | X80: 0 | Y80: 0 | Z80: 0 | AA80: 0 | AB80: 0 | AD80: =23130000-12000000-11130000 -> 0 | AE80: 15610000 | AF80: 19610000 | AG80: 15610000 | AH80: 14110000 | AI80: 14110000 | AJ80: 53810000 | AK80: 51310000 | AL80: 49310000 | AM80: 49310000 | AN80: 21160000 | AO80: 18160000 | AQ80: 18160000 | AR80: 1694936.5 | AS80: 42400371 | AT80: 43938473 | AU80: 27215890 | AV80: 18825168 | AW80: 18846889 | AX80: 18760643 | AY80: 19032761 | AZ80: 15672729 | BA80: 16009814 | BB80: 17136601 | BD80: 20000000 | BK80: 0
A81: Fenalco Sur de Santander | B81: -6500000 | D81: 0 | E81: 0 | F81: 0 | G81: 0 | H81: 0 | I81: 0 | J81: 0 | K81: 0 | L81: 0 | M81: 0 | N81: 50000 | O81: 44000 | Q81: 44000 | R81: 44000 | S81: 44000 | T81: 44000 | U81: 44000 | V81: =+W81 -> 44000 | W81: 44000 | X81: 44000 | Y81: 44000 | Z81: 44000 | AA81: 44000 | AB81: 40000 | AD81: 40000 | AQ81: 0
A82: Centro Comercial El Puente | V82: 0 | W82: 0 | X82: 0 | Y82: 0 | Z82: 0 | AA82: 0 | AB82: 0 | AD82: 0 | AE82: 0 | AF82: , | AG82: 0 | AH82: 5111908 | AI82: 7491908 | AJ82: 6691908 | AK82: 5541908 | AL82: 3161908 | AM82: 5507486 | AN82: 5367578 | AO82: 2725054 | AQ82: 0 | BD82: 0 | BK82: 0
A83: Inversiones servicios y asesoria lTDA | B83: 2065997 | D83: 2065997 | E83: 2997997 | F83: 2896997 | G83: =+H83+931999-931999 -> 1863998 | H83: =+I83+931999-931999 -> 1863998 | I83: =+J83+931999-931999 -> 1863998 | J83: =931999+931999 -> 1863998 | K83: 931999 | L83: 1863998 | M83: 1863998 | N83: 1851998 | O83: 919999 | Q83: =+R83 -> 919999 | R83: =+S83 -> 919999 | S83: 919999 | T83: 890000 | U83: 20000 | W83: 0 | X83: 870000 | AD83: 0 | AQ83: 0
A84: IT Comunicaciones | B84: 0 | D84: 0 | E84: 0 | F84: 0 | G84: 0 | H84: 0 | I84: 0 | J84: 0 | K84: 0 | L84: 0 | M84: 0 | N84: 452200 | O84: 226100 | Q84: 0 | R84: 0 | S84: 404600 | T84: =606900 -> 606900 | U84: 404600 | V84: =+W84+202300 -> 606900 | W84: 404600 | X84: =+Y84+202300 -> 606900 | Y84: =+Z84 -> 404600 | Z84: =+AA84 -> 404600 | AA84: =+AB84+202300 -> 404600 | AB84: 202300 | AD84: 0 | AE84: 0 | AF84: 0 | AG84: 0 | AH84: 0 | AI84: 202300 | AJ84: 202300 | AK84: 0 | AL84: 0 | AM84: 202300 | AN84: 0 | AO84: 0 | AQ84: 0 | BD84: 0 | BK84: 0
A85: Electrificadora de Santander | B85: 0 | D85: 0 | E85: 0 | F85: 0 | G85: 0 | H85: 0 | I85: 0 | J85: 0 | K85: 0 | L85: 0 | M85: 0 | N85: 0 | O85: 0 | Q85: 0 | R85: 0 | T85: 35000
A86: Centro Medico de excelencia en Salud Ocupacional | B86: 0 | D86: 90000 | E86: 0 | F86: 0 | G86: 0 | H86: 60000 | I86: 60000 | J86: 60000
A87: Milton Ruiz Porras | B87: 8000000 | D87: 8000000
A88: Posada don Agustin S.A.S | B88: 0 | D88: 0 | E88: 4620000 | F88: 4620000 | G88: 4620000 | H88: 4620000 | I88: 4620000 | J88: 4620000 | K88: 4620000 | L88: 4620000 | M88: 4620000 | N88: 4620000 | O88: 4620000 | Q88: 4620000 | R88: 0 | AD88: 0 | AQ88: 0
A89: Luis Fernanado Vargas Miranda | B89: 0 | D89: 0 | E89: 0
A90: Suramericana | B90: 0 | D90: 0 | E90: 0 | F90: 189673 | G90: 0 | H90: 0 | I90: 0 | J90: 72128 | K90: 0 | L90: 0 | M90: 654694 | N90: 654694 | O90: 654694 | Q90: 0 | AD90: 0 | AQ90: 0
A91: Proveedor de Telecomunicaciones S.A.S | B91: 227999 | D91: 0 | E91: 0 | F91: 214198 | G91: 0 | H91: 214198 | I91: 0 | J91: 209999 | K91: 209999 | L91: 419998 | M91: 0 | N91: 0 | O91: 0 | Q91: 0 | AD91: 0 | AQ91: 0
A92: Dyalogo SAS | B92: 764821 | D92: 0 | E92: =2307169-10785 -> 2296384 | F92: =2225863-10785 -> 2215078 | G92: =1751572-10785 -> 1740787 | H92: 2294355 | I92: 2031103 | J92: =1212430+427767 -> 1640197 | K92: 1212430 | L92: 1619118 | M92: 2276330 | N92: 1869642 | O92: 1412363 | Q92: 1357831 | R92: 1629001 | S92: 2323105 | T92: 2479597 | U92: 2294953 | V92: =+W92+633120 -> 2345911 | W92: =913346+799445 -> 1712791 | X92: =+Y92+913346 -> 1692452 | Y92: 779106 | Z92: =848654+AA92 -> 1579323 | AA92: 730669 | AB92: 1086709 | AD92: 0 | AE92: 0 | AF92: 0 | AG92: 0 | AH92: 688477.48 | AI92: 620116.11 | AJ92: 502793.35 | AK92: 359866.79 | AL92: 262473 | AM92: 562361.73 | AN92: 568778.73 | AO92: 660118 | AQ92: 0 | BD92: 0 | BK92: 0
A93: Jimmy Archila Silva | B93: 0 | D93: 0 | E93: =11262000-2141108 -> 9120892 | F93: =11262000-2141108 -> 9120892 | G93: =11262000-2141108 -> 9120892 | H93: 11262000 | I93: 11262000 | J93: =762000+5000000 -> 5762000 | K93: =762000+5000000 -> 5762000 | L93: =762000+5000000 -> 5762000 | M93: =762000+5000000 -> 5762000 | N93: 762000 | O93: 0 | Q93: 0 | R93: 0 | T93: 0 | U93: 0 | V93: 0 | W93: 0 | X93: 0 | Y93: 0 | Z93: 0 | AA93: 0 | AB93: 0 | AD93: 0 | AE93: 14300000 | AF93: 14300000 | AG93: 14300000 | AH93: 14300000 | AI93: 14300000 | AJ93: 14300000 | AK93: 14300000 | AL93: 14300000 | AM93: 14300000 | AN93: 14300000 | AO93: 14300000 | AQ93: 14300000 | BD93: 0 | BE93: 0 | BF93: 0 | BG93: 0 | BH93: 0 | BK93: 0
A95: Cuentas Corrientes Comerciales | B95: =+B96 -> 0 | D95: =+D96 -> 0 | E95: =+E96 -> 0 | F95: =+F96 -> 0 | G95: =+G96 -> 0 | H95: =+H96 -> 0 | I95: =+I96 -> 0 | J95: =+J96 -> 0 | K95: =+K96 -> 0 | ... O95: =+O96 -> 0 | Q95: =+Q96 -> 0 | R95: =+R96 -> 0 | S95: =+S96 -> 0 | T95: =+T96 -> 0 | U95: =+U96 -> 0 | V95: =+V96 -> 0 | W95: =+W96 -> 0 | X95: =+X96 -> 0 | ... AB95: =+AB96 -> 0 | AD95: =+AD96 -> 0 | AE95: =+AE96 -> 0 | AF95: =+AF96 -> 0 | AG95: =+AG96 -> 0 | AH95: =+AH96 -> 0 | AI95: =+AI96 -> 0 | AJ95: =+AJ96 -> 0 | AK95: =+AK96 -> 0 | ... AO95: =+AO96 -> 0 | AQ95: =+AQ96 -> 0 | AR95: =+AR96 -> 2380000 | AS95: =+AS96 -> 2380000 | AT95: =+AT96 -> 2380000
A96: Centro Comercial El Puente | B96: 0 | D96: 0 | E96: 0 | F96: 0 | G96: 0 | H96: 0 | I96: 0 | J96: 0 | K96: 0 | L96: 0 | M96: 0 | N96: 0 | O96: 0 | Q96: 0 | R96: 0 | S96: 0 | T96: 0 | U96: 0 | V96: 0 | W96: 0 | X96: 0 | Y96: 0 | Z96: 0 | AA96: 0 | AB96: 0 | AD96: 0 | AE96: 0 | AF96: 0 | AG96: 0 | AH96: 0 | AI96: 0 | AJ96: 0 | AK96: 0 | AL96: 0 | AM96: 0 | AN96: 0 | AO96: 0 | AQ96: 0 | AR96: 2380000 | AS96: 2380000 | AT96: 2380000 | BD96: 0 | BK96: 0
A98: No Finaniceros | B98: =+B99+B103 -> 4356900 | D98: =+D99+D103 -> 3776000 | E98: =+E99+E103 -> 3856900 | F98: =+F99+F103 -> 3856900 | G98: =+G99+G103 -> 3808700 | H98: =+H99+H103 -> 3838500 | I98: =+I99+I103 -> 3856900 | J98: =+J99+J103 -> 3769500 | K98: =+K99+K103 -> 3669800 | ... O98: =+O99+O103 -> 698600 | Q98: =+Q99+Q103 -> 637600 | R98: =+R99+R103 -> 637600 | S98: =+S99+S103 -> 1636800 | T98: =+T99+T103 -> 1912800 | U98: =+U99+U103 -> 1912800 | V98: =+V99+V103 -> 1923700 | W98: =+W99+W103 -> 2242500 | X98: =+X99+X103 -> 3188000 | ... AB98: =+AB99+AB103 -> 956400 | AD98: =+AD99+AD103 -> 897900 | AE98: =+AE99+AE103 -> 897900 | AF98: =+AF99+AF103 -> 1719000 | AG98: =+AG99+AG103 -> 809400 | AH98: =+AH99+AH103 -> 875700 | AI98: =+AI99+AI103 -> 569000 | AJ98: =+AJ99+AJ103 -> 720794 | AK98: =+AK99+AK103 -> 569000 | ... AO98: =+AO99+AO103 -> 569000 | AQ98: =+AQ99+AQ103 -> 780400 | AR98: =+AR99+AR103 -> 1492900 | AS98: =+AS99+AS103 -> 1098944 | AT98: =+AT99+AT103 -> 391956 | AU98: =+AU99+AU103 -> 363278 | AV98: =+AV99+AV103 -> 513452 | AW98: =+AW99+AW103 -> 374078 | AX98: =+AX99+AX103 -> 374078 | ... BB98: =+BB99+BB103 -> 116522 | BD98: =+BD99+BD103 -> 446000 | BE98: =+BE99+BE103 -> 0 | BF98: =+BF99+BF103 -> 0 | BG98: =+BG99+BG103 -> 0 | BH98: =+BH99+BH103 -> 0 | BI98: =+BI99+BI103 -> 0 | BK98: =+BK99+BK103 -> 0
A99: Retenciones y Aportes de Nomina | B99: =SUM(B100:B102) -> 1515100 | D99: =SUM(D100:D102) -> 1313600 | E99: =SUM(E100:E102) -> 1341300 | F99: =SUM(F100:F102) -> 1341300 | G99: =SUM(G100:G102) -> 1293100 | H99: =SUM(H100:H102) -> 1322900 | I99: =SUM(I100:I102) -> 1341300 | J99: =SUM(J100:J102) -> 1310900 | K99: =SUM(K100:K102) -> 1276300 | ... O99: =SUM(O100:O102) -> 243000 | Q99: =SUM(Q100:Q102) -> 221600 | R99: =SUM(R100:R102) -> 221600 | S99: =SUM(S100:S102) -> 569000 | T99: =SUM(T100:T102) -> 664800 | U99: =SUM(U100:U102) -> 664800 | V99: =SUM(V100:V102) -> 668700 | W99: =SUM(W100:W102) -> 779500 | X99: =SUM(X100:X102) -> 1108000 | ... AB99: =SUM(AB100:AB102) -> 332400 | AD99: =SUM(AD100:AD102) -> 341100 | AE99: =SUM(AE100:AE102) -> 341100 | AF99: =SUM(AF100:AF102) -> 641500 | AG99: =SUM(AG100:AG102) -> 295900 | AH99: =SUM(AH100:AH102) -> 318900 | AI99: =SUM(AI100:AI102) -> 197800 | AJ99: =SUM(AJ100:AJ102) -> 250647 | AK99: =SUM(AK100:AK102) -> 197800 | ... AO99: =SUM(AO100:AO102) -> 197800 | AQ99: =SUM(AQ100:AQ102) -> 273600 | AR99: =SUM(AR100:AR102) -> 531700 | AS99: =SUM(AS100:AS102) -> 416969 | AT99: =SUM(AT100:AT102) -> 113931 | AU99: =SUM(AU100:AU102) -> 113931 | AV99: =SUM(AV100:AV102) -> 264105 | AW99: =SUM(AW100:AW102) -> 119331 | AX99: =SUM(AX100:AX102) -> 119331 | ... BB99: =SUM(BB100:BB102) -> 51269 | BD99: =SUM(BD100:BD102) -> 155200 | BE99: =SUM(BE100:BE102) -> 0 | BF99: =SUM(BF100:BF102) -> 0 | BG99: =SUM(BG100:BG102) -> 0 | BH99: =SUM(BH100:BH102) -> 0 | BI99: =SUM(BI100:BI102) -> 0 | BK99: =SUM(BK100:BK102) -> 0
A100: Entidades promotoras de salud | B100: 710900 | D100: 616400 | E100: 629400 | F100: 629400 | G100: 629500 | H100: 629400 | I100: 629400 | J100: 615100 | K100: 598900 | L100: 629400 | M100: 562400 | N100: 492100 | O100: 114000 | Q100: =143000-39000 -> 104000 | R100: =143000-39000 -> 104000 | S100: =306000-39000 -> 267000 | T100: =351000-39000 -> 312000 | U100: =351000-39000 -> 312000 | V100: =352800-39000 -> 313800 | W100: =404800-39000 -> 365800 | X100: =559000-39000 -> 520000 | Y100: =351000-39000 -> 312000 | Z100: 416000 | AA100: 364000 | AB100: 156000 | AD100: 139200 | AE100: 139200 | AF100: 269400 | AG100: 128400 | AH100: 139200 | AI100: 92800 | AJ100: 117547 | AK100: 92800 | AL100: 92800 | AM100: 224267 | AN100: 92800 | AO100: 92800 | AQ100: 126800 | AR100: 240400 | AS100: 208469 | AT100: 31531 | AU100: 31531 | AV100: 181705 | AW100: 36931 | AX100: 36931 | AY100: 36931 | AZ100: 36931 | BA100: 28331 | BB100: 43069 | BD100: 72800 | BK100: 0
A101: Administradoras de Riegos | B101: 93300 | D101: 80800 | E101: 82500 | F101: 82500 | G101: 76900 | H101: 80400 | I101: 82500 | J101: 80700 | K101: 78500 | L101: 82500 | M101: 74000 | N101: 64800 | O101: 15000 | Q101: 13600 | R101: 13600 | S101: 35000 | T101: 40800 | U101: 40800 | V101: 41100 | W101: 47900 | X101: 68000 | Y101: 40800 | Z101: 54400 | AA101: 47600 | AB101: 20400 | AD101: 62700 | AE101: 62700 | AF101: 102700 | AG101: 39100 | AH101: 40500 | AI101: 12200 | AJ101: 15500 | AK101: 12200 | AL101: 12200 | AM101: 92500 | AN101: 12200 | AO101: 12200 | AQ101: 20000 | AR101: 51000 | AS101: 41300 | AT101: 9600 | AU101: 9600 | AV101: 9600 | AW101: 9600 | AX101: 9600 | AY101: 9600 | AZ101: 9600 | BA101: 8300 | BB101: 1000 | BD101: 9600 | BK101: 0
A102: Aportes Cajas de Compensación | B102: 710900 | D102: 616400 | E102: 629400 | F102: 629400 | G102: 586700 | H102: 613100 | I102: 629400 | J102: 615100 | K102: 598900 | L102: 629400 | M102: 562400 | N102: 492100 | O102: 114000 | Q102: 104000 | R102: 104000 | S102: 267000 | T102: 312000 | U102: 312000 | V102: 313800 | W102: 365800 | X102: 520000 | Y102: 312000 | Z102: 416000 | AA102: 364000 | AB102: 156000 | AD102: 139200 | AE102: 139200 | AF102: 269400 | AG102: 128400 | AH102: 139200 | AI102: 92800 | AJ102: 117600 | AK102: 92800 | AL102: 92800 | AM102: 224400 | AN102: 92800 | AO102: 92800 | AQ102: 126800 | AR102: 240300 | AS102: 167200 | AT102: 72800 | AU102: 72800 | AV102: 72800 | AW102: 72800 | AX102: 72800 | AY102: 72800 | AZ102: 72800 | BA102: 64300 | BB102: 7200 | BD102: 72800 | BK102: 0
A103: Acreedores Varios | B103: =SUM(B104:B105) -> 2841800 | D103: =SUM(D104:D105) -> 2462400 | E103: =SUM(E104:E105) -> 2515600 | F103: =SUM(F104:F105) -> 2515600 | G103: =SUM(G104:G105) -> 2515600 | H103: =SUM(H104:H105) -> 2515600 | I103: =SUM(I104:I105) -> 2515600 | J103: =SUM(J104:J105) -> 2458600 | K103: =SUM(K104:K105) -> 2393500 | ... O103: =SUM(O104:O105) -> 455600 | Q103: =SUM(Q104:Q105) -> 416000 | R103: =SUM(R104:R105) -> 416000 | S103: =SUM(S104:S105) -> 1067800 | T103: =SUM(T104:T105) -> 1248000 | U103: =SUM(U104:U105) -> 1248000 | V103: =SUM(V104:V105) -> 1255000 | W103: =SUM(W104:W105) -> 1463000 | X103: =SUM(X104:X105) -> 2080000 | ... AB103: =SUM(AB104:AB105) -> 624000 | AD103: =SUM(AD104:AD105) -> 556800 | AE103: =SUM(AE104:AE105) -> 556800 | AF103: =SUM(AF104:AF105) -> 1077500 | AG103: =SUM(AG104:AG105) -> 513500 | AH103: =SUM(AH104:AH105) -> 556800 | AI103: =SUM(AI104:AI105) -> 371200 | AJ103: =SUM(AJ104:AJ105) -> 470147 | AK103: =SUM(AK104:AK105) -> 371200 | ... AO103: =SUM(AO104:AO105) -> 371200 | AQ103: =SUM(AQ104:AQ105) -> 506800 | AR103: =SUM(AR104:AR105) -> 961200 | AS103: =SUM(AS104:AS105) -> 681975 | AT103: =SUM(AT104:AT105) -> 278025 | AU103: =SUM(AU104:AU105) -> 249347 | AV103: =SUM(AV104:AV105) -> 249347 | AW103: =SUM(AW104:AW105) -> 254747 | AX103: =SUM(AX104:AX105) -> 254747 | ... BB103: =SUM(BB104:BB105) -> 65253 | BD103: =SUM(BD104:BD105) -> 290800 | BE103: =SUM(BE104:BE105) -> 0 | BF103: =SUM(BF104:BF105) -> 0 | BG103: =SUM(BG104:BG105) -> 0 | BH103: =SUM(BH104:BH105) -> 0 | BI103: =SUM(BI104:BI105) -> 0 | BK103: =SUM(BK104:BK105) -> 0
A104: Fondos de Cesantías y Pensiones | B104: 2841800 | D104: 2462400 | E104: 2515600 | F104: 2515600 | G104: 2515600 | H104: 2515600 | I104: 2515600 | J104: 2458600 | K104: =2312500+81000 -> 2393500 | L104: 2515600 | M104: 2247600 | N104: 1966600 | O104: 455600 | Q104: =455000-39000 -> 416000 | R104: =455000-39000 -> 416000 | S104: =1106800-39000 -> 1067800 | T104: =1287000-39000 -> 1248000 | U104: =1287000-39000 -> 1248000 | V104: =1294000-39000 -> 1255000 | W104: =1502000-39000 -> 1463000 | X104: =2119000-39000 -> 2080000 | Y104: =1287000-39000 -> 1248000 | Z104: 1664000 | AA104: 1456000 | AB104: 624000 | AD104: 556800 | AE104: 556800 | AF104: 1077500 | AG104: 513500 | AH104: 556800 | AI104: 371200 | AJ104: 470147 | AK104: 371200 | AL104: 371200 | AM104: 897387 | AN104: 371200 | AO104: 371200 | AQ104: 506800 | AR104: 961200 | AS104: 681975 | AT104: 278025 | AU104: 249347 | AV104: 249347 | AW104: 254747 | AX104: 254747 | AY104: 254747 | AZ104: 254747 | BA104: 221047 | BB104: 65253 | BD104: 290800 | BK104: 0
A105: Fondo de solidaridad
A107: Fiscales | B107: =+B108+B112 -> 38753449 | D107: =+D108+D112 -> 40687062 | E107: =+E108+E112 -> 36865926 | F107: =+F108+F112 -> 32224889 | G107: =+G108+G112 -> 27343774 | H107: =+H108+H112 -> 20796788 | I107: =+I108+I112 -> 21537467 | J107: =+J108+J112 -> 23015077 | K107: =+K108+K112 -> 24848147 | ... O107: =+O108+O112 -> 30697551 | Q107: =+Q108+Q112 -> 32974361 | R107: =+R108+R112 -> 32800049 | S107: =+S108+S112 -> 30758162 | T107: =+T108+T112 -> 31769128 | U107: =+U108+U112 -> 31003445 | V107: =+V108+V112 -> 29069622 | W107: =+W108+W112 -> 26373928 | X107: =+X108+X112 -> 27514427 | ... AB107: =+AB108+AB112 -> 24251628 | AD107: =+AD108+AD112 -> 19565238 | AE107: =+AE108+AE112 -> 14531905 | AF107: =+AF108+AF112 -> 13621990 | AG107: =+AG108+AG112 -> 11593683 | AH107: =+AH108+AH112 -> 10977523 | AI107: =+AI108+AI112 -> 10012082 | AJ107: =+AJ108+AJ112 -> 9171171.7 | AK107: =+AK108+AK112 -> 8670615.1 | ... AO107: =+AO108+AO112 -> 268308 | AQ107: =+AQ108+AQ112 -> 4036561 | AR107: =+AR108+AR112 -> 3427601 | AS107: =+AS108+AS112 -> 3427601 | AT107: =+AT108+AT112 -> 2823278.4 | AU107: =+AU108+AU112 -> 1827340.1 | AV107: =+AV108+AV112 -> -25516.32 | AW107: =+AW108+AW112 -> 27081.76 | AX107: =+AX108+AX112 -> 93272.21 | ... BB107: =+BB108+BB112 -> -648977.02 | BD107: =+BD108+BD112 -> 294499.83 | BE107: =+BE108+BE112 -> 0 | BF107: =+BF108+BF112 -> 0 | BG107: =+BG108+BG112 -> 0 | BH107: =+BH108+BH112 -> 0 | BI107: =+BI108+BI112 -> 0 | BK107: =+BK108+BK112 -> 0
A108: Retencion | B108: =SUM(B109:B111) -> 19634528 | D108: =SUM(D109:D111) -> 19132106 | E108: =SUM(E109:E111) -> 15367460 | F108: =SUM(F109:F111) -> 10822576 | G108: =SUM(G109:G111) -> 5485311.1 | H108: =SUM(H109:H111) -> -679432.83 | I108: =SUM(I109:I111) -> -1847525.3 | J108: =SUM(J109:J111) -> -2606328.7 | K108: =SUM(K109:K111) -> -3107536.2 | ... O108: =SUM(O109:O111) -> 2310061.1 | Q108: =SUM(Q109:Q111) -> 4552159.9 | R108: =SUM(R109:R111) -> 3718708.8 | S108: =SUM(S109:S111) -> 2885310.6 | T108: =SUM(T109:T111) -> 2019237.9 | U108: =SUM(U109:U111) -> 2349896.9 | V108: =SUM(V109:V111) -> 1706713.4 | W108: =SUM(W109:W111) -> 604166.67 | X108: =SUM(X109:X111) -> 2054783.9 | ... AB108: =SUM(AB109:AB111) -> 4652596.4 | AD108: =SUM(AD109:AD111) -> 4578237.5 | AE108: =SUM(AE109:AE111) -> 1154600 | AF108: =SUM(AF109:AF111) -> 1104592 | AG108: =SUM(AG109:AG111) -> 980389.75 | AH108: =SUM(AH109:AH111) -> 944639.75 | AI108: =SUM(AI109:AI111) -> 863463 | AJ108: =SUM(AJ109:AJ111) -> 769704.67 | AK108: =SUM(AK109:AK111) -> 1138101.1 | ... AO108: =SUM(AO109:AO111) -> 169033 | AQ108: =SUM(AQ109:AQ111) -> 254793 | AR108: =SUM(AR109:AR111) -> 196482 | AS108: =SUM(AS109:AS111) -> 196482 | AT108: =SUM(AT109:AT111) -> 149347 | AU108: =SUM(AU109:AU111) -> 135192 | AV108: =SUM(AV109:AV111) -> 28227.68 | AW108: =SUM(AW109:AW111) -> 11280 | AX108: =SUM(AX109:AX111) -> 5640 | ... BB108: =SUM(BB109:BB111) -> 13640 | BD108: =SUM(BD109:BD111) -> 248499.83 | BE108: =SUM(BE109:BE111) -> 0 | BF108: =SUM(BF109:BF111) -> 0 | BG108: =SUM(BG109:BG111) -> 0 | BH108: =SUM(BH109:BH111) -> 0 | BI108: =SUM(BI109:BI111) -> 0 | BK108: =SUM(BK109:BK111) -> 0
A109: Auto-Renta | B109: =1870333+495256 -> 2365589 | D109: 1870333 | E109: =952747+462203 -> 1414950 | F109: 952747 | G109: =+H109+472543 -> 813746 | H109: 341203 | I109: 637746 | J109: 316783 | K109: 292755 | L109: 302016 | M109: 629496 | N109: 304463 | O109: 16610 | Q109: =+R109+76010-80405 -> 76030 | R109: =+S109+80405-152000 -> 80425 | S109: =+T109+76010 -> 152020 | T109: 76010 | U109: =+V109+87010 -> 373270 | V109: =+W109+101970 -> 286260 | W109: =+X109+77220-1034369 -> 184290 | X109: =+Y109+107140 -> 1141439 | Y109: =+Z109+83160 -> 1034299 | Z109: =+AA109+113080 -> 951139 | AA109: =+AB109+83160 -> 838059 | AB109: 754899 | AD109: 1009369 | AE109: 811405 | AF109: 794010 | AG109: 699930 | AH109: 664180 | AI109: 609180 | AJ109: 539220 | AK109: 461340 | AL109: 121574 | AM109: 52321 | AN109: 40161 | AO109: 23521 | AQ109: 248589 | AR109: 179707 | AS109: 179707 | AT109: 149347 | AU109: 92766 | AV109: 0 | AW109: 0 | AX109: 0 | AY109: 48919 | AZ109: 36881 | BA109: 16000 | BB109: 8000 | BD109: 112000 | BK109: 0
A110: Retencion fuente | B110: =+D110+7166 -> 77137 | D110: =59186+10785 -> 69971 | E110: =39144+10785 -> 49929 | F110: =9422+10785 -> 20207 | G110: =10936+10785 -> 21721 | H110: 10936 | I110: 33813 | J110: 17548 | K110: 17598 | L110: 16408 | M110: 66317 | N110: 49503 | O110: 30929 | Q110: =+R110+28433-28433-28800+23130 -> 51811 | R110: =+S110-57840+28800-55000+28433 -> 57481 | S110: =+T110+53711 -> 113088 | T110: =26815+32562 -> 59377 | U110: =+V110+61536 -> 245608.75 | V110: =+W110+56085 -> 184072.75 | W110: =+X110+61870-334000 -> 127987.75 | X110: =+Y110+65832 -> 400117.75 | Y110: =+Z110+61163 -> 334285.75 | Z110: =+AA110+63582 -> 273122.75 | AA110: =+AB110+59478 -> 209540.75 | AB110: 150062.75 | AD110: 430230 | AE110: 343195 | AF110: 310582 | AG110: 280459.75 | AH110: 280459.75 | AI110: 254283 | AJ110: 230484.67 | AK110: 676761.11 | AL110: 322991.75 | AM110: 243122.99 | AN110: 168269 | AO110: 145512 | AQ110: 6204 | AR110: 16775 | AS110: 16775 | AT110: 0 | AU110: 42426 | AV110: 28227.68 | AW110: 11280 | AX110: 5640 | AY110: 22560 | AZ110: 16920 | BA110: 11280 | BB110: 5640 | BD110: 136499.83 | BK110: 0
A111: Provision Renta | B111: =+D111 -> 17191802 | D111: =+E111+'NOTAS ERI'!Q177 -> 17191802 | E111: =+F111+'NOTAS ERI'!R177 -> 13902581 | F111: =+G111+'NOTAS ERI'!S177 -> 9849622.3 | G111: =+H111+'NOTAS ERI'!T177 -> 4649844.1 | H111: =+I111+'NOTAS ERI'!U177 -> -1031571.8 | I111: =+J111+'NOTAS ERI'!V177 -> -2519084.3 | J111: =+K111+'NOTAS ERI'!W177 -> -2940659.7 | K111: =+L111+'NOTAS ERI'!X177-Q111 -> -3417889.2 | L111: =+M111+'NOTAS ERI'!Y177 -> 1536516.9 | M111: =+N111+'NOTAS ERI'!Z177 -> 1770014.5 | N111: =+O111+'NOTAS ERI'!AA177 -> 613705.03 | O111: =+Q111+'NOTAS ERI'!AB177 -> 2262522.1 | Q111: =+R111+'NOTAS ERI'!AE177 -> 4424318.9 | R111: =+S111+'NOTAS ERI'!AF177 -> 3580802.8 | S111: =+T111+'NOTAS ERI'!AG177 -> 2620202.6 | T111: =+U111+'NOTAS ERI'!AH177 -> 1883850.9 | U111: =+V111+'NOTAS ERI'!AI177 -> 1731018.2 | V111: =+W111+'NOTAS ERI'!AJ177 -> 1236380.7 | W111: =+X111+'NOTAS ERI'!AK177 -> 291888.92 | X111: =+'NOTAS ERI'!AP177+'NOTAS ERI'!AO177+'NOTAS ERI'!AN177+'NOTAS ERI'!AM177+'NOTAS ERI'!AL177 -> 513227.17 | Y111: =3138638.524+'NOTAS ERI'!AP177+'NOTAS ERI'!AO177+'NOTAS ERI'!AN177+'NOTAS ERI'!AM177 -> 3221299.1 | Z111: =3138638.524+'NOTAS ERI'!AP177+'NOTAS ERI'!AO177+'NOTAS ERI'!AN177 -> 3925253.4 | AA111: =3138638.524+'NOTAS ERI'!AP177+'NOTAS ERI'!AO177 -> 3385911.8 | AB111: =3138638.524+'NOTAS ERI'!AP177 -> 3747634.7 | AD111: =+ERI!AU49 -> 3138638.5
A112: Iva por Pagar | B112: =SUM(B113:B116) -> 19118921 | D112: =SUM(D113:D116) -> 21554956 | E112: =SUM(E113:E116) -> 21498466 | F112: =SUM(F113:F116) -> 21402313 | G112: =SUM(G113:G116) -> 21858463 | H112: =SUM(H113:H116) -> 21476221 | I112: =SUM(I113:I116) -> 23384992 | J112: =SUM(J113:J116) -> 25621406 | K112: =SUM(K113:K116) -> 27955683 | ... O112: =SUM(O113:O116) -> 28387490 | Q112: =SUM(Q113:Q116) -> 28422201 | R112: =SUM(R113:R116) -> 29081340 | S112: =SUM(S113:S116) -> 27872851 | T112: =SUM(T113:T116) -> 29749890 | U112: =SUM(U113:U116) -> 28653548 | V112: =SUM(V113:V116) -> 27362909 | W112: =SUM(W113:W116) -> 25769761 | X112: =SUM(X113:X116) -> 25459643 | ... AB112: =SUM(AB113:AB116) -> 19599032 | AD112: =SUM(AD113:AD116) -> 14987000 | AE112: =SUM(AE113:AE116) -> 13377305 | AF112: =SUM(AF113:AF116) -> 12517398 | AG112: =SUM(AG113:AG116) -> 10613293 | AH112: =SUM(AH113:AH116) -> 10032883 | AI112: =SUM(AI113:AI116) -> 9148618.6 | AJ112: =SUM(AJ113:AJ116) -> 8401467 | AK112: =SUM(AK113:AK116) -> 7532514 | ... AO112: =SUM(AO113:AO116) -> 99275 | AQ112: =SUM(AQ113:AQ116) -> 3781768 | AR112: =SUM(AR113:AR116) -> 3231119 | AS112: =SUM(AS113:AS116) -> 3231119 | AT112: =SUM(AT113:AT116) -> 2673931.4 | AU112: =SUM(AU113:AU116) -> 1692148.1 | AV112: =SUM(AV113:AV116) -> -53744 | AW112: =SUM(AW113:AW116) -> 15801.76 | AX112: =SUM(AX113:AX116) -> 87632.21 | ... BB112: =SUM(BB113:BB116) -> -662617.02 | BD112: =SUM(BD113:BD116) -> 46000 | BE112: =SUM(BE113:BE116) -> 0 | BF112: =SUM(BF113:BF116) -> 0 | BG112: =SUM(BG113:BG116) -> 0 | BH112: =SUM(BH113:BH116) -> 0 | BI112: =SUM(BI113:BI116) -> 0 | BK112: =SUM(BK113:BK116) -> 0
A113: Generado | B113: 3860517 | D113: =+E113+3660064 -> 15483172 | E113: =+F113+3777864 -> 11823108 | F113: =+G113+4088780-4940756 -> 8045244 | G113: =+H113+3956464 -> 8897220 | H113: =+I113+1687864 -> 4940756 | I113: =648564+1266064+1338264 -> 3252892 | J113: =648564+1266064 -> 1914628 | K113: 648564 | L113: =+M113+1010989 -> 3472817 | M113: =+N113+1408564 -> 2461828 | N113: =+O113+766364 -> 1053264 | O113: 286900 | Q113: =+R113+1312900 -> 18165821 | R113: =+S113+1388822 -> 16852921 | S113: =+T113+1430700-117800 -> 15464099 | T113: =+U113+1312900 -> 14151199 | U113: =+V113+1502900 -> 12838299 | V113: =+W113+1761300 -> 11335399 | W113: =+X113+1333800 -> 9574099.4 | X113: =+Y113+1850600 -> 8240299.4 | Y113: =+Z113+1333800 -> 6389699.4 | Z113: =+AA113+2055800 -> 5055899.4 | AA113: =+AB113+1436400 -> 3000099.4 | AB113: 1563699.4 | AD113: =5963000 -> 5963000 | AE113: 4327330.4 | AF113: 2851900 | AG113: 617500 | AH113: 11510200 | AI113: 10560200 | AJ113: 9351800 | AK113: 8006600 | AL113: 2289911.9 | AM113: 1432631 | AN113: 953832 | AO113: 558631 | AQ113: 5903979 | AR113: 4268047 | AS113: 4268047 | AT113: 3546997 | AU113: 2413189 | AV113: 210000 | AW113: 210000 | AX113: 210000 | AY113: 1161834 | AZ113: 875922 | BA113: 380000 | BB113: 190000 | BD113: 754000 | BK113: 0
A114: Descontable | B114: -490552 | D114: =+E114-170574 -> -785417 | E114: =+F114-246711 -> -614843 | F114: =+G114-226910+622736 -> -368132 | G114: =+H114-141222 -> -763958 | H114: =+I114-163635 -> -622736 | I114: =-150082-167341-141678 -> -459101 | J114: =-150082-167341 -> -317423 | K114: -150082 | L114: =+M114-175885 -> -780728 | M114: =+N114-128017 -> -604843 | N114: =-321611-155215 -> -476826 | O114: -321611 | Q114: =+R114-972039 -> -3206620.4 | R114: =+S114-180333 -> -2234581.4 | S114: =+T114-189939 -> -2054248.4 | T114: =+U114-216558 -> -1864309.4 | U114: =+V114-212261 -> -1647751.4 | V114: =+W114-168152 -> -1435490.4 | W114: =+X114-215682 -> -1267338.4 | X114: =+Y114-208032 -> -1051656.4 | Y114: =+Z114-210295 -> -843624.43 | Z114: =+AA114-194301 -> -633329.43 | AA114: =+AB114-203361 -> -439028.43 | AB114: -235667.43 | AC114: =+AB113-AD113 -> -4399300.6 | AD114: =-1008694.03+261 -> -1008433 | AE114: -982458.46 | AF114: -366935.6 | AG114: -36639.9 | AH114: -1439317 | AI114: -1373581.4 | AJ114: -912333 | AK114: -436086 | AL114: -1864162.6 | AM114: -1444167 | AN114: -935413 | AO114: -459356 | AQ114: -2122211 | AR114: -1036928 | AS114: -1036928 | AT114: -873065.58 | AU114: -721040.94 | AV114: -263744 | AW114: -194198.24 | AX114: -122367.79 | AY114: -1170903.8 | AZ114: -1120163.3 | BA114: -911268.5 | BB114: -852617.02 | BD114: -708000 | BK114: 0
A115: Devoluciones | V115: 0 | W115: 0 | X115: 0 | Y115: 0 | Z115: 0 | AA115: 0 | AB115: 0 | AD115: 0 | AE115: 0 | AG115: 0 | AH115: -38000 | AI115: -38000 | AJ115: -38000 | AK115: -38000 | AL115: -190000 | AM115: -190000
A116: Periodos anteriores | B116: =+D116+12849755-3958000 -> 15748956 | D116: =+E116-3433000 -> 6857201 | E116: =+F116-3435000 -> 10290201 | F116: =+G116 -> 13725201 | G116: =+H116-3433000 -> 13725201 | H116: =+I116-3433000 -> 17158201 | I116: =+J116-3433000 -> 20591201 | J116: =+K116-3433000 -> 24024201 | K116: =+L116-3433000 -> 27457201 | L116: =+M116-3433000 -> 30890201 | M116: =+N116-3433000 -> 34323201 | N116: =+O116+9334000 -> 37756201 | O116: =+Q116+Q113+Q114 -> 28422201 | Q116: =+R116-1000000 -> 13463000 | R116: =+S116 -> 14463000 | S116: =+T116-3000000 -> 14463000 | T116: =+U116 -> 17463000 | U116: =+V116 -> 17463000 | V116: =+W116 -> 17463000 | W116: =+X116-808000 -> 17463000 | X116: =+Y116 -> 18271000 | Y116: =+Z116 -> 18271000 | Z116: =+AA116 -> 18271000 | AA116: =+AB116 -> 18271000 | AB116: =14987000.09+3284000 -> 18271000 | AD116: 10032433 | AE116: 10032433 | AF116: 10032433 | AG116: 10032433
A118: Por Beneficios A Empleados | B118: =SUM(B119:B123) -> 44679735 | D118: =SUM(D119:D123) -> 35230529 | E118: =SUM(E119:E123) -> 46596939 | F118: =SUM(F119:F123) -> 29319455 | G118: =SUM(G119:G123) -> 44412470 | H118: =SUM(H119:H123) -> 40577188 | I118: =SUM(I119:I123) -> 36741704 | J118: =SUM(J119:J123) -> 33292159 | K118: =SUM(K119:K123) -> 37217535 | ... O118: =SUM(O119:O123) -> 16395504 | Q118: =SUM(Q119:Q123) -> 16398640 | R118: =SUM(R119:R123) -> 16775928 | S118: =SUM(S119:S123) -> 16355689 | T118: =SUM(T119:T123) -> 20855057 | U118: =SUM(U119:U123) -> 17768027 | V118: =SUM(V119:V123) -> 17113268 | W118: =SUM(W119:W123) -> 17254521 | X118: =SUM(X119:X123) -> 17747629 | ... AB118: =SUM(AB119:AB123) -> 11572647 | AD118: =SUM(AD119:AD123) -> 10384219 | AE118: =SUM(AE119:AE123) -> 11172268 | AF118: =SUM(AF119:AF123) -> 10466235 | AG118: =SUM(AG119:AG123) -> 5838235 | AH118: =SUM(AH119:AH123) -> 5506749 | AI118: =SUM(AI119:AI123) -> 4822615 | AJ118: =SUM(AJ119:AJ123) -> 5416539 | AK118: =SUM(AK119:AK123) -> 5076869 | ... AO118: =SUM(AO119:AO123) -> 3714002 | AQ118: =SUM(AQ119:AQ123) -> 3419676.7 | AR118: =SUM(AR119:AR123) -> 6199779 | AS118: =SUM(AS119:AS123) -> 5368633 | AT118: =SUM(AT119:AT123) -> 4087491 | AU118: =SUM(AU119:AU123) -> 2824195 | AV118: =SUM(AV119:AV123) -> 2579874 | AW118: =SUM(AW119:AW123) -> 2162737 | AX118: =SUM(AX119:AX123) -> 2463015 | ... BB118: =SUM(BB119:BB123) -> 2415217 | BD118: =SUM(BD119:BD123) -> 1499566.3 | BE118: =SUM(BE119:BE123) -> 0 | BF118: =SUM(BF119:BF123) -> 0 | BG118: =SUM(BG119:BG123) -> 0 | BH118: =SUM(BH119:BH123) -> 0 | BI118: =SUM(BI119:BI123) -> 0 | BK118: =SUM(BK119:BK123) -> 0
A119: Salarios por pagar | B119: 19611117 | D119: 14538199 | E119: 13442000 | F119: 0 | G119: 17060800 | H119: 17061002 | I119: 17061002 | J119: 16386868 | K119: 15959000 | L119: 16761000 | M119: 15403235 | N119: 13332019 | O119: 3319000 | Q119: 4039400 | R119: 3454600 | S119: 3684267 | T119: 8875200 | U119: 5007533 | V119: 4715133 | W119: 4568933 | X119: 6024400 | Y119: 6268067 | Z119: 6078400 | AA119: =4590507+407400+407400+817000 -> 6222307 | AB119: =3590665+679000+679000 -> 4948665 | AD119: 3943548 | AE119: 3688852 | AF119: 3775288 | AG119: 0 | AH119: 0 | AI119: 0 | AJ119: 0 | AK119: 0 | AL119: 0 | AM119: 0 | AN119: 0 | AO119: 0 | AQ119: 0 | BD119: 0 | BK119: 0
A120: Cesantías | B120: =+D120+1681892 -> 14898492 | D120: =+E120+1448951-4923335 -> 13216600 | E120: =+F120+1476648 -> 16690984 | F120: =+G120+1476648-938024 -> 15214336 | G120: =+H120+1476648 -> 14675712 | H120: =+I120+1476648 -> 13199064 | I120: 11722416 | J120: =9693933+1443087-477314 -> 10659706 | K120: 9693933 | L120: 8289201 | M120: 10535734 | N120: 9200854 | O120: =+Q120+270584 -> 8032837 | Q120: 7762253 | R120: 7518587 | S120: 7274921 | T120: 7015011 | U120: 6649512 | V120: 6284013 | W120: 6405846 | X120: 6040347 | Y120: 5553015 | Z120: 5065683 | AA120: 4578351 | AB120: =3969187+121833 -> 4091020 | AD120: 3725520 | AE120: 3399279 | AF120: 3090508 | AG120: 2758265 | AH120: 2737817 | AI120: 2412797 | AJ120: 2196117 | AK120: 1921655 | AL120: 1704975 | AM120: 1488295 | AN120: 629224 | AO120: 2397396 | AQ120: 2180716 | AR120: 2498092 | AS120: 2448039 | AT120: 1947989 | AU120: 1454717 | AV120: 1357213 | AW120: 1310944 | AX120: 1310944 | AY120: 1310944 | AZ120: 1310944 | BA120: 310944 | BB120: 1292332 | BD120: 937116 | BK120: 0
...

Sheet NOTAS ERI
A1: =+ESF!B2 -> JELCOM SOLUCIONES EMPRESARIALES SAS
A2: NIT. 900.566.015-4
A3: NOTAS A LOS ESTADOS FINANCIEROS
B5: 2026 | C5: 2026 | D5: 2026 | E5: 2026 | F5: 2026 | G5: 2026 | H5: 2026 | I5: 2026 | J5: 2026 | K5: 2026 | L5: 2026 | M5: 2026 | N5: 2026 | P5: 2025 | Q5: 2025 | R5: 2025 | S5: 2025 | T5: 2025 | U5: 2025 | V5: 2025 | W5: 2025 | X5: 2025 | Y5: 2025 | Z5: 2025 | AA5: 2025 | AB5: 2025 | AD5: 2024 | AE5: 2024 | AF5: 2024 | AG5: 2024 | AH5: 2024 | AI5: 2024 | AJ5: 2024 | AK5: 2024 | AL5: 2024 | AM5: 2024 | AN5: 2024 | AO5: 2024 | AP5: 2024 | AR5: 2023 | AS5: 2023 | AT5: 2023 | AU5: 2023 | AV5: 2023 | AW5: 2023 | AX5: 2023 | AY5: 2023 | AZ5: 2023 | BA5: 2023 | BB5: 2023 | BC5: 2023 | BD5: 2023 | BF5: 2022 | BG5: 2022 | BH5: 2022 | BI5: 2022 | BJ5: 2022 | BK5: 2022 | BL5: 2022 | BM5: 2022 | BN5: 2022 | BO5: 2022 | BP5: 2022 | BQ5: 2022 | BR5: 2022 | BT5: 2021 | BU5: 2021 | BV5: 2021 | BW5: 2021 | BX5: 2021 | BY5: 2021 | BZ5: 2021 | CB5: 2020
B6: ACUMULADO | C6: DICIEMBRE | D6: NOVIEMBRE | E6: OCTUBRE | F6: SEPTIEMBRE | G6: AGOSTO | H6: JULIO | I6: JUNIO | J6: MAYO | K6: ABRIL | L6: MARZO | M6: FEBRERO | N6: ENERO | P6: DICIEMBRE | Q6: DICIEMBRE | R6: NOVIEMBRE | S6: OCTUBRE | T6: SEPTIEMBRE | U6: AGOSTO | V6: JULIO | W6: JUNIO | X6: MAYO | Y6: ABRIL | Z6: MARZO | AA6: FEBRERO | AB6: ENERO | AD6: DICIEMBRE | AE6: DIC | AF6: NOV | AG6: OCTU | AH6: SEPTI | AI6: AGOST | AJ6: JUL | AK6: JUN | AL6: MAYO | AM6: ABRIL | AN6: MARZO | AO6: FEBRERO | AP6: ENERO | AR6: DICIEMBRE | AS6: DICIEMBRE | AT6: NOVIEMBRE | AU6: OCTUBRE | AV6: SEPTIEMBRE | AW6: AGOSTO | AX6: JULIO | AY6: JUNIO | AZ6: MAYO | BA6: ABRIL | BB6: MARZO | BC6: FEBRERO | BD6: ENERO | BF6: DICIEMBRE | BG6: DICIEMBRE | BH6: NOVIEMBRE | BI6: OCTUBRE | BJ6: SEPTIEMBRE | BK6: AGOSTO | BL6: JULIO | BM6: JUNIO | BN6: MAYO | BO6: ABRIL | BP6: MARZO | BQ6: FEBRERO | BR6: ENERO | BT6: DICIEMBRE | BU6: DICIEMBRE | BV6: SEPTIEMBRE | BW6: AGOSTO | BX6: JULIO | BY6: JUNIO | BZ6: MAYO | CB6: DICIEMBRE
A7: INGRESOS
A9: OPERACIONALES | B9: =+B10+B38 -> 45023259 | C9: =+C10+C38 -> 0 | D9: =+D10+D38 -> 0 | E9: =+E10+E38 -> 0 | F9: =+F10+F38 -> 0 | G9: =+G10+G38 -> 0 | H9: =+H10+H38 -> 0 | I9: =+I10+I38 -> 0 | ... N9: =+N10+N38 -> 45023259 | P9: =+P10+P38 -> 370322671 | Q9: =+Q10+Q38 -> 41398469 | R9: =+R10+R38 -> 42018469 | S9: =+S10+S38 -> 43654871 | T9: =+T10+T38 -> 42958469 | U9: =+U10+U38 -> 31018469 | V9: =+V10+V38 -> 29178469 | W9: =+W10+W38 -> 28798469 | ... AB9: =+AB10+AB38 -> 1510000 | AD9: =+AD10+AD38 -> 95609587 | AE9: =+AE10+AE38 -> 6910000 | AF9: =+AF10+AF38 -> 7309587 | AG9: =+AG10+AG38 -> 6910000 | AH9: =+AH10+AH38 -> 6910000 | AI9: =+AI10+AI38 -> 7910000 | AJ9: =+AJ10+AJ38 -> 9270000 | AK9: =+AK10+AK38 -> 7020000 | ... AP9: =+AP10+AP38 -> 8230000 | AR9: =+AR10+AR38 -> 102813014 | AS9: =+AS10+AS38 -> 8185423 | AT9: =+AT10+AT38 -> 8185423 | AU9: =+AU10+AU38 -> 11760000 | AV9: =+AV10+AV38 -> 2360000 | AW9: =+AW10+AW38 -> 5890000 | AX9: =+AX10+AX38 -> 6360000 | AY9: =+AY10+AY38 -> 7080000 | ... BD9: =+BD10+BD38 -> 2940168 | BF9: =+BF10+BF38 -> 47784225 | BG9: =+BG10+BG38 -> 6640168 | BH9: =+BH10+BH38 -> 1970000 | BI9: =+BI10+BI38 -> 3795000 | BJ9: =+BJ10+BJ38 -> 18668403 | BK9: =+BK10+BK38 -> 11595735 | BL9: =+BL10+BL38 -> 0 | BM9: =+BM10+BM38 -> 0 | ... BR9: =+BR10+BR38 -> 1000000 | BT9: =+BT10+BT38 -> 18444000 | BU9: =SUM(BU37:BU37) -> 0 | BV9: =SUM(BV37:BV37) -> 0 | BW9: =SUM(BW37:BW37) -> 0 | BX9: =SUM(BX37:BX37) -> 0 | BY9: =SUM(BY37:BY37) -> 0 | BZ9: =SUM(BZ37:BZ37) -> 0 | CB9: =SUM(CB37:CB37) -> 0
A10: Actividades de Centro de Llamadas | B10: =SUM(B11:B37) -> 66237137 | C10: =SUM(C11:C37) -> 0 | D10: =SUM(D11:D37) -> 0 | E10: =SUM(E11:E37) -> 0 | F10: =SUM(F11:F37) -> 0 | G10: =SUM(G11:G37) -> 0 | H10: =SUM(H11:H37) -> 0 | I10: =SUM(I11:I37) -> 0 | ... N10: =SUM(N11:N37) -> 66237137 | P10: =SUM(P11:P37) -> 399036750 | Q10: =SUM(Q11:Q37) -> 41398469 | R10: =SUM(R11:R37) -> 42018469 | S10: =SUM(S11:S37) -> 43654871 | T10: =SUM(T11:T37) -> 42958469 | U10: =SUM(U11:U37) -> 31018469 | V10: =SUM(V11:V37) -> 56826938 | W10: =SUM(W11:W37) -> 28798469 | ... AB10: =SUM(AB11:AB37) -> 1510000 | AD10: =SUM(AD11:AD37) -> 96769587 | AE10: =SUM(AE11:AE37) -> 6910000 | AF10: =SUM(AF11:AF37) -> 7309587 | AG10: =SUM(AG11:AG37) -> 7530000 | AH10: =SUM(AH11:AH37) -> 6910000 | AI10: =SUM(AI11:AI37) -> 7910000 | AJ10: =SUM(AJ11:AJ37) -> 9270000 | AK10: =SUM(AK11:AK37) -> 7020000 | ... AP10: =SUM(AP11:AP37) -> 8230000 | AR10: =SUM(AR11:AR37) -> 105983014 | AS10: =SUM(AS11:AS37) -> 8185423 | AT10: =SUM(AT11:AT37) -> 8185423 | AU10: =SUM(AU11:AU37) -> 13260000 | AV10: =SUM(AV11:AV37) -> 2360000 | AW10: =SUM(AW11:AW37) -> 6360000 | AX10: =SUM(AX11:AX37) -> 6360000 | AY10: =SUM(AY11:AY37) -> 7080000 | ... BD10: =SUM(BD11:BD37) -> 2940168 | BF10: =SUM(BF11:BF37) -> 51027964 | BG10: =SUM(BG11:BG37) -> 6640168 | BH10: =SUM(BH11:BH37) -> 1970000 | BI10: =SUM(BI11:BI37) -> 3795000 | BJ10: =SUM(BJ11:BJ37) -> 18668403 | BK10: =SUM(BK11:BK37) -> 12733235 | BL10: =SUM(BL11:BL37) -> 0 | BM10: =SUM(BM11:BM37) -> 0 | ... BR10: =SUM(BR11:BR37) -> 1000000 | BT10: =SUM(BT11:BT37) -> 29847361
A11: Alirio Salaza Bayona | B11: =SUM(C11:N11) -> 0 | C11: 0 | D11: 0 | E11: 0 | F11: 0 | G11: 0 | H11: 0 | I11: 0 | J11: 0 | K11: 0 | L11: 0 | M11: 0 | N11: 0 | P11: =SUM(Q11:AB11) -> 7440000 | Q11: 0 | R11: 620000 | S11: 620000 | T11: 620000 | U11: 620000 | V11: 620000 | W11: 620000 | X11: 620000 | Y11: 620000 | Z11: 620000 | AA11: 1240000 | AB11: 620000 | AD11: =SUM(AE11:AP11) -> 7910000 | AE11: 620000 | AF11: 620000 | AG11: 1240000 | AH11: 620000 | AI11: 620000 | AJ11: 620000 | AK11: 620000 | AL11: 620000 | AM11: 620000 | AN11: 620000 | AO11: 620000 | AP11: 470000 | AR11: =SUM(AS11:BD11) -> 0 | AS11: 0 | AT11: 0 | AU11: 0 | AV11: 0 | AW11: 0 | AX11: 0 | AY11: 0 | AZ11: 0 | BA11: 0 | BB11: 0 | BC11: 0 | BD11: 0 | BF11: =SUM(BG11:BR11) -> 0 | BG11: 0 | BH11: 0 | BI11: 0 | BJ11: 0 | BK11: 0 | BL11: 0 | BM11: 0 | BN11: 0 | BO11: 0 | BP11: 0 | BQ11: 0 | BR11: 0 | BT11: =SUM(BU11:BZ11) -> 0 | BU11: 0 | BV11: 0 | BW11: 0 | BX11: 0 | BY11: 0 | BZ11: 0
A12: Antonio Maria Rodriguez Bravo | B12: =SUM(C12:N12) -> 0 | C12: 0 | D12: 0 | E12: 0 | F12: 0 | G12: 0 | H12: 0 | I12: 0 | J12: 0 | K12: 0 | L12: 0 | M12: 0 | N12: 0 | P12: =SUM(Q12:AB12) -> 0 | Q12: 0 | R12: 0 | S12: 0 | T12: 0 | U12: 0 | V12: 0 | W12: 0 | X12: 0 | Y12: 0 | Z12: 0 | AA12: 0 | AB12: 0 | AD12: =SUM(AE12:AP12) -> 0 | AE12: 0 | AF12: 0 | AG12: 0 | AH12: 0 | AI12: 0 | AJ12: 0 | AK12: 0 | AL12: 0 | AM12: 0 | AN12: 0 | AO12: 0 | AP12: 0 | AR12: =SUM(AS12:BD12) -> 1225423 | AS12: 425423 | AT12: 0 | AU12: 0 | AV12: 0 | AW12: 0 | AX12: 0 | AY12: 200000 | AZ12: 200000 | BA12: 400000 | BB12: 0 | BC12: 0 | BD12: 0 | BF12: =SUM(BG12:BR12) -> 450000 | BG12: 300000 | BH12: 150000 | BI12: 0 | BJ12: 0 | BK12: 0 | BL12: 0 | BM12: 0 | BN12: 0 | BO12: 0 | BP12: 0 | BQ12: 0 | BR12: 0 | BT12: =SUM(BU12:BZ12) -> 0 | BU12: 0 | BV12: 0 | BW12: 0 | BX12: 0 | BY12: 0 | BZ12: 0
A13: Caja Santandereana - Cajasan | B13: =SUM(C13:N13) -> 11000000 | C13: 0 | D13: 0 | E13: 0 | F13: 0 | G13: 0 | H13: 0 | I13: 0 | J13: 0 | K13: 0 | L13: 0 | M13: 0 | N13: 11000000 | P13: =SUM(Q13:AB13) -> 44000000 | Q13: 11000000 | R13: 11000000 | S13: 11000000 | T13: 11000000 | U13: 0 | V13: 0 | W13: 0 | X13: 0 | Y13: 0 | Z13: 0 | AA13: 0 | AB13: 0 | AD13: =SUM(AE13:AP13) -> 64800000 | AE13: 5400000 | AF13: 5400000 | AG13: 5400000 | AH13: 5400000 | AI13: 5400000 | AJ13: 5400000 | AK13: 5400000 | AL13: 5400000 | AM13: 5400000 | AN13: 5400000 | AO13: 5400000 | AP13: 5400000 | AR13: =SUM(AS13:BD13) -> 32200000 | AS13: 5400000 | AT13: 5400000 | AU13: 9400000 | AV13: 0 | AW13: 4000000 | AX13: 4000000 | AY13: 4000000 | AZ13: 0 | BA13: 0 | BB13: 0 | BC13: 0 | BD13: 0 | BF13: =SUM(BG13:BR13) -> 25050000 | BG13: 0 | BH13: 0 | BI13: 0 | BJ13: 16700000 | BK13: 8350000 | BL13: 0 | BM13: 0 | BN13: 0 | BO13: 0 | BP13: 0 | BQ13: 0 | BR13: 0 | BT13: =SUM(BU13:BZ13) -> 0 | BU13: 0 | BV13: 0 | BW13: 0 | BX13: 0 | BY13: 0 | BZ13: 0
A14: Centro Comercial El Puente | B14: =SUM(C14:N14) -> 0 | C14: 0 | D14: 0 | E14: 0 | F14: 0 | G14: 0 | H14: 0 | I14: 0 | J14: 0 | K14: 0 | L14: 0 | M14: 0 | N14: 0 | P14: =SUM(Q14:AB14) -> 1703122 | Q14: 0 | R14: 0 | S14: 811902 | T14: 0 | U14: 0 | V14: 0 | W14: 0 | X14: 445610 | Y14: 445610 | Z14: 0 | AA14: 0 | AB14: 0 | AD14: =SUM(AE14:AP14) -> 8000000 | AE14: 0 | AF14: 0 | AG14: 0 | AH14: 0 | AI14: 1000000 | AJ14: 1000000 | AK14: 1000000 | AL14: 1000000 | AM14: 1000000 | AN14: 1000000 | AO14: 1000000 | AP14: 1000000 | AR14: =SUM(AS14:BD14) -> 12500000 | AS14: 1000000 | AT14: 1000000 | AU14: 2500000 | AV14: 1000000 | AW14: 1000000 | AX14: 1000000 | AY14: 1000000 | AZ14: 1000000 | BA14: 1000000 | BB14: 1000000 | BC14: 0 | BD14: 1000000 | BF14: =SUM(BG14:BR14) -> 8000000 | BG14: 1000000 | BH14: 1000000 | BI14: 1000000 | BJ14: 0 | BK14: 1000000 | BL14: 0 | BM14: 0 | BN14: 0 | BO14: 1000000 | BP14: 1000000 | BQ14: 1000000 | BR14: 1000000 | BT14: 1500000 | BU14: 0 | BV14: 0 | BW14: 500000 | BX14: 0 | BY14: 0 | BZ14: 0
A15: Camara De Comercio De Bucaramanga | B15: =SUM(C15:N15) -> 0 | C15: 0 | D15: 0 | E15: 0 | F15: 0 | G15: 0 | H15: 0 | I15: 0 | J15: 0 | K15: 0 | L15: 0 | M15: 0 | N15: 0 | P15: =SUM(Q15:AB15) -> 0 | Q15: 0 | R15: 0 | S15: 0 | T15: 0 | U15: 0 | V15: 0 | W15: 0 | X15: 0 | Y15: 0 | Z15: 0 | AA15: 0 | AB15: 0 | AD15: =SUM(AE15:AP15) -> 0 | AE15: 0 | AF15: 0 | AG15: 0 | AH15: 0 | AI15: 0 | AJ15: 0 | AK15: 0 | AL15: 0 | AM15: 0 | AN15: 0 | AO15: 0 | AP15: 0 | AR15: =SUM(AS15:BD15) -> 40000000 | AS15: 0 | AT15: 0 | AU15: 0 | AV15: 0 | AW15: 0 | AX15: 0 | AY15: 0 | AZ15: 40000000 | BA15: 0 | BB15: 0 | BC15: 0 | BD15: 0 | BF15: =SUM(BG15:BR15) -> 0 | BG15: 0 | BH15: 0 | BI15: 0 | BJ15: 0 | BK15: 0 | BL15: 0 | BM15: 0 | BN15: 0 | BO15: 0 | BP15: 0 | BQ15: 0 | BR15: 0 | BT15: =SUM(BU15:BZ15) -> 0 | BU15: 0 | BV15: 0 | BW15: 0 | BX15: 0 | BY15: 0 | BZ15: 0
A16: Centro De Diagnostico Automotor Cotrasangil | B16: =SUM(C16:N16) -> 0 | C16: 0 | D16: 0 | E16: 0 | F16: 0 | G16: 0 | H16: 0 | I16: 0 | J16: 0 | K16: 0 | L16: 0 | M16: 0 | N16: 0 | P16: =SUM(Q16:AB16) -> 0 | Q16: 0 | R16: 0 | S16: 0 | T16: 0 | U16: 0 | V16: 0 | W16: 0 | X16: 0 | Y16: 0 | Z16: 0 | AA16: 0 | AB16: 0 | AD16: =SUM(AE16:AP16) -> 0 | AE16: 0 | AF16: 0 | AG16: 0 | AH16: 0 | AI16: 0 | AJ16: 0 | AK16: 0 | AL16: 0 | AM16: 0 | AN16: 0 | AO16: 0 | AP16: 0 | AR16: =SUM(AS16:BD16) -> 730000 | AS16: 0 | AT16: 0 | AU16: 0 | AV16: 0 | AW16: 0 | AX16: 0 | AY16: 0 | AZ16: 0 | BA16: 0 | BB16: 0 | BC16: 730000 | BD16: 0 | BF16: =SUM(BG16:BR16) -> 0 | BG16: 0 | BH16: 0 | BI16: 0 | BJ16: 0 | BK16: 0 | BL16: 0 | BM16: 0 | BN16: 0 | BO16: 0 | BP16: 0 | BQ16: 0 | BR16: 0 | BT16: =SUM(BU16:BZ16) -> 0 | BU16: 0 | BV16: 0 | BW16: 0 | BX16: 0 | BY16: 0 | BZ16: 0
A17: Centro Comercial San Gil Plaza | B17: =SUM(C17:N17) -> 0 | C17: 0 | D17: 0 | E17: 0 | F17: 0 | G17: 0 | H17: 0 | I17: 0 | J17: 0 | K17: 0 | L17: 0 | M17: 0 | N17: 0 | P17: =SUM(Q17:AB17) -> 1222000 | Q17: 0 | R17: 0 | S17: 824500 | T17: 0 | U17: 0 | V17: 0 | W17: 0 | X17: 0 | Y17: 397500 | Z17: 0 | AA17: 0 | AB17: 0 | AD17: =SUM(AE17:AP17) -> 399587 | AE17: 0 | AF17: 399587 | AG17: 0 | AH17: 0 | AI17: 0 | AJ17: 0 | AK17: 0 | AL17: 0 | AM17: 0 | AN17: 0 | AO17: 0 | AP17: 0 | AR17: =SUM(AS17:BD17) -> 657423 | AS17: 0 | AT17: 425423 | AU17: 0 | AV17: 0 | AW17: 0 | AX17: 0 | AY17: 0 | AZ17: 0 | BA17: 232000 | BB17: 0 | BC17: 0 | BD17: 0 | BF17: =SUM(BG17:BR17) -> 1200000 | BG17: 300000 | BH17: 300000 | BI17: 0 | BJ17: 600000 | BK17: 0 | BL17: 0 | BM17: 0 | BN17: 0 | BO17: 0 | BP17: 0 | BQ17: 0 | BR17: 0 | BT17: =SUM(BU17:BZ17) -> 0 | BU17: 0 | BV17: 0 | BW17: 0 | BX17: 0 | BY17: 0 | BZ17: 0
A18: Clever Moves Sas | B18: =SUM(C18:N18) -> 0 | C18: =SUM(E18:P18) -> 0 | D18: =SUM(F18:Q18) -> 0 | E18: =SUM(G18:R18) -> 0 | F18: =SUM(H18:S18) -> 0 | G18: =SUM(I18:T18) -> 0 | H18: =SUM(J18:U18) -> 0 | I18: =SUM(K18:V18) -> 0 | J18: =SUM(L18:W18) -> 0 | ... N18: =SUM(P18:AA18) -> 0 | P18: =SUM(Q18:AB18) -> 0 | Q18: 0 | R18: 0 | S18: 0 | T18: 0 | U18: 0 | V18: 0 | W18: 0 | X18: 0 | Y18: 0 | Z18: 0 | AA18: 0 | AB18: 0 | AD18: =SUM(AE18:AP18) -> 0 | AE18: 0 | AF18: 0 | AG18: 0 | AH18: 0 | AI18: 0 | AJ18: 0 | AK18: 0 | AL18: 0 | AM18: 0 | AN18: 0 | AO18: 0 | AP18: 0 | AR18: =SUM(AS18:BD18) -> 0 | AS18: 0 | AT18: 0 | AU18: 0 | AV18: 0 | AW18: 0 | AX18: 0 | AY18: 0 | AZ18: 0 | BA18: 0 | BB18: 0 | BC18: 0 | BD18: 0 | BF18: =SUM(BG18:BR18) -> 1500000 | BG18: 1500000 | BH18: 0 | BI18: 0 | BJ18: 0 | BK18: 0 | BL18: 0 | BM18: 0 | BN18: 0 | BO18: 0 | BP18: 0 | BQ18: 0 | BR18: 0 | BT18: =SUM(BU18:BZ18) -> 0 | BU18: 0 | BV18: 0 | BW18: 0 | BX18: 0 | BY18: 0 | BZ18: 0
A19: Cooperativa de Caficultores de santander LTA | B19: =SUM(C19:N19) -> 0 | C19: =SUM(E19:P19) -> 0 | D19: =SUM(F19:Q19) -> 0 | E19: =SUM(G19:R19) -> 0 | F19: =SUM(H19:S19) -> 0 | G19: =SUM(I19:T19) -> 0 | H19: =SUM(J19:U19) -> 0 | I19: =SUM(K19:V19) -> 0 | J19: =SUM(L19:W19) -> 0 | ... N19: =SUM(P19:AA19) -> 0 | P19: =SUM(Q19:AB19) -> 0 | Q19: 0 | R19: 0 | S19: 0 | T19: 0 | U19: 0 | V19: 0 | W19: 0 | X19: 0 | Y19: 0 | Z19: 0 | AA19: 0 | AB19: 0 | BT19: 9444500
A20: Cooperativa Multiactiva De Hilados Del Fonce Limitada | B20: =SUM(C20:N20) -> 0 | C20: =SUM(E20:P20) -> 0 | D20: =SUM(F20:Q20) -> 0 | E20: =SUM(G20:R20) -> 0 | F20: =SUM(H20:S20) -> 0 | G20: =SUM(I20:T20) -> 0 | H20: =SUM(J20:U20) -> 0 | I20: =SUM(K20:V20) -> 0 | J20: =SUM(L20:W20) -> 0 | ... N20: =SUM(P20:AA20) -> 0 | P20: =SUM(Q20:AB20) -> 0 | Q20: 0 | R20: 0 | S20: 0 | T20: 0 | U20: 0 | V20: 0 | W20: 0 | X20: 0 | Y20: 0 | Z20: 0 | AA20: 0 | AB20: 0 | AD20: =SUM(AE20:AP20) -> 0 | AE20: 0 | AF20: 0 | AG20: 0 | AH20: 0 | AI20: 0 | AJ20: 0 | AK20: 0 | AL20: 0 | AM20: 0 | AN20: 0 | AO20: 0 | AP20: 0 | AR20: =SUM(AS20:BD20) -> 0 | AS20: 0 | AT20: 0 | AU20: 0 | AV20: 0 | AW20: 0 | AX20: 0 | AY20: 0 | AZ20: 0 | BA20: 0 | BB20: 0 | BC20: 0 | BD20: 0 | BF20: =SUM(BG20:BR20) -> 1600000 | BG20: 1600000 | BH20: 0 | BI20: 0 | BJ20: 0 | BK20: 0 | BL20: 0 | BM20: 0 | BN20: 0 | BO20: 0 | BP20: 0 | BQ20: 0 | BR20: 0 | BT20: =SUM(BU20:BZ20) -> 0 | BU20: 0 | BV20: 0 | BW20: 0 | BX20: 0 | BY20: 0 | BZ20: 0
A21: Cubik Construcciones Sas | B21: =SUM(C21:N21) -> 0 | C21: =SUM(E21:P21) -> 0 | D21: =SUM(F21:Q21) -> 0 | E21: =SUM(G21:R21) -> 0 | F21: =SUM(H21:S21) -> 0 | G21: =SUM(I21:T21) -> 0 | H21: =SUM(J21:U21) -> 0 | I21: =SUM(K21:V21) -> 0 | J21: =SUM(L21:W21) -> 0 | ... N21: =SUM(P21:AA21) -> 0 | P21: =SUM(Q21:AB21) -> 0 | Q21: 0 | R21: 0 | S21: 0 | T21: 0 | U21: 0 | V21: 0 | W21: 0 | X21: 0 | Y21: 0 | Z21: 0 | AA21: 0 | AB21: 0 | AD21: =SUM(AE21:AP21) -> 0 | AE21: 0 | AF21: 0 | AG21: 0 | AH21: 0 | AI21: 0 | AJ21: 0 | AK21: 0 | AL21: 0 | AM21: 0 | AN21: 0 | AO21: 0 | AP21: 0 | AR21: =SUM(AS21:BD21) -> 0 | AS21: 0 | AT21: 0 | AU21: 0 | AV21: 0 | AW21: 0 | AX21: 0 | AY21: 0 | AZ21: 0 | BA21: 0 | BB21: 0 | BC21: 0 | BD21: 0 | BF21: =SUM(BG21:BR21) -> 360000 | BG21: 0 | BH21: 0 | BI21: 0 | BJ21: 360000 | BK21: 0 | BL21: 0 | BM21: 0 | BN21: 0 | BO21: 0 | BP21: 0 | BQ21: 0 | BR21: 0 | BT21: =SUM(BU21:BZ21) -> 0 | BU21: 0 | BV21: 0 | BW21: 0 | BX21: 0 | BY21: 0 | BZ21: 0
A22: Departamento de Santander | B22: =SUM(C22:N22) -> 0 | C22: =SUM(E22:P22) -> 0 | D22: =SUM(F22:Q22) -> 0 | E22: =SUM(G22:R22) -> 0 | F22: =SUM(H22:S22) -> 0 | G22: =SUM(I22:T22) -> 0 | H22: =SUM(J22:U22) -> 0 | I22: =SUM(K22:V22) -> 0 | J22: =SUM(L22:W22) -> 0 | ... N22: =SUM(P22:AA22) -> 0 | P22: =SUM(Q22:AB22) -> 0 | Q22: 0 | R22: 0 | S22: 0 | T22: 0 | U22: 0 | V22: 0 | W22: 0 | X22: 0 | Y22: 0 | Z22: 0 | AA22: 0 | AB22: 0 | BT22: 18403361
A23: Dugoptica SAS | B23: =SUM(C23:N23) -> 0 | C23: 0 | D23: 0 | E23: 0 | F23: 0 | G23: 0 | H23: 0 | I23: 0 | J23: 0 | K23: 0 | L23: 0 | M23: 0 | N23: 0 | P23: =SUM(Q23:AB23) -> 0 | Q23: 0 | R23: 0 | S23: 0 | T23: 0 | U23: 0 | V23: 0 | W23: 0 | X23: 0 | Y23: 0 | Z23: 0 | AA23: 0 | AB23: 0 | AD23: =SUM(AE23:AP23) -> 0 | AE23: 0 | AF23: 0 | AG23: 0 | AH23: 0 | AI23: 0 | AJ23: 0 | AK23: 0 | AL23: 0 | AM23: 0 | AN23: 0 | AO23: 0 | AP23: 0 | AR23: =SUM(AS23:BD23) -> 420168 | AS23: 0 | AT23: 0 | AU23: 0 | AV23: 0 | AW23: 0 | AX23: 0 | AY23: 0 | AZ23: 0 | BA23: 0 | BB23: 0 | BC23: 0 | BD23: 420168 | BF23: =SUM(BG23:BR23) -> 840336 | BG23: 420168 | BH23: 0 | BI23: 0 | BJ23: 420168 | BK23: 0 | BL23: 0 | BM23: 0 | BN23: 0 | BO23: 0 | BP23: 0 | BQ23: 0 | BR23: 0 | BT23: =SUM(BU23:BZ23) -> 0 | BU23: 0 | BV23: 0 | BW23: 0 | BX23: 0 | BY23: 0 | BZ23: 0
A24: Edwin Leonardo Vinchery Valbuena | B24: =SUM(C24:N24) -> 0 | C24: 0 | D24: 0 | E24: 0 | F24: 0 | G24: 0 | H24: 0 | I24: 0 | J24: 0 | K24: 0 | L24: 0 | M24: 0 | N24: 0 | P24: =SUM(Q24:AB24) -> 0 | Q24: 0 | R24: 0 | S24: 0 | T24: 0 | U24: 0 | V24: 0 | W24: 0 | X24: 0 | Y24: 0 | Z24: 0 | AA24: 0 | AB24: 0 | AD24: =SUM(AE24:AP24) -> 540000 | AE24: 0 | AF24: 0 | AG24: 0 | AH24: 0 | AI24: 0 | AJ24: 0 | AK24: 0 | AL24: 0 | AM24: 0 | AN24: 540000 | AO24: 0 | AP24: 0 | AR24: =SUM(AS24:BD24) -> 0 | AS24: 0 | AT24: 0 | AU24: 0 | AV24: 0 | AW24: 0 | AX24: 0 | AY24: 0 | AZ24: 0 | BA24: 0 | BB24: 0 | BC24: 0 | BD24: 0 | BF24: =SUM(BG24:BR24) -> 0 | BG24: 0 | BH24: 0 | BI24: 0 | BJ24: 0 | BK24: 0 | BL24: 0 | BM24: 0 | BN24: 0 | BO24: 0 | BP24: 0 | BQ24: 0 | BR24: 0 | BT24: =SUM(BU24:BZ24) -> 0 | BU24: 0 | BV24: 0 | BW24: 0 | BX24: 0 | BY24: 0 | BZ24: 0
A25: Fenalco Sur De Santander | B25: =SUM(C25:N25) -> 0 | C25: 0 | D25: 0 | E25: 0 | F25: 0 | G25: 0 | H25: 0 | I25: 0 | J25: 0 | K25: 0 | L25: 0 | M25: 0 | N25: 0 | P25: =SUM(Q25:AB25) -> 0 | Q25: 0 | R25: 0 | S25: 0 | T25: 0 | U25: 0 | V25: 0 | W25: 0 | X25: 0 | Y25: 0 | Z25: 0 | AA25: 0 | AB25: 0 | AD25: =SUM(AE25:AP25) -> 2820000 | AE25: 0 | AF25: 0 | AG25: 0 | AH25: 0 | AI25: 0 | AJ25: 470000 | AK25: 0 | AL25: 940000 | AN25: 940000 | AP25: 470000 | AR25: =SUM(AS25:BD25) -> 5940000 | AS25: 470000 | AT25: 470000 | AU25: 470000 | AV25: 470000 | AW25: 470000 | AX25: 470000 | AY25: 520000 | AZ25: 520000 | BA25: 1040000 | BB25: 520000 | BC25: 0 | BD25: 520000 | BF25: =SUM(BG25:BR25) -> 3088680 | BG25: 520000 | BH25: 520000 | BI25: 520000 | BJ25: 0 | BK25: 520000 | BL25: 0 | BM25: 0 | BN25: 0 | BO25: 504800 | BP25: 503880 | BQ25: 0 | BR25: 0 | BT25: 499500 | BU25: 0 | BV25: 0 | BW25: 0 | BX25: 0 | BY25: 0 | BZ25: 0
A26: Faustino Tapias | B26: =SUM(C26:N26) -> 0 | C26: 0 | D26: 0 | E26: 0 | F26: 0 | G26: 0 | H26: 0 | I26: 0 | J26: 0 | K26: 0 | L26: 0 | M26: 0 | N26: 0 | P26: =SUM(Q26:AB26) -> 0 | Q26: 0 | R26: 0 | S26: 0 | T26: 0 | U26: 0 | V26: 0 | W26: 0 | X26: 0 | Y26: 0 | Z26: 0 | AA26: 0 | AB26: 0 | AD26: =SUM(AE26:AP26) -> 1620000 | AE26: 0 | AF26: 0 | AG26: 0 | AH26: 0 | AI26: 0 | AJ26: 0 | AK26: 0 | AL26: 0 | AM26: 540000 | AN26: 540000 | AO26: 540000 | AP26: 0 | AR26: =SUM(AS26:BD26) -> 0 | AS26: 0 | AT26: 0 | AU26: 0 | AV26: 0 | AW26: 0 | AX26: 0 | AY26: 0 | AZ26: 0 | BA26: 0 | BB26: 0 | BC26: 0 | BD26: 0 | BF26: =SUM(BG26:BR26) -> 0 | BG26: 0 | BH26: 0 | BI26: 0 | BJ26: 0 | BK26: 0 | BL26: 0 | BM26: 0 | BN26: 0 | BO26: 0 | BP26: 0 | BQ26: 0 | BR26: 0 | BT26: =SUM(BU26:BZ26) -> 0 | BU26: 0 | BV26: 0 | BW26: 0 | BX26: 0 | BY26: 0 | BZ26: 0
A27: Fundacion Medica Marie Curie S.A.S | B27: =SUM(C27:N27) -> 0 | C27: 0 | D27: 0 | E27: 0 | F27: 0 | G27: 0 | H27: 0 | I27: 0 | J27: 0 | K27: 0 | L27: 0 | M27: 0 | N27: 0 | P27: =SUM(Q27:AB27) -> 0 | Q27: 0 | R27: 0 | S27: 0 | T27: 0 | U27: 0 | V27: 0 | W27: 0 | X27: 0 | Y27: 0 | Z27: 0 | AA27: 0 | AB27: 0 | AD27: =SUM(AE27:AP27) -> 0 | AE27: 0 | AF27: 0 | AG27: 0 | AH27: 0 | AI27: 0 | AJ27: 0 | AK27: 0 | AL27: 0 | AM27: 0 | AN27: 0 | AO27: 0 | AP27: 0 | AR27: =SUM(AS27:BD27) -> 350000 | AS27: 0 | AT27: 0 | AU27: 0 | AV27: 0 | AW27: 0 | AX27: 0 | AY27: 0 | AZ27: 0 | BA27: 0 | BB27: 0 | BC27: 350000 | BD27: 0 | BF27: =SUM(BG27:BR27) -> 0 | BG27: 0 | BH27: 0 | BI27: 0 | BJ27: 0 | BK27: 0 | BL27: 0 | BM27: 0 | BN27: 0 | BO27: 0 | BP27: 0 | BQ27: 0 | BR27: 0 | BT27: =SUM(BU27:BZ27) -> 0 | BU27: 0 | BV27: 0 | BW27: 0 | BX27: 0 | BY27: 0 | BZ27: 0
A28: Gustavo Benitez Berdugo | B28: =SUM(C28:N28) -> 0 | C28: =SUM(E28:P28) -> 0 | D28: =SUM(F28:Q28) -> 0 | E28: =SUM(G28:R28) -> 0 | F28: =SUM(H28:S28) -> 0 | G28: =SUM(I28:T28) -> 0 | H28: =SUM(J28:U28) -> 0 | I28: =SUM(K28:V28) -> 0 | J28: =SUM(L28:W28) -> 0 | ... N28: =SUM(P28:AA28) -> 0 | P28: =SUM(Q28:AB28) -> 0 | Q28: 0 | R28: 0 | S28: 0 | T28: 0 | U28: 0 | V28: 0 | W28: 0 | X28: 0 | Y28: 0 | Z28: 0 | AA28: 0 | AB28: 0 | AD28: =SUM(AE28:AP28) -> 0 | AE28: 0 | AF28: 0 | AG28: 0 | AH28: 0 | AI28: 0 | AJ28: 0 | AK28: 0 | AL28: 0 | AM28: 0 | AN28: 0 | AO28: 0 | AP28: 0 | AR28: =SUM(AS28:BD28) -> 0 | AS28: 0 | AT28: 0 | AU28: 0 | AV28: 0 | AW28: 0 | AX28: 0 | AY28: 0 | AZ28: 0 | BA28: 0 | BB28: 0 | BC28: 0 | BD28: 0 | BF28: =SUM(BG28:BR28) -> 1176470 | BG28: 0 | BH28: 0 | BI28: 0 | BJ28: 588235 | BK28: 588235 | BL28: 0 | BM28: 0 | BN28: 0 | BO28: 0 | BP28: 0 | BQ28: 0 | BR28: 0 | BT28: =SUM(BU28:BZ28) -> 0 | BU28: 0 | BV28: 0 | BW28: 0 | BX28: 0 | BY28: 0 | BZ28: 0
A29: Proveedor de Telecomunicaciones S.A.S | B29: =SUM(C29:N29) -> 0 | C29: 0 | D29: 0 | E29: 0 | F29: 0 | G29: 0 | H29: 0 | I29: 0 | J29: 0 | K29: 0 | L29: 0 | M29: 0 | N29: 0 | P29: =SUM(Q29:AB29) -> 800000 | Q29: 0 | R29: 0 | S29: 0 | T29: 0 | U29: 0 | V29: 0 | W29: 0 | X29: 0 | Y29: 0 | Z29: 800000 | AA29: 0 | AB29: 0 | AD29: 0 | AR29: 0 | BF29: 0
A30: Grupo Arte | B30: =SUM(C30:N30) -> 0 | C30: 0 | D30: 0 | E30: 0 | F30: 0 | G30: 0 | H30: 0 | I30: 0 | J30: 0 | K30: 0 | L30: 0 | M30: 0 | N30: 0 | P30: =SUM(Q30:AB30) -> 800000 | Q30: 0 | R30: 0 | S30: 0 | T30: 0 | U30: 0 | V30: 0 | W30: 0 | X30: 0 | Y30: 0 | Z30: 800000 | AA30: 0 | AB30: 0 | AD30: 0 | AR30: 0 | BF30: 0
A31: Hector Armando Norriega Carrizosa | B31: =SUM(C31:N31) -> 0 | C31: =SUM(E31:P31) -> 0 | D31: =SUM(F31:Q31) -> 0 | E31: =SUM(G31:R31) -> 0 | F31: =SUM(H31:S31) -> 0 | G31: =SUM(I31:T31) -> 0 | H31: =SUM(J31:U31) -> 0 | I31: =SUM(K31:V31) -> 0 | J31: =SUM(L31:W31) -> 0 | ... N31: =SUM(P31:AA31) -> 0 | P31: =SUM(Q31:AB31) -> 0 | Q31: 0 | R31: 0 | S31: 0 | T31: 0 | U31: 0 | V31: 0 | W31: 0 | X31: 0 | Y31: 0 | Z31: 0 | AA31: 0 | AB31: 0 | AR31: 0 | BF31: =SUM(BG31:BR31) -> 1137500 | BG31: 0 | BH31: 0 | BI31: 0 | BJ31: 0 | BK31: 1137500 | BL31: 0 | BM31: 0 | BN31: 0 | BO31: 0 | BP31: 0 | BQ31: 0 | BR31: 0 | BU31: 0 | BV31: 0 | BW31: 0 | BX31: 0 | BY31: 0 | BZ31: 0
A32: Jhoan Sebastian Dueñas Gomez | B32: =SUM(C32:N32) -> 0 | C32: =SUM(E32:P32) -> 0 | D32: =SUM(F32:Q32) -> 0 | E32: =SUM(G32:R32) -> 0 | F32: =SUM(H32:S32) -> 0 | G32: =SUM(I32:T32) -> 0 | H32: =SUM(J32:U32) -> 0 | I32: =SUM(K32:V32) -> 0 | J32: =SUM(L32:W32) -> 0 | ... N32: =SUM(P32:AA32) -> 0 | P32: =SUM(Q32:AB32) -> 0 | Q32: 0 | R32: 0 | S32: 0 | T32: 0 | U32: 0 | V32: 0 | W32: 0 | X32: 0 | Y32: 0 | Z32: 0 | AA32: 0 | AB32: 0 | AD32: =SUM(AE32:AP32) -> 0 | AE32: 0 | AF32: 0 | AG32: 0 | AH32: 0 | AI32: 0 | AJ32: 0 | AK32: 0 | AL32: 0 | AM32: 0 | AN32: 0 | AO32: 0 | AP32: 0 | AR32: =SUM(AS32:BD32) -> 0 | AS32: 0 | AT32: 0 | AU32: 0 | AV32: 0 | AW32: 0 | AX32: 0 | AY32: 0 | AZ32: 0 | BA32: 0 | BB32: 0 | BC32: 0 | BD32: 0 | BF32: =SUM(BG32:BR32) -> 0 | BG32: 0 | BH32: 0 | BI32: 0 | BJ32: 0 | BK32: 0 | BL32: 0 | BM32: 0 | BN32: 0 | BO32: 0 | BP32: 0 | BQ32: 0 | BR32: 0 | BT32: =SUM(BU32:BZ32) -> 0 | BU32: 0 | BV32: 0 | BW32: 0 | BX32: 0 | BY32: 0 | BZ32: 0
A33: Jose Alberto Bastilla Hernandez | B33: =SUM(C33:N33) -> 0 | C33: 0 | D33: 0 | E33: 0 | F33: 0 | G33: 0 | H33: 0 | I33: 0 | J33: 0 | K33: 0 | L33: 0 | M33: 0 | N33: 0 | P33: =SUM(Q33:AB33) -> 2940000 | Q33: 0 | R33: 0 | S33: 0 | T33: 0 | U33: 0 | V33: 420000 | W33: 840000 | X33: 0 | Y33: 420000 | Z33: 840000 | AA33: 0 | AB33: 420000 | AD33: =SUM(AE33:AP33) -> 5040000 | AE33: 420000 | AF33: 420000 | AG33: 420000 | AH33: 420000 | AI33: 420000 | AJ33: 840000 | AK33: 0 | AL33: 840000 | AM33: 0 | AN33: 840000 | AO33: 0 | AP33: 420000 | AR33: =SUM(AS33:BD33) -> 4200000 | AS33: 420000 | AT33: 420000 | AU33: 420000 | AV33: 420000 | AW33: 420000 | AX33: 420000 | AY33: 420000 | AZ33: 420000 | BA33: 840000 | BB33: 0 | BC33: 0 | BD33: 0 | BF33: =SUM(BG33:BR33) -> 0 | BG33: 0 | BH33: 0 | BI33: 0 | BJ33: 0 | BK33: 0 | BL33: 0 | BM33: 0 | BN33: 0 | BO33: 0 | BP33: 0 | BQ33: 0 | BR33: 0 | BT33: =SUM(BU33:BZ33) -> 0 | BU33: 0 | BV33: 0 | BW33: 0 | BX33: 0 | BY33: 0 | BZ33: 0
A34: Noriega Campiño & Cia S En C | B34: =SUM(C34:N34) -> 0 | C34: 0 | D34: 0 | E34: 0 | F34: 0 | G34: 0 | H34: 0 | I34: 0 | J34: 0 | K34: 0 | L34: 0 | M34: 0 | N34: 0 | P34: =SUM(Q34:AB34) -> 4230000 | Q34: 0 | R34: 0 | S34: 0 | T34: =470000+470000 -> 940000 | U34: 0 | V34: 470000 | W34: 940000 | X34: 0 | Y34: 470000 | Z34: 940000 | AA34: 0 | AB34: 470000 | AD34: =SUM(AE34:AP34) -> 5640000 | AE34: 470000 | AF34: 470000 | AG34: 470000 | AH34: 470000 | AI34: 470000 | AJ34: 940000 | AK34: 0 | AL34: 940000 | AM34: 0 | AN34: 940000 | AO34: 0 | AP34: 470000 | AR34: =SUM(AS34:BD34) -> 7760000 | AS34: 470000 | AT34: 470000 | AU34: 470000 | AV34: 470000 | AW34: 470000 | AX34: 470000 | AY34: 940000 | AZ34: 0 | BA34: 1000000 | BB34: 1000000 | BC34: 1000000 | BD34: 1000000 | BF34: =SUM(BG34:BR34) -> 4412500 | BG34: 1000000 | BH34: 0 | BI34: 2275000 | BJ34: 0 | BK34: 1137500 | BL34: 0 | BM34: 0 | BN34: 0 | BO34: 0 | BP34: 0 | BQ34: 0 | BR34: 0 | BT34: =SUM(BU34:BZ34) -> 0 | BU34: 0 | BV34: 0 | BW34: 0 | BX34: 0 | BY34: 0 | BZ34: 0
A35: Metrogas de Colombia S.A | B35: =SUM(C35:N35) -> 0 | C35: =SUM(E35:P35) -> 0 | D35: =SUM(F35:Q35) -> 0 | E35: =SUM(G35:R35) -> 0 | F35: =SUM(H35:S35) -> 0 | G35: =SUM(I35:T35) -> 0 | H35: =SUM(J35:U35) -> 0 | I35: =SUM(K35:V35) -> 0 | J35: =SUM(L35:W35) -> 0 | ... N35: =SUM(P35:AA35) -> 0 | P35: =SUM(Q35:AB35) -> 0 | Q35: 0 | R35: 0 | S35: 0 | T35: 0 | U35: 0 | V35: 0 | W35: 0 | X35: 0 | Y35: 0 | Z35: 0 | AA35: 0 | AB35: 0 | AD35: 0 | AR35: =SUM(AS35:BD35) -> 0 | BF35: =SUM(BG35:BR35) -> 2212478 | BG35: 0 | BH35: 0 | BI35: 0 | BJ35: 0 | BK35: 0 | BL35: 0 | BM35: 0 | BN35: 1106239 | BO35: 0 | BP35: 1106239 | BU35: 0 | BV35: 0 | BW35: 0 | BX35: 0 | BY35: 0 | BZ35: 0
A36: Empresa Social del estado Hospital regional de San Gil | B36: =SUM(C36:N36) -> 55237137 | C36: 0 | D36: 0 | E36: 0 | F36: 0 | G36: 0 | H36: 0 | I36: 0 | J36: 0 | K36: 0 | L36: 0 | M36: 0 | N36: 55237137 | P36: =SUM(Q36:AB36) -> 335901628 | Q36: 30398469 | R36: 30398469 | S36: 30398469 | T36: 30398469 | U36: 30398469 | V36: 55316938 | W36: 26398469 | X36: 25548469 | Y36: 25548469 | Z36: 25548469 | AA36: 25548469 | AD36: 0
A37: Actividades de Centro de Llamadas | B37: =SUM(C37:N37) -> 0 | C37: =SUM(E37:P37) -> 0 | D37: =SUM(F37:Q37) -> 0 | E37: =SUM(G37:R37) -> 0 | F37: =SUM(H37:S37) -> 0 | G37: =SUM(I37:T37) -> 0 | H37: =SUM(J37:U37) -> 0 | I37: =SUM(K37:V37) -> 0 | J37: =SUM(L37:W37) -> 0 | ... N37: =SUM(P37:AA37) -> 0 | P37: =SUM(Q37:AB37) -> 0 | Q37: 0 | R37: 0 | S37: 0 | T37: 0 | U37: 0 | V37: 0 | W37: 0 | X37: 0 | Y37: 0 | Z37: 0 | AA37: 0 | AB37: 0 | AD37: =SUM(AE37:AP37) -> 0 | AE37: 0 | AF37: 0 | AG37: 0 | AH37: 0 | AI37: 0 | AJ37: 0 | AK37: 0 | AL37: 0 | AM37: 0 | AN37: 0 | AO37: 0 | AP37: 0 | AR37: =SUM(AS37:BD37) -> 0 | AS37: 0 | AT37: 0 | AU37: 0 | AV37: 0 | AW37: 0 | AX37: 0 | AY37: 0 | AZ37: 0 | BA37: 0 | BB37: 0 | BC37: 0 | BD37: 0 | BF37: =SUM(BG37:BR37) -> 0 | BG37: 0 | BH37: 0 | BI37: 0 | BJ37: 0 | BK37: 0 | BL37: 0 | BM37: 0 | BN37: 0 | BO37: 0 | BP37: 0 | BQ37: 0 | BR37: 0 | BT37: =SUM(BU37:BZ37) -> 0 | BU37: 0 | BV37: 0 | BW37: 0 | BX37: 0 | BY37: 0 | BZ37: 0
A38: Devoluciones | B38: =SUM(C38:N38) -> -21213878 | C38: 0 | D38: 0 | E38: 0 | F38: 0 | G38: 0 | H38: 0 | I38: 0 | J38: 0 | K38: 0 | L38: 0 | M38: 0 | N38: -21213878 | P38: =SUM(Q38:AB38) -> -28714079 | Q38: 0 | R38: 0 | S38: 0 | T38: 0 | U38: 0 | V38: -27648469 | W38: 0 | X38: 0 | Y38: -445610 | Z38: 0 | AA38: -620000 | AB38: 0 | AD38: =SUM(AE38:AP38) -> -1160000 | AE38: 0 | AF38: 0 | AG38: -620000 | AH38: 0 | AI38: 0 | AJ38: 0 | AK38: 0 | AL38: 0 | AM38: -540000 | AN38: 0 | AO38: 0 | AP38: 0 | AR38: =SUM(AS38:BD38) -> -3170000 | AU38: -1500000 | AW38: -470000 | AZ38: -200000 | BB38: -1000000 | BF38: =SUM(BG38:BR38) -> -3243739 | BG38: 0 | BH38: 0 | BI38: 0 | BJ38: 0 | BK38: -1137500 | BL38: 0 | BM38: 0 | BN38: -1106239 | BO38: -1000000 | BP38: 0 | BQ38: 0 | BR38: 0 | BT38: -11403361
A41: NO OPERACIONALES | B41: =+B42 -> 0 | C41: =+C42 -> 0 | D41: =+D42 -> 0 | E41: =+E42 -> 0 | F41: =+F42 -> 0 | G41: =+G42 -> 0 | H41: =+H42 -> 0 | I41: =+I42 -> 0 | ... N41: =+N42 -> 0 | P41: =+P42 -> 2492.75 | Q41: =+Q42 -> 0 | R41: =+R42 -> 0 | S41: =+S42 -> 0 | T41: =+T42 -> 0 | U41: =+U42 -> 0 | V41: =+V42 -> 0 | W41: =+W42 -> 0 | ... AB41: =+AB42 -> 840.75 | AD41: =SUM(AE41:AP41) -> 2182 | AE41: =SUM(AE42:AE42) -> 638 | AF41: =SUM(AF42:AF42) -> 0 | AG41: =SUM(AG42:AG42) -> 0 | AH41: =SUM(AH42:AH42) -> 879 | AI41: =SUM(AI42:AI42) -> 0 | AK41: =+AK42 -> 369 | AL41: =+AL42 -> 296 | AM41: =+AM42 -> 0 | AN41: =+AN42 -> 0 | AO41: =+AO42 -> 0 | AP41: =+AP42 -> 0 | AR41: =+AR42 -> 200 | AS41: =+AS42 -> 0 | AT41: =+AT42 -> 0 | AU41: =+AU42 -> 0 | AV41: =+AV42 -> 0 | AW41: =+AW42 -> 0 | AX41: =+AX42 -> 200 | AY41: =SUM(BI41:BL43) -> 0 | AZ41: =SUM(BJ41:BM43) -> 0 | BA41: =SUM(BK41:BN43) -> 0 | BB41: =SUM(BL41:BO43) -> 0 | BC41: =SUM(BM41:BP43) -> 0 | BD41: =SUM(BN41:BQ43) -> 0 | BF41: =SUM(BO41:BR43) -> 0 | BG41: =+BG42 -> 0 | BH41: =+BH42 -> 0 | BI41: =+BI42 -> 0 | BJ41: =+BJ42 -> 0 | BK41: =+BK42 -> 0 | BL41: =+BL42 -> 0 | BM41: =+BM42 -> 0 | BN41: =+BN42 -> 0 | ... BR41: =+BR42 -> 0 | BT41: =SUM(BW41:BZ43) -> 0 | BY41: =SUM(BY42:BY42) -> 0 | BZ41: =SUM(BZ42:BZ42) -> 0 | CB41: =SUM(CB42:CB42) -> 0
A42: Ajuste al peso | B42: =SUM(C42:N42) -> 0 | C42: 0 | D42: 0 | E42: 0 | F42: 0 | G42: 0 | H42: 0 | I42: 0 | J42: 0 | K42: 0 | L42: 0 | M42: 0 | N42: 0 | P42: =SUM(Q42:AB42) -> 2492.75 | Q42: 0 | R42: 0 | S42: 0 | T42: 0 | U42: 0 | V42: 0 | W42: 0 | X42: 839 | Y42: 813 | Z42: 0 | AA42: 0 | AB42: 840.75 | AD42: =SUM(AE42:AP42) -> 2182 | AE42: 638 | AF42: 0 | AG42: 0 | AH42: 879 | AI42: 0 | AJ42: 0 | AK42: 369 | AL42: 296 | AM42: 0 | AN42: 0 | AO42: 0 | AP42: 0 | AR42: =SUM(AS42:BD42) -> 200 | AS42: 0 | AT42: 0 | AU42: 0 | AV42: 0 | AW42: 0 | AX42: 200 | AY42: =SUM(BI42:BL43) -> 0 | AZ42: =SUM(BJ42:BM43) -> 0 | BA42: =SUM(BK42:BN43) -> 0 | BB42: =SUM(BL42:BO43) -> 0 | BC42: =SUM(BM42:BP43) -> 0 | BD42: =SUM(BN42:BQ43) -> 0 | BF42: =SUM(BO42:BR43) -> 0 | BG42: 0 | BH42: 0 | BI42: 0 | BJ42: 0 | BK42: 0 | BL42: 0 | BM42: 0 | BN42: 0 | BO42: 0 | BP42: 0 | BQ42: 0 | BR42: 0 | BT42: =SUM(BW42:BZ43) -> 0
A44: TOTAL INGRESOS | B44: =+B9+B41 -> 45023259 | C44: =+C9+C41 -> 0 | D44: =+D9+D41 -> 0 | E44: =+E9+E41 -> 0 | F44: =+F9+F41 -> 0 | G44: =+G9+G41 -> 0 | H44: =+H9+H41 -> 0 | I44: =+I9+I41 -> 0 | ... N44: =+N9+N41 -> 45023259 | P44: =+P9+P41 -> 3.7032516e+08 | Q44: =+Q9+Q41 -> 41398469 | R44: =+R9+R41 -> 42018469 | S44: =+S9+S41 -> 43654871 | T44: =+T9+T41 -> 42958469 | U44: =+U9+U41 -> 31018469 | V44: =+V9+V41 -> 29178469 | W44: =+W9+W41 -> 28798469 | ... AB44: =+AB9+AB41 -> 1510840.8 | AD44: =+AD9+AD41 -> 95611769 | AE44: =+AE9+AE41 -> 6910638 | AF44: =+AF9+AF41 -> 7309587 | AG44: =+AG9+AG41 -> 6910000 | AH44: =+AH9+AH41 -> 6910879 | AI44: =+AI9+AI41 -> 7910000 | AJ44: =+AJ9+AJ41 -> 9270000 | AK44: =+AK9+AK41 -> 7020369 | ... AP44: =+AP9+AP41 -> 8230000 | AR44: =+AR9+AR41 -> 102813214 | AS44: =+AS9+AS41 -> 8185423 | AT44: =+AT9+AT41 -> 8185423 | AU44: =+AU9+AU41 -> 11760000 | AV44: =+AV9+AV41 -> 2360000 | AW44: =+AW9+AW41 -> 5890000 | AX44: =+AX9+AX41 -> 6360200 | AY44: =+AY9+AY41 -> 7080000 | ... BD44: =+BD9+BD41 -> 2940168 | BF44: =+BF9+BF41 -> 47784225 | BG44: =+BG9+BG41 -> 6640168 | BH44: =+BH9+BH41 -> 1970000 | BI44: =+BI9+BI41 -> 3795000 | BJ44: =+BJ9+BJ41 -> 18668403 | BK44: =+BK9+BK41 -> 11595735 | BL44: =+BL9+BL41 -> 0 | BM44: =+BM9+BM41 -> 0 | ... BR44: =+BR9+BR41 -> 1000000 | BT44: =+BT9+BT41 -> 18444000 | BU44: =+BU9+BU41 -> 0 | BV44: =+BV9+BV41 -> 0 | BW44: =+BW9+BW41 -> 0 | BX44: =+BX9+BX41 -> 0 | BY44: =+BY9+BY41 -> 0 | BZ44: =+BZ9+BZ41 -> 0 | CB44: =+CB9+CB41 -> 0
A46: GASTOS DE ADMON
A48: DE PERSONAL | B48: =SUM(B49:B64) -> 28343153 | C48: =SUM(C49:C64) -> 0 | D48: =SUM(D49:D64) -> 0 | E48: =SUM(E49:E64) -> 0 | F48: =SUM(F49:F64) -> 0 | G48: =SUM(G49:G64) -> 0 | H48: =SUM(H49:H64) -> 0 | I48: =SUM(I49:I64) -> 0 | ... N48: =SUM(N49:N64) -> 28343153 | P48: =SUM(P49:P64) -> 274839697 | Q48: =SUM(Q49:Q64) -> 25704974 | R48: =SUM(R49:R64) -> 25253559 | S48: =SUM(S49:S64) -> 25200857 | T48: =SUM(T49:T64) -> 24705084 | U48: =SUM(U49:U64) -> 25034984 | V48: =SUM(V49:V64) -> 25453384 | W48: =SUM(W49:W64) -> 24717866 | ... AB48: =SUM(AB49:AB64) -> 4734864 | AD48: =SUM(AD49:AD64) -> 78133865 | AE48: =SUM(AE49:AE64) -> 4303506 | AF48: =SUM(AF49:AF64) -> 4303506 | AG48: =SUM(AG49:AG64) -> 4568899 | AH48: =SUM(AH49:AH64) -> 6292759 | AI48: =SUM(AI49:AI64) -> 6292759 | AJ48: =SUM(AJ49:AJ64) -> 6292759 | AK48: =SUM(AK49:AK64) -> 6528793 | ... AP48: =SUM(AP49:AP64) -> 6292760 | AR48: =SUM(AS48:BD48) -> 61808180 | AS48: =SUM(AS49:AS64) -> 5656536 | AT48: =SUM(AT49:AT64) -> 5587989 | AU48: =SUM(AU49:AU64) -> 5678706 | AV48: =SUM(AV49:AV64) -> 5204740 | AW48: =SUM(AW49:AW64) -> 5628594 | AX48: =SUM(AX49:AX64) -> 3793838 | AY48: =SUM(AY49:AY64) -> 4758686 | AZ48: =SUM(AZ49:AZ64) -> 3793838 | ... BD48: =SUM(BD49:BD64) -> 5232130 | BF48: =SUM(BF49:BF64) -> 44303847 | BG48: =SUM(BG49:BG66) -> 1751117.4 | BH48: =SUM(BH49:BH66) -> 7284177.5 | BI48: =SUM(BI49:BI66) -> 8335077.5 | BJ48: =SUM(BJ49:BJ66) -> 8396593.7 | BK48: =SUM(BK49:BK66) -> 5226039.7 | BL48: =SUM(BL49:BL66) -> 672313.55 | BM48: =SUM(BM49:BM66) -> 0 | BN48: =SUM(BN49:BN66) -> 0 | ... BR48: =SUM(BR49:BR66) -> 3042927.4 | BT48: =SUM(BT49:BT64) -> 17377485 | BU48: =SUM(BU49:BU66) -> 17377485 | BV48: =SUM(BV49:BV66) -> 0 | BW48: =SUM(BW49:BW66) -> 0 | BX48: =SUM(BX49:BX66) -> 0 | BY48: =SUM(BY49:BY66) -> 0 | BZ48: =SUM(BZ49:BZ66) -> 0 | CB48: =SUM(CB49:CB66) -> 0
A49: Sueldos | B49: =SUM(C49:N49) -> 17758145 | C49: 0 | D49: 0 | E49: 0 | F49: 0 | G49: 0 | H49: 0 | I49: 0 | J49: 0 | K49: 0 | L49: 0 | M49: 0 | N49: 17758145 | P49: =SUM(Q49:AB49) -> 169208484 | Q49: 15387400 | R49: 15719800 | S49: 15719800 | T49: 15719800 | U49: 15719800 | V49: 15719800 | W49: 15363734 | X49: 14956800 | Y49: 15719800 | Z49: 14045200 | AA49: 12289550 | AB49: 2847000 | AD49: =SUM(AE49:AP49) -> 48316668 | AE49: 2600000 | AF49: 2600000 | AG49: 2773334 | AH49: 3900000 | AI49: 3900000 | AJ49: 3900000 | AK49: 3943334 | AL49: 5200000 | AM49: 5200000 | AN49: 5200000 | AO49: =3988333-368333+390000+390000+800000 -> 5200000 | AP49: =3066667-466667+650000+650000 -> 3900000 | AR49: =SUM(AS49:BD49) -> 38434668 | AS49: 3480000 | AT49: 3480000 | AU49: 3480000 | AV49: 3209334 | AW49: 3480000 | AX49: 2320000 | AY49: 2938667 | AZ49: 2320000 | BA49: 2320000 | BB49: 5606667 | BC49: 2320000 | BD49: 3480000 | BF49: 28233333 | BG49: 1000000 | BH49: 5000000 | BI49: 5000000 | BJ49: 4916667 | BK49: 2950000 | BL49: 450000 | BQ49: 200000 | BR49: 2000000 | BT49: =SUM(BU49:BZ49) -> 11529800 | BU49: 11529800 | CB49: 0
A50: Apoyo sostenimiento aprendices | B50: =SUM(C50:N50) -> 0 | C50: =SUM(E50:P50) -> 0 | D50: =SUM(F50:Q50) -> 0 | E50: =SUM(G50:R50) -> 0 | F50: =SUM(H50:S50) -> 0 | G50: =SUM(I50:T50) -> 0 | H50: =SUM(J50:U50) -> 0 | I50: =SUM(K50:V50) -> 0 | J50: =SUM(L50:W50) -> 0 | ... N50: =SUM(P50:AA50) -> 0 | P50: =SUM(Q50:AB50) -> 0 | Q50: =SUM(R50:AC50) -> 0 | R50: =SUM(S50:AD50) -> 0 | S50: =SUM(T50:AE50) -> 0 | T50: =SUM(U50:AF50) -> 0 | U50: =SUM(V50:AG50) -> 0 | V50: =SUM(W50:AH50) -> 0 | W50: =SUM(X50:AI50) -> 0 | ... AB50: =SUM(AC50:AN50) -> 0 | AD50: =SUM(AE50:AP50) -> 0 | AR50: =SUM(AS50:BD50) -> 0 | AS50: 0
A51: Auxilio de transporte | B51: =SUM(C51:N51) -> 2424525 | C51: 0 | D51: 0 | E51: 0 | F51: 0 | G51: 0 | H51: 0 | I51: 0 | J51: 0 | K51: 0 | L51: 0 | M51: 0 | N51: 2424525 | P51: =SUM(Q51:AB51) -> 21953337 | Q51: 2000000 | R51: 2000000 | S51: 2000000 | T51: 2000000 | U51: 2000000 | V51: 2000000 | W51: 1953334 | X51: 1900000 | Y51: 2000000 | Z51: 1973334 | AA51: 1726669 | AB51: 400000 | AD51: =SUM(AE51:AP51) -> 6021000 | AE51: 324000 | AF51: 324000 | AG51: 345600 | AH51: 486000 | AI51: 486000 | AJ51: 486000 | AK51: 491400 | AL51: 648000 | AM51: 648000 | AN51: =569700-32400+56700+54000 -> 648000 | AO51: =515700-45900+48600+48600+81000 -> 648000 | AP51: =432000-108000+81000+81000 -> 486000 | AR51: =SUM(AS51:BD51) -> 4410342 | AS51: 424161 | AT51: 400728 | AU51: 431192 | AV51: 389010 | AW51: 421818 | AX51: 281212 | AY51: 356202 | AZ51: 281212 | BA51: 281212 | BB51: 581171 | BC51: 281212 | BD51: 281212 | BF51: 3308156.1 | BG51: 117172 | BH51: 703032 | BI51: 703032 | BJ51: 704984 | BK51: 511652 | BL51: 105456 | BQ51: 23434 | BR51: 234344 | BT51: =SUM(BU51:BZ51) -> 1355514 | BU51: 1355514 | CB51: 0
A52: Viaticos | B52: =SUM(C52:N52) -> 0 | C52: 0 | D52: 0 | E52: 0 | F52: 0 | G52: 0 | H52: 0 | I52: 0 | J52: 0 | K52: 0 | L52: 0 | M52: 0 | N52: 0 | P52: =SUM(Q52:AB52) -> 832000 | Q52: 0 | R52: 0 | S52: 0 | T52: 0 | U52: 300000 | V52: 0 | W52: 0 | X52: 150000 | Y52: 0 | Z52: 150000 | AA52: 232000 | AB52: =SUM(AC52:AN52) -> 0 | AD52: =SUM(AE52:AP52) -> 0 | AR52: =SUM(AS52:BD52) -> 0 | AY52: 0 | AZ52: 0 | BA52: 0 | BC52: 0 | BD52: 0 | BF52: 0 | BG52: 0 | BH52: 0 | BT52: =SUM(BU52:BZ52) -> 0
A53: Cesantias | B53: =SUM(C53:N53) -> 1681892 | C53: 0 | D53: 0 | E53: 0 | F53: 0 | G53: 0 | H53: 0 | I53: 0 | J53: 0 | K53: 0 | L53: 0 | M53: 0 | N53: 1681892 | P53: =SUM(Q53:AB53) -> 16086098 | Q53: 1604910 | R53: 1476648 | S53: 1476648 | T53: 1476648 | U53: 1476648 | V53: 1476648 | W53: 1443087 | X53: 1404732 | Y53: 1476648 | Z53: 1334880 | AA53: 1168017 | AB53: 270584 | AD53: =SUM(AE53:AP53) -> 4524066 | AE53: 243666 | AF53: 243666 | AG53: 259910 | AH53: 365499 | AI53: 365499 | AJ53: 365499 | AK53: 365499 | AL53: 487332 | AM53: 487332 | AN53: =341914+42641+40611+62166 -> 487332 | AO53: 487332 | AP53: =243667+121833 -> 365500 | AR53: =SUM(AS53:BD53) -> 3473521 | AS53: 326241 | AT53: 308771 | AU53: 332243 | AV53: 299741 | AW53: 325020 | AX53: 216680 | AY53: 274462 | AZ53: 216680 | BA53: 216680 | BB53: 523643 | BC53: 216680 | BD53: 216680 | BF53: 2627406.1 | BG53: 130100.94 | BH53: 500052.57 | BI53: 500052.57 | BJ53: 493273.59 | BK53: 308919.73 | BL53: 46269 | BQ53: 18612 | BR53: 186120 | BT53: =SUM(BU53:BZ53) -> 1168238 | BU53: 1168238 | CB53: 0
A54: Intereses a la cesantias | B54: =SUM(C54:N54) -> 201827 | C54: 0 | D54: 0 | E54: 0 | F54: 0 | G54: 0 | H54: 0 | I54: 0 | J54: 0 | K54: 0 | L54: 0 | M54: 0 | N54: 201827 | P54: =SUM(Q54:AB54) -> 1803232 | Q54: =173874-60862 -> 113012 | R54: 177198 | S54: =177198-47527 -> 129671 | T54: 177198 | U54: 177198 | V54: 177198 | W54: 173170 | X54: 168568 | Y54: 177198 | Z54: 160186 | AA54: 140165 | AB54: 32470 | AD54: =SUM(AE54:AP54) -> 542889 | AE54: 29240 | AF54: 29240 | AG54: 31189 | AH54: 43860 | AI54: 43860 | AJ54: 43860 | AK54: 43860 | AL54: 58480 | AM54: 58480 | AN54: =41030+5117+4873+7460 -> 58480 | AO54: =40898+4386+4386+8810 -> 58480 | AP54: =29240+14620 -> 43860 | AR54: =SUM(AS54:BD54) -> 416988 | AS54: 39165 | AT54: 37067 | AU54: 39885 | AV54: 35983 | AW54: 39018 | AX54: 26012 | AY54: 32949 | AZ54: 26012 | BA54: 26012 | BB54: 62861 | BC54: 26012 | BD54: 26012 | BF54: 315414.89 | BG54: 15618.36 | BH54: 60030.32 | BI54: 60030.32 | BJ54: 59216.518 | BK54: 37085.202 | BL54: 5554.548 | BQ54: 2234 | BR54: 22343.44 | BT54: =SUM(BU54:BZ54) -> 140245 | BU54: 140245 | CB54: 0
